Workbook
Name Formas: OFFSET('C-Das2'!$Y$6,0,0,SUM('C-Das2'!$AA$17-'C-Das2'!$AA$14),1)
Name Formas: OFFSET('[1]C-Das1'!$Y$6,0,0,SUM('[1]C-Das1'!$AA$18-'[1]C-Das1'!$AA$15),1)
Name Formas: OFFSET('C-Das1'!$Y$6,0,0,SUM('C-Das1'!$AA$18-'C-Das1'!$AA$15),1)
Name Segmento: OFFSET('[1]C-Das2'!$AB$6,0,0,SUM('[1]C-Das2'!$AD$7-'[1]C-Das2'!$AD$6),1)
Name Segmento: OFFSET('C-Das2'!$AB$6,0,0,SUM('C-Das2'!$AD$7-'C-Das2'!$AD$6),1)
Name SegmentoValor: OFFSET('[1]C-Das2'!$AC$6,0,0,COUNT('[1]C-Das2'!$AC$6:$AC$80),1)
Name SegmentoValor: OFFSET('C-Das2'!$AC$6,0,0,COUNT('C-Das2'!$AC$6:$AC$80),1)
Name ValorForma: OFFSET('C-Das2'!$Z$6,0,0,COUNT('C-Das2'!$Z$6:$Z$25),1)
Name ValorForma: OFFSET('[1]C-Das1'!$Z$6,0,0,COUNT('[1]C-Das1'!$Z$6:$Z$26),1)
Name ValorForma: OFFSET('C-Das1'!$Z$6,0,0,COUNT('C-Das1'!$Z$6:$Z$26),1)

Sheet Painel
K3: =SUM('C-Das1'!V5+'C-Das2'!V6) -> 57
L4: =TODAY() -> 46079
F5: =Q5 -> 0 | K5: =COUNTIF('Proc-G'!C7:C799,"Ativo") -> 134 | M5: Pode Esperar | N5: =COUNTIFS(Taref!$E$5:$E$6801,M5,Taref!$C$5:$C$6801,"<>Concluída") -> 0 | O5: PRAZO | P5: hoje | Q5: =COUNTIF('Proc-G'!U7:U8802,TODAY()) -> 0 | R5: =IF(Q5>0,IF(Q5=1,"Você tem 1 prazo em aberto para hoje!",CONCATENATE("Você tem ",Q5," prazos em aberto para hoje!")),"Você não tem prazos em aberto para hoje.") -> Você não tem prazos em aberto para hoje.
F6: =Q6 -> 0 | K6: =COUNTIF(Audie!G7:G800,"Agendada") -> 13 | M6: Pouco Urgente | N6: =COUNTIFS(Taref!$E$5:$E$6801,M6,Taref!$C$5:$C$6801,"<>Concluída") -> 0 | P6: 7 dias | Q6: =COUNTIFS('Proc-G'!AF7:AF9802,"<=7",'Proc-G'!AF7:AF9802,">0") -> 0 | R6: =IF(Q6>0,IF(Q6=1,"Você tem 1 prazo em aberto para os próximos 7 dias.",CONCATENATE("Você tem ",Q6," prazos em aberto para os próximos 7 dias!")),"Você não tem prazos em aberto para os próximos 7 dias.") -> Você não tem prazos em aberto para os próximos 7 dias.
M7: Requer Atenção | N7: =COUNTIFS(Taref!$E$5:$E$6801,M7,Taref!$C$5:$C$6801,"<>Concluída") -> 1
F8: =Q8 -> 0 | M8: Muito Urgente | N8: =COUNTIFS(Taref!$E$5:$E$6801,M8,Taref!$C$5:$C$6801,"<>Concluída") -> 0 | O8: audie | P8: hoje | Q8: =COUNTIF(Audie!C7:C8810,TODAY()) -> 0 | R8: =IF(Q8>0,IF(Q8=1,"Você tem 1 audiência agendada para hoje!",CONCATENATE("Você tem ",Q8," audiências agendadas para hoje!")),"Você não tem audiências agendadas para hoje.") -> Você não tem audiências agendadas para hoje.
F9: =Q9 -> 0 | M9: Exige Atenção Imediata | N9: =COUNTIFS(Taref!$E$5:$E$6801,M9,Taref!$C$5:$C$6801,"<>Concluída") -> 1 | P9: 7 dias | Q9: =COUNTIFS(Audie!D7:D8810,"<=7",Audie!D7:D8810,">0") -> 0 | R9: =IF(Q9>0,IF(Q9=1,"Você tem 1 audiência agendada para os próximos 7 dias!",CONCATENATE("Você tem ",Q9," audiências agendadas para os próximos dias!")),"Você não tem audiências agendadas para os próximos 7 dias.") -> Você não tem audiências agendadas para os próximos 7 dias.
D14: =IF('Clie-F'!I3>0,IF('Clie-F'!I3=1,"Você tem 1 cliente de aniversário hoje.",CONCATENATE("Você tem ",'Clie-F'!I3," clientes de aniversário hoje.")),"Você não tem clientes de aniversário hoje.") -> Você não tem clientes de aniversário hoje.
I15: =IF(H15<>"",COUNTIF('Proc-G'!M16:M408,Painel!H15),"")
I16: =IF(H16<>"",COUNTIF('Proc-G'!M17:M409,Painel!H16),"")
I17: =IF(H17<>"",COUNTIF('Proc-G'!M18:M410,Painel!H17),"")
I18: =IF(H18<>"",COUNTIF('Proc-G'!M19:M411,Painel!H18),"")
C19: =IF(Atend!J3>0,IF(Atend!J3=1,"Você tem que fazer contato com 1 cliente hoje.",CONCATENATE("Você tem que fazer contato com ",Atend!J3," clientes hoje.")),"Você não tem clientes para retornar o contato hoje.") -> Você não tem clientes para retornar o contato hoje. | I19: =IF(H19<>"",COUNTIF('Proc-G'!M20:M412,Painel!H19),"")
I20: =IF(H20<>"",COUNTIF('Proc-G'!M21:M413,Painel!H20),"")
I21: =IF(H21<>"",COUNTIF('Proc-G'!M22:M414,Painel!H21),"")
I22: =IF(H22<>"",COUNTIF('Proc-G'!M23:M415,Painel!H22),"")
I23: =IF(H23<>"",COUNTIF('Proc-G'!M24:M416,Painel!H23),"")
C33: =IF('Conf-G'!D23<>"",'Conf-G'!D23,"") | D33: =IF(C33<>"",COUNTIF('Proc-G'!M25:M417,Painel!C33),"")
C34: =IF('Conf-G'!D24<>"",'Conf-G'!D24,"") | D34: =IF(C34<>"",COUNTIF('Proc-G'!M26:M418,Painel!C34),"")
C35: =IF('Conf-G'!D25<>"",'Conf-G'!D25,"")
C36: =IF('Conf-G'!D26<>"",'Conf-G'!D26,"")
C37: =IF('Conf-G'!D27<>"",'Conf-G'!D27,"")

Sheet Gráfico1

Sheet Proc-G
I4: =CONCATENATE("PRAZOS PARA OS PRÓXIMOS 7 DIAS = ",COUNTIFS(AF7:AF9302,"<=7",AF7:AF9302,">0")) -> PRAZOS PARA OS PRÓXIMOS 7 DIAS = 0 | J4: =CONCATENATE("PRAZOS PARA HOJE = ", COUNTIF(U7:U9302,TODAY())) -> PRAZOS PARA HOJE = 0
B6: # | C6: Status | D6: Tipo | E6: Fase | F6: Nº do Processo | G6: Tipo de Ação | H6: Tipo de Cliente | I6: Cliente | J6: Qualificação | K6: Outro Envolvido | L6: Qualificação | M6: Advogado | N6: Valor da Causa | O6: Valor de Acordo / Sentença | P6: Valor Honorários em R$ | Q6: Valor Honorários em % | R6: Sucumbências | S6: Total em Honorários | T6: Prazo em Aberto? | U6: Data do Prazo | V6: Instância | W6: Comarca | X6: Vara | Y6: Observações | Z6: Data de Início do Processo | AA6: Data Fim do Processo | AB6: Duração | AC6: Resultado | AD6: Link do Processo | AE6: Link para Pasta de Documentos Digital | AF6: Diferença de dias (não apagar!)
B7: 1 | C7: Encerrado | D7: Judicial | E7: Fase de Sentença | F7: 1024471-68.2021.8.26.0506 | G7: Embargos à Execução | H7: Pessoa Jurídica | I7: Pepe Oficina | J7: Autor | K7: Bradesco Auto RE Companhia de Seguro | L7: Réu | M7: FERES JUNQUEIRA NAJM | N7: 62139.16 | O7: 62139.16 | S7: =IF(O7<>0,IF(P7<>0,SUM(P7+Q7*O7+O7*R7),IF(Q7<>0,SUM(P7+Q7*O7+O7*R7),"")),IF(P7<>0,SUM(P7+Q7*N7+N7*R7),IF(Q7<>0,SUM(P7+Q7*N7+N7*R7),""))) | T7: Não | V7: 1ª Instância | W7: Ribeirão Preto | X7: 2ª Vara Cível | Y7: Manifestar-se sobre o ato ordinatório sobre o processo de cancelamento do protesto perante ao Cartório | Z7: 44392 | AB7: =IFERROR(IF(Z7<>"",IF(AA7="",CONCATENATE(DATEDIF(Z7,TODAY(),"D")," dias"),CONCATENATE(DATEDIF(Z7,AA7,"D")," dias")),""),"") -> 1687 dias | AC7: Procedente | AD7: https://esaj.tjsp.jus.br/cpopg/show.do?processo.codigo=E2000LBKJ0000&processo.foro=506&processo.numero=1024471-68.2021.8.26.0506 | AF7: =DATEDIF(TODAY(),U7,"D") -> #NUM! | AG7: =IFERROR(IF(Z7<>"",IF(AA7="",DATEDIF(Z7,TODAY(),"D"),DATEDIF(Z7,AA7,"D")),""),"") -> 1687 | AI7: =IF(I7<>"",IF(F7<>"",CONCATENATE(I7," - ",G7," (",F7,")"),CONCATENATE(I7," - ",G7)),"") -> Pepe Oficina - Embargos à Execução (1024471-68.2021.8.26.0506) | AJ7: =IF(I7<>"",IF(F7<>"",CONCATENATE(I7," - ",G7," (",F7,")"),CONCATENATE(I7," - ",G7)),"") -> Pepe Oficina - Embargos à Execução (1024471-68.2021.8.26.0506)
B8: 2 | C8: Encerrado | D8: Judicial | E8: Fase de Sentença | F8: 1029547-15.2017.8.26.0506 | G8: Inventário | H8: Pessoa Física | I8: Maria Neide Ribas Silva | J8: Inventariante | K8: José Aparecido da Silva | L8: Inventariado | M8: FERES JUNQUEIRA NAJM | N8: 1000 | S8: =IF(O8<>0,IF(P8<>0,SUM(P8+Q8*O8+O8*R8),IF(Q8<>0,SUM(P8+Q8*O8+O8*R8),"")),IF(P8<>0,SUM(P8+Q8*N8+N8*R8),IF(Q8<>0,SUM(P8+Q8*N8+N8*R8),""))) | T8: Não | V8: 1ª Instância | W8: Ribeirão Preto | X8: 1ª Vara Familia e Sucessões | Y8: Saiu a Certidão de Objeto e Pé | Z8: 42907 | AA8: 44791 | AB8: =IFERROR(IF(Z8<>"",IF(AA8="",CONCATENATE(DATEDIF(Z8,TODAY(),"D")," dias"),CONCATENATE(DATEDIF(Z8,AA8,"D")," dias")),""),"") -> 1884 dias | AD8: https://esaj.tjsp.jus.br/cpopg/show.do?processo.codigo=E2000BLUQ0000&processo.foro=506&processo.numero=1029547-15.2017.8.26.0506 | AF8: =DATEDIF(TODAY(),U8,"D") -> #NUM! | AG8: =IFERROR(IF(Z8<>"",IF(AA8="",DATEDIF(Z8,TODAY(),"D"),DATEDIF(Z8,AA8,"D")),""),"") -> 1884 | AI8: =IF(I8<>"",IF(F8<>"",CONCATENATE(I8," - ",G8," (",F8,")"),CONCATENATE(I8," - ",G8)),"") -> Maria Neide Ribas Silva - Inventário (1029547-15.2017.8.26.0506) | AJ8: =IF(I8<>"",IF(F8<>"",CONCATENATE(I8," - ",G8," (",F8,")"),CONCATENATE(I8," - ",G8)),"") -> Maria Neide Ribas Silva - Inventário (1029547-15.2017.8.26.0506)
B9: 3 | C9: Encerrado | D9: Judicial | E9: Fase de Sentença | F9: 1001371-05.2019.8.26.0070 | G9: Ação Declaratória de Constitucionalidade | H9: Pessoa Física | I9: Arlene Sofiati Salgado | J9: Autor | K9: Banco ItauCard S/A | L9: Réu | M9: ADRIANO LOURENÇO MORAIS DOS SANTOS | N9: 5397.4 | O9: 5397.4 | S9: =IF(O9<>0,IF(P9<>0,SUM(P9+Q9*O9+O9*R9),IF(Q9<>0,SUM(P9+Q9*O9+O9*R9),"")),IF(P9<>0,SUM(P9+Q9*N9+N9*R9),IF(Q9<>0,SUM(P9+Q9*N9+N9*R9),""))) | T9: Não | V9: 1ª Instância | W9: Batatais | X9: 1ª Vara Cível | Y9: Aguardando a extinção do processo | Z9: 43593 | AB9: =IFERROR(IF(Z9<>"",IF(AA9="",CONCATENATE(DATEDIF(Z9,TODAY(),"D")," dias"),CONCATENATE(DATEDIF(Z9,AA9,"D")," dias")),""),"") -> 2486 dias | AC9: Procedente | AD9: https://esaj.tjsp.jus.br/cpopg/show.do?processo.codigo=1Y0001DVR0000&processo.foro=70&processo.numero=1001371-05.2019.8.26.0070 | AF9: =DATEDIF(TODAY(),U9,"D") -> #NUM! | AG9: =IFERROR(IF(Z9<>"",IF(AA9="",DATEDIF(Z9,TODAY(),"D"),DATEDIF(Z9,AA9,"D")),""),"") -> 2486 | AI9: =IF(I9<>"",IF(F9<>"",CONCATENATE(I9," - ",G9," (",F9,")"),CONCATENATE(I9," - ",G9)),"") -> Arlene Sofiati Salgado - Ação Declaratória de Constitucionalidade (1001371-05.2019.8.26.0070) | AJ9: =IF(I9<>"",IF(F9<>"",CONCATENATE(I9," - ",G9," (",F9,")"),CONCATENATE(I9," - ",G9)),"") -> Arlene Sofiati Salgado - Ação Declaratória de Constitucionalidade (1001371-05.2019.8.26.0070)
B10: 4 | C10: Ativo | D10: Judicial | E10: Fase de Sentença | F10: 1039671-28.2015.8.26.0506 | G10: Cumprimento de sentença | H10: Pessoa Física | I10: Maria Regina Dos Santos Geraldo | J10: Autor | K10: Banco do Brasil S/A | L10: Réu | M10: ADRIANO LOURENÇO MORAIS DOS SANTOS | N10: 75763.57 | S10: =IF(O10<>0,IF(P10<>0,SUM(P10+Q10*O10+O10*R10),IF(Q10<>0,SUM(P10+Q10*O10+O10*R10),"")),IF(P10<>0,SUM(P10+Q10*N10+N10*R10),IF(Q10<>0,SUM(P10+Q10*N10+N10*R10),""))) | T10: Não | V10: 1ª Instância | W10: São Paulo | X10: 1ª Vara Cível | Y10: Petição de produção de prova especificada - juntada - aguarando o despacho do Juiz | Z10: 42314 | AB10: =IFERROR(IF(Z10<>"",IF(AA10="",CONCATENATE(DATEDIF(Z10,TODAY(),"D")," dias"),CONCATENATE(DATEDIF(Z10,AA10,"D")," dias")),""),"") -> 3765 dias | AC10: Parcialmente Procedente | AD10: https://esaj.tjsp.jus.br/cpopg/show.do?processo.codigo=E20007N5Z0000&processo.foro=506&processo.numero=1039671-28.2015.8.26.0506 | AF10: =DATEDIF(TODAY(),U10,"D") -> #NUM! | AG10: =IFERROR(IF(Z10<>"",IF(AA10="",DATEDIF(Z10,TODAY(),"D"),DATEDIF(Z10,AA10,"D")),""),"") -> 3765 | AI10: =IF(I10<>"",IF(F10<>"",CONCATENATE(I10," - ",G10," (",F10,")"),CONCATENATE(I10," - ",G10)),"") -> Maria Regina Dos Santos Geraldo - Cumprimento de sentença (1039671-28.2015.8.26.0506) | AJ10: =IF(I10<>"",IF(F10<>"",CONCATENATE(I10," - ",G10," (",F10,")"),CONCATENATE(I10," - ",G10)),"") -> Maria Regina Dos Santos Geraldo - Cumprimento de sentença (1039671-28.2015.8.26.0506)
B11: 5 | C11: Encerrado | D11: Judicial | E11: Fase de Sentença | F11: 1015312-04.2021.8.26.0506 | G11: Rescisão de Contrato | H11: Pessoa Física | I11: Danielle Contin Nader | J11: Recorrido | K11: Cipreste Residencial Incorporadora Imobiliária Ltda. | L11: Recorrente | M11: FERES JUNQUEIRA NAJM | N11: 321500 | O11: 5089.12 | S11: =IF(O11<>0,IF(P11<>0,SUM(P11+Q11*O11+O11*R11),IF(Q11<>0,SUM(P11+Q11*O11+O11*R11),"")),IF(P11<>0,SUM(P11+Q11*N11+N11*R11),IF(Q11<>0,SUM(P11+Q11*N11+N11*R11),""))) | T11: Não | V11: 1ª Instância | W11: Ribeirão Preto | X11: 9ª Vara Cível | Y11: Arquivado Definitivamente - Extinto | Z11: 44319 | AA11: 45049 | AB11: =IFERROR(IF(Z11<>"",IF(AA11="",CONCATENATE(DATEDIF(Z11,TODAY(),"D")," dias"),CONCATENATE(DATEDIF(Z11,AA11,"D")," dias")),""),"") -> 730 dias | AC11: Parcialmente Procedente | AD11: https://esaj.tjsp.jus.br/cpopg/show.do?processo.codigo=E2000KWUO0000&processo.foro=506&processo.numero=1015312-04.2021.8.26.0506 | AF11: =DATEDIF(TODAY(),U11,"D") -> #NUM! | AG11: =IFERROR(IF(Z11<>"",IF(AA11="",DATEDIF(Z11,TODAY(),"D"),DATEDIF(Z11,AA11,"D")),""),"") -> 730 | AI11: =IF(I11<>"",IF(F11<>"",CONCATENATE(I11," - ",G11," (",F11,")"),CONCATENATE(I11," - ",G11)),"") -> Danielle Contin Nader - Rescisão de Contrato (1015312-04.2021.8.26.0506) | AJ11: =IF(I11<>"",IF(F11<>"",CONCATENATE(I11," - ",G11," (",F11,")"),CONCATENATE(I11," - ",G11)),"") -> Danielle Contin Nader - Rescisão de Contrato (1015312-04.2021.8.26.0506)
B12: 6 | C12: Encerrado | D12: Judicial | E12: Fase de Sentença | F12: 0004512-60.2023.8.26.0506 | G12: Cumprimento de sentença | H12: Pessoa Física | I12: Danielle Contin Nader | J12: Executante | K12: Cipreste Residencial Incorporadora Imobiliária Ltda. | L12: Executado | M12: FERES JUNQUEIRA NAJM | N12: 5089.12 | S12: =IF(O12<>0,IF(P12<>0,SUM(P12+Q12*O12+O12*R12),IF(Q12<>0,SUM(P12+Q12*O12+O12*R12),"")),IF(P12<>0,SUM(P12+Q12*N12+N12*R12),IF(Q12<>0,SUM(P12+Q12*N12+N12*R12),""))) | T12: Não | V12: 1ª Instância | W12: Ribeirão Preto | X12: 9ª Vara Cível | Y12: A outra parte juntou guia de pagamento de parte das custas | Z12: 44999 | AB12: =IFERROR(IF(Z12<>"",IF(AA12="",CONCATENATE(DATEDIF(Z12,TODAY(),"D")," dias"),CONCATENATE(DATEDIF(Z12,AA12,"D")," dias")),""),"") -> 1080 dias | AD12: https://esaj.tjsp.jus.br/cpopg/show.do?processo.codigo=E2000P7HZ0000&processo.foro=506&processo.numero=0004512-60.2023.8.26.0506 | AF12: =DATEDIF(TODAY(),U12,"D") -> #NUM! | AG12: =IFERROR(IF(Z12<>"",IF(AA12="",DATEDIF(Z12,TODAY(),"D"),DATEDIF(Z12,AA12,"D")),""),"") -> 1080 | AI12: =IF(I12<>"",IF(F12<>"",CONCATENATE(I12," - ",G12," (",F12,")"),CONCATENATE(I12," - ",G12)),"") -> Danielle Contin Nader - Cumprimento de sentença (0004512-60.2023.8.26.0506) | AJ12: =IF(I12<>"",IF(F12<>"",CONCATENATE(I12," - ",G12," (",F12,")"),CONCATENATE(I12," - ",G12)),"") -> Danielle Contin Nader - Cumprimento de sentença (0004512-60.2023.8.26.0506)
B13: 7 | C13: Encerrado | D13: Judicial | E13: Fase de Sentença | F13: 1015179-59.2021.8.26.0506 | G13: Fornecimento de Medicamento | H13: Pessoa Física | I13: Julio Cesar Borges | J13: Autor | K13: Ribeirão Preto/Estado/União | L13: Réu | M13: FERES JUNQUEIRA NAJM | N13: 368338.03 | S13: =IF(O13<>0,IF(P13<>0,SUM(P13+Q13*O13+O13*R13),IF(Q13<>0,SUM(P13+Q13*O13+O13*R13),"")),IF(P13<>0,SUM(P13+Q13*N13+N13*R13),IF(Q13<>0,SUM(P13+Q13*N13+N13*R13),""))) | T13: Não | V13: 1ª Instância | W13: Ribeirão Preto | X13: 1ª Vara da Fazenda | Y13: Encaminhado para a Justiça Federal | Z13: 44316 | AB13: =IFERROR(IF(Z13<>"",IF(AA13="",CONCATENATE(DATEDIF(Z13,TODAY(),"D")," dias"),CONCATENATE(DATEDIF(Z13,AA13,"D")," dias")),""),"") -> 1763 dias | AD13: https://esaj.tjsp.jus.br/cpopg/show.do?processo.codigo=E2000KWK90000&processo.foro=506&processo.numero=1015179-59.2021.8.26.0506 | AF13: =DATEDIF(TODAY(),U13,"D") -> #NUM! | AG13: =IFERROR(IF(Z13<>"",IF(AA13="",DATEDIF(Z13,TODAY(),"D"),DATEDIF(Z13,AA13,"D")),""),"") -> 1763 | AI13: =IF(I13<>"",IF(F13<>"",CONCATENATE(I13," - ",G13," (",F13,")"),CONCATENATE(I13," - ",G13)),"") -> Julio Cesar Borges - Fornecimento de Medicamento (1015179-59.2021.8.26.0506) | AJ13: =IF(I13<>"",IF(F13<>"",CONCATENATE(I13," - ",G13," (",F13,")"),CONCATENATE(I13," - ",G13)),"") -> Julio Cesar Borges - Fornecimento de Medicamento (1015179-59.2021.8.26.0506)
B14: 8 | C14: Encerrado | D14: Judicial | E14: Fase de Sentença | F14: 1025487-17.2021.8.26.0196 | G14: Ação Indenizatória | H14: Pessoa Jurídica | I14: Supermercados Big Compra Ltda. | J14: Requerido | K14: Angélica Cardoso de Oliveira Olaia | L14: Requerente | M14: FERES JUNQUEIRA NAJM | N14: 1000 | S14: =IF(O14<>0,IF(P14<>0,SUM(P14+Q14*O14+O14*R14),IF(Q14<>0,SUM(P14+Q14*O14+O14*R14),"")),IF(P14<>0,SUM(P14+Q14*N14+N14*R14),IF(Q14<>0,SUM(P14+Q14*N14+N14*R14),""))) | T14: Não | V14: 1ª Instância | W14: Franca | X14: 5ª Vara Cível | Y14: Aguardando Extinção do Processo | Z14: 44459 | AB14: =IFERROR(IF(Z14<>"",IF(AA14="",CONCATENATE(DATEDIF(Z14,TODAY(),"D")," dias"),CONCATENATE(DATEDIF(Z14,AA14,"D")," dias")),""),"") -> 1620 dias | AC14: Acordo | AD14: https://esaj.tjsp.jus.br/cpopg/show.do?processo.codigo=5G000C88A0000&processo.foro=196&processo.numero=1025487-17.2021.8.26.0196 | AF14: =DATEDIF(TODAY(),U14,"D") -> #NUM! | AG14: =IFERROR(IF(Z14<>"",IF(AA14="",DATEDIF(Z14,TODAY(),"D"),DATEDIF(Z14,AA14,"D")),""),"") -> 1620 | AI14: =IF(I14<>"",IF(F14<>"",CONCATENATE(I14," - ",G14," (",F14,")"),CONCATENATE(I14," - ",G14)),"") -> Supermercados Big Compra Ltda. - Ação Indenizatória (1025487-17.2021.8.26.0196) | AJ14: =IF(I14<>"",IF(F14<>"",CONCATENATE(I14," - ",G14," (",F14,")"),CONCATENATE(I14," - ",G14)),"") -> Supermercados Big Compra Ltda. - Ação Indenizatória (1025487-17.2021.8.26.0196)
B15: 9 | C15: Encerrado | D15: Judicial | E15: Fase Recursal | F15: 1026606-13.2021.8.26.0196 | G15: Ação Indenizatória | H15: Pessoa Jurídica | I15: Supermercados Big Compra Ltda. | J15: Requerido | K15: Joel Fonseca da Cunha | L15: Requerente | M15: FERES JUNQUEIRA NAJM | N15: 50000 | S15: =IF(O15<>0,IF(P15<>0,SUM(P15+Q15*O15+O15*R15),IF(Q15<>0,SUM(P15+Q15*O15+O15*R15),"")),IF(P15<>0,SUM(P15+Q15*N15+N15*R15),IF(Q15<>0,SUM(P15+Q15*N15+N15*R15),""))) | T15: Não | V15: Tribunal de Justiça - São Paulo | W15: Franca | X15: 1ª Vara Cível | Y15: Baixa definitiva | Z15: 44469 | AA15: 45359 | AB15: =IFERROR(IF(Z15<>"",IF(AA15="",CONCATENATE(DATEDIF(Z15,TODAY(),"D")," dias"),CONCATENATE(DATEDIF(Z15,AA15,"D")," dias")),""),"") -> 890 dias | AC15: Improcedente | AD15: https://esaj.tjsp.jus.br/cpopg/show.do?processo.codigo=5G000C9VM0000&processo.foro=196&processo.numero=1026606-13.2021.8.26.0196 | AF15: =DATEDIF(TODAY(),U15,"D") -> #NUM! | AG15: =IFERROR(IF(Z15<>"",IF(AA15="",DATEDIF(Z15,TODAY(),"D"),DATEDIF(Z15,AA15,"D")),""),"") -> 890 | AI15: =IF(I15<>"",IF(F15<>"",CONCATENATE(I15," - ",G15," (",F15,")"),CONCATENATE(I15," - ",G15)),"") -> Supermercados Big Compra Ltda. - Ação Indenizatória (1026606-13.2021.8.26.0196) | AJ15: =IF(I15<>"",IF(F15<>"",CONCATENATE(I15," - ",G15," (",F15,")"),CONCATENATE(I15," - ",G15)),"") -> Supermercados Big Compra Ltda. - Ação Indenizatória (1026606-13.2021.8.26.0196)
B16: 10 | C16: Encerrado | D16: Judicial | E16: Fase Recursal | F16: 1032968-71.2021.8.26.0506 | G16: Ação Indenizatória | H16: Pessoa Jurídica | I16: Supermercados Big Compra Ltda. | J16: Requerido | K16: Edielton de Sousa Vieira | L16: Requerente | M16: FERES JUNQUEIRA NAJM | N16: 20000 | S16: =IF(O16<>0,IF(P16<>0,SUM(P16+Q16*O16+O16*R16),IF(Q16<>0,SUM(P16+Q16*O16+O16*R16),"")),IF(P16<>0,SUM(P16+Q16*N16+N16*R16),IF(Q16<>0,SUM(P16+Q16*N16+N16*R16),""))) | T16: Não | V16: 1ª Instância | W16: Ribeirão Preto | X16: 2ª Vara Cível | Y16: Autos Redistribuídos para outra Seção do Tribunal de Justiça do Estado de São Paulo | Z16: 44456 | AB16: =IFERROR(IF(Z16<>"",IF(AA16="",CONCATENATE(DATEDIF(Z16,TODAY(),"D")," dias"),CONCATENATE(DATEDIF(Z16,AA16,"D")," dias")),""),"") -> 1623 dias | AD16: https://esaj.tjsp.jus.br/cpopg/show.do?processo.codigo=E2000LPHG0000&processo.foro=506&processo.numero=1032968-71.2021.8.26.0506 | AF16: =DATEDIF(TODAY(),U16,"D") -> #NUM! | AG16: =IFERROR(IF(Z16<>"",IF(AA16="",DATEDIF(Z16,TODAY(),"D"),DATEDIF(Z16,AA16,"D")),""),"") -> 1623 | AI16: =IF(I16<>"",IF(F16<>"",CONCATENATE(I16," - ",G16," (",F16,")"),CONCATENATE(I16," - ",G16)),"") -> Supermercados Big Compra Ltda. - Ação Indenizatória (1032968-71.2021.8.26.0506) | AJ16: =IF(I16<>"",IF(F16<>"",CONCATENATE(I16," - ",G16," (",F16,")"),CONCATENATE(I16," - ",G16)),"") -> Supermercados Big Compra Ltda. - Ação Indenizatória (1032968-71.2021.8.26.0506)
B17: 11 | C17: Ativo | D17: Judicial | E17: Fase Inicial | F17: 1041082-96.2021.8.26.0506 | G17: Declaração de Inexistência de Débito | H17: Pessoa Jurídica | I17: Brilho Auto Center | J17: Requerente | K17: Associação Imperial Paulista Proteção Automotiva | L17: Requerido | M17: FERES JUNQUEIRA NAJM | N17: 20332 | S17: =IF(O17<>0,IF(P17<>0,SUM(P17+Q17*O17+O17*R17),IF(Q17<>0,SUM(P17+Q17*O17+O17*R17),"")),IF(P17<>0,SUM(P17+Q17*N17+N17*R17),IF(Q17<>0,SUM(P17+Q17*N17+N17*R17),""))) | T17: Não | V17: 1ª Instância | W17: Ribeirão Preto | X17: 3ª Vara Cível | Y17: Foi juntada guia de pagamento de custas após tentativa de encontrar réu | Z17: 44497 | AB17: =IFERROR(IF(Z17<>"",IF(AA17="",CONCATENATE(DATEDIF(Z17,TODAY(),"D")," dias"),CONCATENATE(DATEDIF(Z17,AA17,"D")," dias")),""),"") -> 1582 dias | AD17: https://esaj.tjsp.jus.br/cpopg/show.do?processo.codigo=E2000M0HD0000&processo.foro=506&processo.numero=1041082-96.2021.8.26.0506 | AF17: =DATEDIF(TODAY(),U17,"D") -> #NUM! | AG17: =IFERROR(IF(Z17<>"",IF(AA17="",DATEDIF(Z17,TODAY(),"D"),DATEDIF(Z17,AA17,"D")),""),"") -> 1582 | AI17: =IF(I17<>"",IF(F17<>"",CONCATENATE(I17," - ",G17," (",F17,")"),CONCATENATE(I17," - ",G17)),"") -> Brilho Auto Center - Declaração de Inexistência de Débito (1041082-96.2021.8.26.0506) | AJ17: =IF(I17<>"",IF(F17<>"",CONCATENATE(I17," - ",G17," (",F17,")"),CONCATENATE(I17," - ",G17)),"") -> Brilho Auto Center - Declaração de Inexistência de Débito (1041082-96.2021.8.26.0506)
B18: 12 | C18: Encerrado | D18: Judicial | E18: Fase Inicial | F18: 1046715-88.2021.8.26.0506 | G18: Ação Indenizatória | H18: Pessoa Física | I18: Giuseppe Bonjovani de Paiva | J18: Requerente | K18: Azul Companhia de Seguros Gerais | L18: Requerido | M18: FERES JUNQUEIRA NAJM | N18: 43486 | S18: =IF(O18<>0,IF(P18<>0,SUM(P18+Q18*O18+O18*R18),IF(Q18<>0,SUM(P18+Q18*O18+O18*R18),"")),IF(P18<>0,SUM(P18+Q18*N18+N18*R18),IF(Q18<>0,SUM(P18+Q18*N18+N18*R18),""))) | T18: Não | V18: 1ª Instância | W18: Ribeirão Preto | X18: 3ª Vara Cível | Y18: Verificar constância de pagamentos do autor. Foi feito o pedido de homologação de acordo | Z18: 44533 | AB18: =IFERROR(IF(Z18<>"",IF(AA18="",CONCATENATE(DATEDIF(Z18,TODAY(),"D")," dias"),CONCATENATE(DATEDIF(Z18,AA18,"D")," dias")),""),"") -> 1546 dias | AD18: https://esaj.tjsp.jus.br/cpopg/show.do?processo.codigo=E2000M8N30000&processo.foro=506&processo.numero=1046715-88.2021.8.26.0506 | AF18: =DATEDIF(TODAY(),U18,"D") -> #NUM! | AG18: =IFERROR(IF(Z18<>"",IF(AA18="",DATEDIF(Z18,TODAY(),"D"),DATEDIF(Z18,AA18,"D")),""),"") -> 1546 | AI18: =IF(I18<>"",IF(F18<>"",CONCATENATE(I18," - ",G18," (",F18,")"),CONCATENATE(I18," - ",G18)),"") -> Giuseppe Bonjovani de Paiva - Ação Indenizatória (1046715-88.2021.8.26.0506) | AJ18: =IF(I18<>"",IF(F18<>"",CONCATENATE(I18," - ",G18," (",F18,")"),CONCATENATE(I18," - ",G18)),"") -> Giuseppe Bonjovani de Paiva - Ação Indenizatória (1046715-88.2021.8.26.0506)
B19: 13 | C19: Encerrado | D19: Judicial | E19: Fase de Execução | F19: 1032652-18.2021.8.26.0196 | G19: Ação de Título de Crédito | H19: Pessoa Jurídica | I19: Supermercados Big Compra Ltda. | J19: Requerente | K19: LS Interbank Fundo de Investimento | L19: Requerido | M19: FERES JUNQUEIRA NAJM | N19: 30354.54 | S19: =IF(O19<>0,IF(P19<>0,SUM(P19+Q19*O19+O19*R19),IF(Q19<>0,SUM(P19+Q19*O19+O19*R19),"")),IF(P19<>0,SUM(P19+Q19*N19+N19*R19),IF(Q19<>0,SUM(P19+Q19*N19+N19*R19),""))) | T19: Não | V19: 1ª Instância | W19: Franca | X19: 5ª Vara Cível | Y19: Extinto | Z19: 44544 | AA19: 45000 | AB19: =IFERROR(IF(Z19<>"",IF(AA19="",CONCATENATE(DATEDIF(Z19,TODAY(),"D")," dias"),CONCATENATE(DATEDIF(Z19,AA19,"D")," dias")),""),"") -> 456 dias | AC19: Extinto | AD19: https://esaj.tjsp.jus.br/cpopg/show.do?processo.codigo=5G000CL6A0000&processo.foro=196&processo.numero=1032652-18.2021.8.26.0196 | AF19: =DATEDIF(TODAY(),U19,"D") -> #NUM! | AG19: =IFERROR(IF(Z19<>"",IF(AA19="",DATEDIF(Z19,TODAY(),"D"),DATEDIF(Z19,AA19,"D")),""),"") -> 456 | AI19: =IF(I19<>"",IF(F19<>"",CONCATENATE(I19," - ",G19," (",F19,")"),CONCATENATE(I19," - ",G19)),"") -> Supermercados Big Compra Ltda. - Ação de Título de Crédito (1032652-18.2021.8.26.0196) | AJ19: =IF(I19<>"",IF(F19<>"",CONCATENATE(I19," - ",G19," (",F19,")"),CONCATENATE(I19," - ",G19)),"") -> Supermercados Big Compra Ltda. - Ação de Título de Crédito (1032652-18.2021.8.26.0196)
B20: 14 | C20: Encerrado | D20: Judicial | E20: Fase de Sentença | F20: 1003841-84.2021.8.26.0572 | G20: Ação de Título de Crédito | H20: Pessoa Jurídica | I20: Supermercados Big Compra Ltda. | J20: Requerente | K20: LS Interbank Fundo de Investimento | L20: Requerido | M20: FERES JUNQUEIRA NAJM | N20: 55192.01 | S20: =IF(O20<>0,IF(P20<>0,SUM(P20+Q20*O20+O20*R20),IF(Q20<>0,SUM(P20+Q20*O20+O20*R20),"")),IF(P20<>0,SUM(P20+Q20*N20+N20*R20),IF(Q20<>0,SUM(P20+Q20*N20+N20*R20),""))) | T20: Não | V20: 1ª Instância | W20: Sã Joaquim da Barra | X20: 1ª Vara Cível | Y20: Processo já transitou em julgado - pronto para realizar o cumprimento de sentença | Z20: 44540 | AA20: 45084 | AB20: =IFERROR(IF(Z20<>"",IF(AA20="",CONCATENATE(DATEDIF(Z20,TODAY(),"D")," dias"),CONCATENATE(DATEDIF(Z20,AA20,"D")," dias")),""),"") -> 544 dias | AC20: Extinto | AD20: https://esaj.tjsp.jus.br/cpopg/show.do?processo.codigo=FW0002JBM0000&processo.foro=572&processo.numero=1003841-84.2021.8.26.0572 | AF20: =DATEDIF(TODAY(),U20,"D") -> #NUM! | AG20: =IFERROR(IF(Z20<>"",IF(AA20="",DATEDIF(Z20,TODAY(),"D"),DATEDIF(Z20,AA20,"D")),""),"") -> 544 | AI20: =IF(I20<>"",IF(F20<>"",CONCATENATE(I20," - ",G20," (",F20,")"),CONCATENATE(I20," - ",G20)),"") -> Supermercados Big Compra Ltda. - Ação de Título de Crédito (1003841-84.2021.8.26.0572) | AJ20: =IF(I20<>"",IF(F20<>"",CONCATENATE(I20," - ",G20," (",F20,")"),CONCATENATE(I20," - ",G20)),"") -> Supermercados Big Compra Ltda. - Ação de Título de Crédito (1003841-84.2021.8.26.0572)
B21: 15 | C21: Encerrado | D21: Judicial | E21: Fase de Sentença | F21: 1000128-71.2022.8.26.0506 | G21: Ação Declaratória de Constitucionalidade | H21: Pessoa Jurídica | I21: Supermercados Big Compra Ltda. | J21: Requerido | K21: Silvana Quirino de Sousa | L21: Requerido | M21: FERES JUNQUEIRA NAJM | N21: 51432.62 | S21: =IF(O21<>0,IF(P21<>0,SUM(P21+Q21*O21+O21*R21),IF(Q21<>0,SUM(P21+Q21*O21+O21*R21),"")),IF(P21<>0,SUM(P21+Q21*N21+N21*R21),IF(Q21<>0,SUM(P21+Q21*N21+N21*R21),""))) | T21: Não | V21: 1ª Instância | W21: Ribeirão Preto | X21: 7ª Vara Cível | Y21: Aguardando o arquivamento e extinção | Z21: 44566 | AB21: =IFERROR(IF(Z21<>"",IF(AA21="",CONCATENATE(DATEDIF(Z21,TODAY(),"D")," dias"),CONCATENATE(DATEDIF(Z21,AA21,"D")," dias")),""),"") -> 1513 dias | AC21: Acordo | AD21: https://esaj.tjsp.jus.br/cpopg/show.do?processo.codigo=E2000MEVC0000&processo.foro=506&processo.numero=1000128-71.2022.8.26.0506 | AF21: =DATEDIF(TODAY(),U21,"D") -> #NUM! | AG21: =IFERROR(IF(Z21<>"",IF(AA21="",DATEDIF(Z21,TODAY(),"D"),DATEDIF(Z21,AA21,"D")),""),"") -> 1513 | AI21: =IF(I21<>"",IF(F21<>"",CONCATENATE(I21," - ",G21," (",F21,")"),CONCATENATE(I21," - ",G21)),"") -> Supermercados Big Compra Ltda. - Ação Declaratória de Constitucionalidade (1000128-71.2022.8.26.0506) | AJ21: =IF(I21<>"",IF(F21<>"",CONCATENATE(I21," - ",G21," (",F21,")"),CONCATENATE(I21," - ",G21)),"") -> Supermercados Big Compra Ltda. - Ação Declaratória de Constitucionalidade (1000128-71.2022.8.26.0506)
B22: 16 | C22: Encerrado | D22: Judicial | E22: Fase Recursal | F22: 1002154-72.2021.8.26.0572 | G22: Declaração de Inexistência de Débito | H22: Pessoa Jurídica | I22: Supermercados Big Compra Ltda. | J22: Requerido | K22: Patricia Alves dos Santos | L22: Requerente | M22: FERES JUNQUEIRA NAJM | N22: 15000 | S22: =IF(O22<>0,IF(P22<>0,SUM(P22+Q22*O22+O22*R22),IF(Q22<>0,SUM(P22+Q22*O22+O22*R22),"")),IF(P22<>0,SUM(P22+Q22*N22+N22*R22),IF(Q22<>0,SUM(P22+Q22*N22+N22*R22),""))) | T22: Não | V22: Tribunal de Justiça - São Paulo | W22: São Paulo | X22: 19ª Câmara Direito Privado | Y22: Aguardando o despacho do Juiz - OMNI é quem iria pagar | Z22: 44392 | AB22: =IFERROR(IF(Z22<>"",IF(AA22="",CONCATENATE(DATEDIF(Z22,TODAY(),"D")," dias"),CONCATENATE(DATEDIF(Z22,AA22,"D")," dias")),""),"") -> 1687 dias | AD22: https://esaj.tjsp.jus.br/cpopg/show.do?processo.codigo=FW0002GIO0000&processo.foro=572&processo.numero=1002154-72.2021.8.26.0572 | AF22: =DATEDIF(TODAY(),U22,"D") -> #NUM! | AG22: =IFERROR(IF(Z22<>"",IF(AA22="",DATEDIF(Z22,TODAY(),"D"),DATEDIF(Z22,AA22,"D")),""),"") -> 1687 | AI22: =IF(I22<>"",IF(F22<>"",CONCATENATE(I22," - ",G22," (",F22,")"),CONCATENATE(I22," - ",G22)),"") -> Supermercados Big Compra Ltda. - Declaração de Inexistência de Débito (1002154-72.2021.8.26.0572) | AJ22: =IF(I22<>"",IF(F22<>"",CONCATENATE(I22," - ",G22," (",F22,")"),CONCATENATE(I22," - ",G22)),"") -> Supermercados Big Compra Ltda. - Declaração de Inexistência de Débito (1002154-72.2021.8.26.0572)
B23: 17 | C23: Ativo | D23: Judicial | E23: Fase de Sentença | F23: 1016717-41.2022.8.26.0506 | G23: Declaração de Inexistência de Débito | H23: Pessoa Física | I23: Edson José Marques | J23: Requerente | K23: Banco Estado do Rio Grande do Sul S/A (Banrisul) | L23: Requerido | M23: FERES JUNQUEIRA NAJM | N23: 20063.69 | S23: =IF(O23<>0,IF(P23<>0,SUM(P23+Q23*O23+O23*R23),IF(Q23<>0,SUM(P23+Q23*O23+O23*R23),"")),IF(P23<>0,SUM(P23+Q23*N23+N23*R23),IF(Q23<>0,SUM(P23+Q23*N23+N23*R23),""))) | T23: Sim | V23: 1ª Instância | W23: Ribeirão Preto | X23: 8ª Vara Cível | Y23: Foi emitido despecho para serem feitas as alegações finais. | Z23: 44679 | AB23: =IFERROR(IF(Z23<>"",IF(AA23="",CONCATENATE(DATEDIF(Z23,TODAY(),"D")," dias"),CONCATENATE(DATEDIF(Z23,AA23,"D")," dias")),""),"") -> 1400 dias | AD23: https://esaj.tjsp.jus.br/cpopg/show.do?processo.codigo=E2000N56Z0000&processo.foro=506&processo.numero=1016717-41.2022.8.26.0506 | AF23: =DATEDIF(TODAY(),U23,"D") -> #NUM! | AG23: =IFERROR(IF(Z23<>"",IF(AA23="",DATEDIF(Z23,TODAY(),"D"),DATEDIF(Z23,AA23,"D")),""),"") -> 1400 | AI23: =IF(I23<>"",IF(F23<>"",CONCATENATE(I23," - ",G23," (",F23,")"),CONCATENATE(I23," - ",G23)),"") -> Edson José Marques - Declaração de Inexistência de Débito (1016717-41.2022.8.26.0506) | AJ23: =IF(I23<>"",IF(F23<>"",CONCATENATE(I23," - ",G23," (",F23,")"),CONCATENATE(I23," - ",G23)),"") -> Edson José Marques - Declaração de Inexistência de Débito (1016717-41.2022.8.26.0506)
B24: 18 | C24: Ativo | D24: Judicial | E24: Fase de Contestação | F24: 1017163-44.2022.8.26.0506 | G24: Declaração de Inexistência de Débito | H24: Pessoa Física | I24: Fernando José Pereira | J24: Requerente | K24: Banco C6 Consignado S/A | L24: Requerido | M24: FERES JUNQUEIRA NAJM | N24: 27993.22 | S24: =IF(O24<>0,IF(P24<>0,SUM(P24+Q24*O24+O24*R24),IF(Q24<>0,SUM(P24+Q24*O24+O24*R24),"")),IF(P24<>0,SUM(P24+Q24*N24+N24*R24),IF(Q24<>0,SUM(P24+Q24*N24+N24*R24),""))) | T24: Não | V24: 1ª Instância | W24: Ribeirão Preto | X24: 2ª Vara Cível | Y24: Foi feito o pedido para levantamento dos valores em depósito judicial | Z24: 44683 | AB24: =IFERROR(IF(Z24<>"",IF(AA24="",CONCATENATE(DATEDIF(Z24,TODAY(),"D")," dias"),CONCATENATE(DATEDIF(Z24,AA24,"D")," dias")),""),"") -> 1396 dias | AD24: https://esaj.tjsp.jus.br/cpopg/show.do?processo.codigo=E2000N5U80000&processo.foro=506&processo.numero=1017163-44.2022.8.26.0506 | AF24: =DATEDIF(TODAY(),U24,"D") -> #NUM! | AG24: =IFERROR(IF(Z24<>"",IF(AA24="",DATEDIF(Z24,TODAY(),"D"),DATEDIF(Z24,AA24,"D")),""),"") -> 1396 | AI24: =IF(I24<>"",IF(F24<>"",CONCATENATE(I24," - ",G24," (",F24,")"),CONCATENATE(I24," - ",G24)),"") -> Fernando José Pereira - Declaração de Inexistência de Débito (1017163-44.2022.8.26.0506) | AJ24: =IF(I24<>"",IF(F24<>"",CONCATENATE(I24," - ",G24," (",F24,")"),CONCATENATE(I24," - ",G24)),"") -> Fernando José Pereira - Declaração de Inexistência de Débito (1017163-44.2022.8.26.0506)
B25: 19 | C25: Encerrado | D25: Judicial | E25: Fase de Sentença | F25: 1001052-78.2022.8.26.0572 | G25: Ação Indenizatória | H25: Pessoa Jurídica | I25: Supermercados Big Compra Ltda. | J25: Requerido | K25: Manoel Jeronimo da Silva Neto | L25: Requerente | M25: FERES JUNQUEIRA NAJM | N25: 248000 | O25: 114000 | S25: =IF(O25<>0,IF(P25<>0,SUM(P25+Q25*O25+O25*R25),IF(Q25<>0,SUM(P25+Q25*O25+O25*R25),"")),IF(P25<>0,SUM(P25+Q25*N25+N25*R25),IF(Q25<>0,SUM(P25+Q25*N25+N25*R25),""))) | T25: Não | V25: 1ª Instância | W25: São Joaquim da Barra | X25: 2ª Vara Cível | Y25: Aguardando Homologar o Acordo | Z25: 44662 | AA25: 45091 | AB25: =IFERROR(IF(Z25<>"",IF(AA25="",CONCATENATE(DATEDIF(Z25,TODAY(),"D")," dias"),CONCATENATE(DATEDIF(Z25,AA25,"D")," dias")),""),"") -> 429 dias | AD25: https://esaj.tjsp.jus.br/cpopg/show.do?processo.codigo=FW0002LQ20000&processo.foro=572&processo.numero=1001052-78.2022.8.26.0572 | AF25: =DATEDIF(TODAY(),U25,"D") -> #NUM! | AG25: =IFERROR(IF(Z25<>"",IF(AA25="",DATEDIF(Z25,TODAY(),"D"),DATEDIF(Z25,AA25,"D")),""),"") -> 429 | AI25: =IF(I25<>"",IF(F25<>"",CONCATENATE(I25," - ",G25," (",F25,")"),CONCATENATE(I25," - ",G25)),"") -> Supermercados Big Compra Ltda. - Ação Indenizatória (1001052-78.2022.8.26.0572) | AJ25: =IF(I25<>"",IF(F25<>"",CONCATENATE(I25," - ",G25," (",F25,")"),CONCATENATE(I25," - ",G25)),"") -> Supermercados Big Compra Ltda. - Ação Indenizatória (1001052-78.2022.8.26.0572)
B26: 20 | C26: Encerrado | D26: Judicial | E26: Fase de Sentença | F26: 1021378-63.2022.8.26.0506 | G26: Seguro / Remoção / Vaga Técnica | H26: Pessoa Jurídica | I26: Leco Car | J26: Requerente | K26: HDI Seguros S/A | L26: Requerido | M26: FERES JUNQUEIRA NAJM | N26: 1000 | S26: =IF(O26<>0,IF(P26<>0,SUM(P26+Q26*O26+O26*R26),IF(Q26<>0,SUM(P26+Q26*O26+O26*R26),"")),IF(P26<>0,SUM(P26+Q26*N26+N26*R26),IF(Q26<>0,SUM(P26+Q26*N26+N26*R26),""))) | T26: Não | V26: 1ª Instância | W26: Ribeirão Preto | X26: 5ª Vara Cível | Y26: Extinto | Z26: 44705 | AA26: 45116 | AB26: =IFERROR(IF(Z26<>"",IF(AA26="",CONCATENATE(DATEDIF(Z26,TODAY(),"D")," dias"),CONCATENATE(DATEDIF(Z26,AA26,"D")," dias")),""),"") -> 411 dias | AD26: https://esaj.tjsp.jus.br/cpopg/show.do?processo.codigo=E2000NBJ30000&processo.foro=506&processo.numero=1021378-63.2022.8.26.0506 | AF26: =DATEDIF(TODAY(),U26,"D") -> #NUM! | AG26: =IFERROR(IF(Z26<>"",IF(AA26="",DATEDIF(Z26,TODAY(),"D"),DATEDIF(Z26,AA26,"D")),""),"") -> 411 | AI26: =IF(I26<>"",IF(F26<>"",CONCATENATE(I26," - ",G26," (",F26,")"),CONCATENATE(I26," - ",G26)),"") -> Leco Car - Seguro / Remoção / Vaga Técnica (1021378-63.2022.8.26.0506) | AJ26: =IF(I26<>"",IF(F26<>"",CONCATENATE(I26," - ",G26," (",F26,")"),CONCATENATE(I26," - ",G26)),"") -> Leco Car - Seguro / Remoção / Vaga Técnica (1021378-63.2022.8.26.0506)
B27: 21 | C27: Encerrado | D27: Judicial | E27: Fase de Sentença | F27: 1023475-36.2022.8.26.0506 | G27: Seguro / Remoção / Vaga Técnica | H27: Pessoa Jurídica | I27: Leco Car | J27: Requerente | K27: HDI Seguros S/A | L27: Requerido | M27: FERES JUNQUEIRA NAJM | N27: 11762 | S27: =IF(O27<>0,IF(P27<>0,SUM(P27+Q27*O27+O27*R27),IF(Q27<>0,SUM(P27+Q27*O27+O27*R27),"")),IF(P27<>0,SUM(P27+Q27*N27+N27*R27),IF(Q27<>0,SUM(P27+Q27*N27+N27*R27),""))) | T27: Não | V27: 1ª Instância | W27: Ribeirão Preto | X27: 5ª Vara Cível | Y27: Extinto | Z27: 44715 | AB27: =IFERROR(IF(Z27<>"",IF(AA27="",CONCATENATE(DATEDIF(Z27,TODAY(),"D")," dias"),CONCATENATE(DATEDIF(Z27,AA27,"D")," dias")),""),"") -> 1364 dias | AD27: https://esaj.tjsp.jus.br/cpopg/show.do?processo.codigo=E2000NEAN0000&processo.foro=506&processo.numero=1023475-36.2022.8.26.0506 | AF27: =DATEDIF(TODAY(),U27,"D") -> #NUM! | AG27: =IFERROR(IF(Z27<>"",IF(AA27="",DATEDIF(Z27,TODAY(),"D"),DATEDIF(Z27,AA27,"D")),""),"") -> 1364 | AI27: =IF(I27<>"",IF(F27<>"",CONCATENATE(I27," - ",G27," (",F27,")"),CONCATENATE(I27," - ",G27)),"") -> Leco Car - Seguro / Remoção / Vaga Técnica (1023475-36.2022.8.26.0506) | AJ27: =IF(I27<>"",IF(F27<>"",CONCATENATE(I27," - ",G27," (",F27,")"),CONCATENATE(I27," - ",G27)),"") -> Leco Car - Seguro / Remoção / Vaga Técnica (1023475-36.2022.8.26.0506)
B28: 22 | C28: Ativo | D28: Judicial | E28: Fase de Produção de Provas | F28: 1005036-74.2022.8.26.0506 | G28: Ação Indenizatória | H28: Pessoa Física | I28: Felipe Augusto Taveiros Palei | J28: Requerente | K28: Polimport - Comércio e Expostação (Americanas) | L28: Requerido | M28: FERES JUNQUEIRA NAJM | N28: 7173.59 | S28: =IF(O28<>0,IF(P28<>0,SUM(P28+Q28*O28+O28*R28),IF(Q28<>0,SUM(P28+Q28*O28+O28*R28),"")),IF(P28<>0,SUM(P28+Q28*N28+N28*R28),IF(Q28<>0,SUM(P28+Q28*N28+N28*R28),""))) | T28: Não | V28: 1ª Instância | W28: Ribeirão Preto | X28: 10ª Vara Cível | Y28: Foi feito um pedido de habilitação de novos patronos | Z28: 44606 | AB28: =IFERROR(IF(Z28<>"",IF(AA28="",CONCATENATE(DATEDIF(Z28,TODAY(),"D")," dias"),CONCATENATE(DATEDIF(Z28,AA28,"D")," dias")),""),"") -> 1473 dias | AD28: https://esaj.tjsp.jus.br/cpopg/show.do?processo.codigo=E2000MN7B0000&processo.foro=506&processo.numero=1005036-74.2022.8.26.0506 | AF28: =DATEDIF(TODAY(),U28,"D") -> #NUM! | AG28: =IFERROR(IF(Z28<>"",IF(AA28="",DATEDIF(Z28,TODAY(),"D"),DATEDIF(Z28,AA28,"D")),""),"") -> 1473 | AI28: =IF(I28<>"",IF(F28<>"",CONCATENATE(I28," - ",G28," (",F28,")"),CONCATENATE(I28," - ",G28)),"") -> Felipe Augusto Taveiros Palei - Ação Indenizatória (1005036-74.2022.8.26.0506) | AJ28: =IF(I28<>"",IF(F28<>"",CONCATENATE(I28," - ",G28," (",F28,")"),CONCATENATE(I28," - ",G28)),"") -> Felipe Augusto Taveiros Palei - Ação Indenizatória (1005036-74.2022.8.26.0506)
B29: 23 | C29: Ativo | D29: Judicial | E29: Fase Recursal | F29: 1000042-06.2022.8.26.0602 | G29: Declaração de Inexistência de Débito | H29: Pessoa Física | I29: Maria Angélica Cal Garcia Prado | J29: Requerente | K29: SPPREV - São Paulo Previdência | L29: Requerido | M29: FERES JUNQUEIRA NAJM | N29: 1000 | S29: =IF(O29<>0,IF(P29<>0,SUM(P29+Q29*O29+O29*R29),IF(Q29<>0,SUM(P29+Q29*O29+O29*R29),"")),IF(P29<>0,SUM(P29+Q29*N29+N29*R29),IF(Q29<>0,SUM(P29+Q29*N29+N29*R29),""))) | T29: Sim | V29: Tribunal de Justiça - São Paulo | W29: Sorocaba | X29: Juizado Especial Cível | Y29: Foi declarado vencido o Ministério da Fazenda. Aberto para cumprimento de sentença. | Z29: 44564 | AB29: =IFERROR(IF(Z29<>"",IF(AA29="",CONCATENATE(DATEDIF(Z29,TODAY(),"D")," dias"),CONCATENATE(DATEDIF(Z29,AA29,"D")," dias")),""),"") -> 1515 dias | AD29: https://esaj.tjsp.jus.br/cpopg/show.do?processo.codigo=GQ000QYKS0000&processo.foro=602&processo.numero=1000042-06.2022.8.26.0602 | AF29: =DATEDIF(TODAY(),U29,"D") -> #NUM! | AG29: =IFERROR(IF(Z29<>"",IF(AA29="",DATEDIF(Z29,TODAY(),"D"),DATEDIF(Z29,AA29,"D")),""),"") -> 1515 | AI29: =IF(I29<>"",IF(F29<>"",CONCATENATE(I29," - ",G29," (",F29,")"),CONCATENATE(I29," - ",G29)),"") -> Maria Angélica Cal Garcia Prado - Declaração de Inexistência de Débito (1000042-06.2022.8.26.0602) | AJ29: =IF(I29<>"",IF(F29<>"",CONCATENATE(I29," - ",G29," (",F29,")"),CONCATENATE(I29," - ",G29)),"") -> Maria Angélica Cal Garcia Prado - Declaração de Inexistência de Débito (1000042-06.2022.8.26.0602)
B30: 24 | C30: Encerrado | D30: Judicial | E30: Fase de Execução | F30: 1500252-07.2016.8.26.0506 | G30: Execução Fiscal | H30: Pessoa Jurídica | I30: Mister Ottani | J30: Requerido | K30: Prefeitura Municipal de Ribeirão Preto (Fazendo Municipal) | L30: Requerente | M30: FERES JUNQUEIRA NAJM | N30: 2622.4 | S30: =IF(O30<>0,IF(P30<>0,SUM(P30+Q30*O30+O30*R30),IF(Q30<>0,SUM(P30+Q30*O30+O30*R30),"")),IF(P30<>0,SUM(P30+Q30*N30+N30*R30),IF(Q30<>0,SUM(P30+Q30*N30+N30*R30),""))) | T30: Não | V30: 1ª Instância | W30: Ribeirão Preto | X30: Vara Execuções Fiscais | Y30: Aguardando a extinção do processo | Z30: 42978 | AB30: =IFERROR(IF(Z30<>"",IF(AA30="",CONCATENATE(DATEDIF(Z30,TODAY(),"D")," dias"),CONCATENATE(DATEDIF(Z30,AA30,"D")," dias")),""),"") -> 3101 dias | AD30: https://esaj.tjsp.jus.br/cpopg/show.do?processo.codigo=E20008C0H0000&processo.foro=506&processo.numero=1500252-07.2016.8.26.0506 | AF30: =DATEDIF(TODAY(),U30,"D") -> #NUM! | AG30: =IFERROR(IF(Z30<>"",IF(AA30="",DATEDIF(Z30,TODAY(),"D"),DATEDIF(Z30,AA30,"D")),""),"") -> 3101 | AI30: =IF(I30<>"",IF(F30<>"",CONCATENATE(I30," - ",G30," (",F30,")"),CONCATENATE(I30," - ",G30)),"") -> Mister Ottani - Execução Fiscal (1500252-07.2016.8.26.0506) | AJ30: =IF(I30<>"",IF(F30<>"",CONCATENATE(I30," - ",G30," (",F30,")"),CONCATENATE(I30," - ",G30)),"") -> Mister Ottani - Execução Fiscal (1500252-07.2016.8.26.0506)
B31: 25 | C31: Encerrado | D31: Judicial | E31: Fase de Execução | F31: 1505481-45.2016.8.26.0506 | G31: Execução Fiscal | H31: Pessoa Jurídica | I31: Mister Ottani | J31: Requerido | K31: Prefeitura Municipal de Ribeirão Preto (Fazendo Municipal) | L31: Requerente | M31: FERES JUNQUEIRA NAJM | N31: 2594.61 | S31: =IF(O31<>0,IF(P31<>0,SUM(P31+Q31*O31+O31*R31),IF(Q31<>0,SUM(P31+Q31*O31+O31*R31),"")),IF(P31<>0,SUM(P31+Q31*N31+N31*R31),IF(Q31<>0,SUM(P31+Q31*N31+N31*R31),""))) | T31: Não | V31: 1ª Instância | W31: Ribeirão Preto | X31: Vara Execuções Fiscais | Y31: Aguardando a extinção do processo | Z31: 42977 | AB31: =IFERROR(IF(Z31<>"",IF(AA31="",CONCATENATE(DATEDIF(Z31,TODAY(),"D")," dias"),CONCATENATE(DATEDIF(Z31,AA31,"D")," dias")),""),"") -> 3102 dias | AD31: https://esaj.tjsp.jus.br/cpopg/show.do?processo.codigo=E20009APM0000&processo.foro=506&processo.numero=1505481-45.2016.8.26.0506 | AF31: =DATEDIF(TODAY(),U31,"D") -> #NUM! | AG31: =IFERROR(IF(Z31<>"",IF(AA31="",DATEDIF(Z31,TODAY(),"D"),DATEDIF(Z31,AA31,"D")),""),"") -> 3102 | AI31: =IF(I31<>"",IF(F31<>"",CONCATENATE(I31," - ",G31," (",F31,")"),CONCATENATE(I31," - ",G31)),"") -> Mister Ottani - Execução Fiscal (1505481-45.2016.8.26.0506) | AJ31: =IF(I31<>"",IF(F31<>"",CONCATENATE(I31," - ",G31," (",F31,")"),CONCATENATE(I31," - ",G31)),"") -> Mister Ottani - Execução Fiscal (1505481-45.2016.8.26.0506)
B32: 26 | C32: Encerrado | D32: Judicial | E32: Fase de Sentença | F32: 1014033-06.2022.8.26.0196 | G32: Ação Indenizatória | H32: Pessoa Jurídica | I32: Supermercados Big Compra Ltda. | J32: Requerido | K32: Mirtes Helena Neves | L32: Requerente | M32: FERES JUNQUEIRA NAJM | N32: 12120 | S32: =IF(O32<>0,IF(P32<>0,SUM(P32+Q32*O32+O32*R32),IF(Q32<>0,SUM(P32+Q32*O32+O32*R32),"")),IF(P32<>0,SUM(P32+Q32*N32+N32*R32),IF(Q32<>0,SUM(P32+Q32*N32+N32*R32),""))) | T32: Não | V32: 1ª Instância | W32: Franca | X32: 2ª Vara Cível | Y32: Concluso para sentença | Z32: 44721 | AB32: =IFERROR(IF(Z32<>"",IF(AA32="",CONCATENATE(DATEDIF(Z32,TODAY(),"D")," dias"),CONCATENATE(DATEDIF(Z32,AA32,"D")," dias")),""),"") -> 1358 dias | AD32: https://esaj.tjsp.jus.br/cpopg/show.do?processo.codigo=5G000DHZG0000&processo.foro=196&processo.numero=1014033-06.2022.8.26.0196 | AF32: =DATEDIF(TODAY(),U32,"D") -> #NUM! | AG32: =IFERROR(IF(Z32<>"",IF(AA32="",DATEDIF(Z32,TODAY(),"D"),DATEDIF(Z32,AA32,"D")),""),"") -> 1358 | AI32: =IF(I32<>"",IF(F32<>"",CONCATENATE(I32," - ",G32," (",F32,")"),CONCATENATE(I32," - ",G32)),"") -> Supermercados Big Compra Ltda. - Ação Indenizatória (1014033-06.2022.8.26.0196) | AJ32: =IF(I32<>"",IF(F32<>"",CONCATENATE(I32," - ",G32," (",F32,")"),CONCATENATE(I32," - ",G32)),"") -> Supermercados Big Compra Ltda. - Ação Indenizatória (1014033-06.2022.8.26.0196)
B33: 27 | C33: Encerrado | D33: Judicial | E33: Fase Recursal | F33: 1034463-19.2022.8.26.0506 | G33: Seguro / Remoção / Vaga Técnica | H33: Pessoa Jurídica | I33: André Luís Massaro | J33: Requerente | K33: HDI Seguros S/A | L33: Requerido | M33: FERES JUNQUEIRA NAJM | N33: 1000 | S33: =IF(O33<>0,IF(P33<>0,SUM(P33+Q33*O33+O33*R33),IF(Q33<>0,SUM(P33+Q33*O33+O33*R33),"")),IF(P33<>0,SUM(P33+Q33*N33+N33*R33),IF(Q33<>0,SUM(P33+Q33*N33+N33*R33),""))) | T33: Não | V33: Tribunal de Justiça - São Paulo | W33: Rbeirão Preto | X33: 30ª Câmara de Direito Privado | Y33: Desembargador negou o provimento | Z33: 44778 | AA33: 45392 | AB33: =IFERROR(IF(Z33<>"",IF(AA33="",CONCATENATE(DATEDIF(Z33,TODAY(),"D")," dias"),CONCATENATE(DATEDIF(Z33,AA33,"D")," dias")),""),"") -> 614 dias | AD33: https://esaj.tjsp.jus.br/cpopg/show.do?processo.codigo=E2000NT950000&processo.foro=506&processo.numero=1034463-19.2022.8.26.0506 | AF33: =DATEDIF(TODAY(),U33,"D") -> #NUM! | AG33: =IFERROR(IF(Z33<>"",IF(AA33="",DATEDIF(Z33,TODAY(),"D"),DATEDIF(Z33,AA33,"D")),""),"") -> 614 | AI33: =IF(I33<>"",IF(F33<>"",CONCATENATE(I33," - ",G33," (",F33,")"),CONCATENATE(I33," - ",G33)),"") -> André Luís Massaro - Seguro / Remoção / Vaga Técnica (1034463-19.2022.8.26.0506) | AJ33: =IF(I33<>"",IF(F33<>"",CONCATENATE(I33," - ",G33," (",F33,")"),CONCATENATE(I33," - ",G33)),"") -> André Luís Massaro - Seguro / Remoção / Vaga Técnica (1034463-19.2022.8.26.0506)
B34: 28 | C34: Encerrado | D34: Judicial | E34: Fase de Sentença | F34: 1035727-71.2022.8.26.0506 | G34: Dissolução e Liquidação de Sociedade | H34: Pessoa Jurídica | I34: Brilho Auto Center | J34: Requerente | K34: Não tem | M34: FERES JUNQUEIRA NAJM | N34: 22500 | S34: =IF(O34<>0,IF(P34<>0,SUM(P34+Q34*O34+O34*R34),IF(Q34<>0,SUM(P34+Q34*O34+O34*R34),"")),IF(P34<>0,SUM(P34+Q34*N34+N34*R34),IF(Q34<>0,SUM(P34+Q34*N34+N34*R34),""))) | T34: Não | V34: 1ª Instância | W34: Ribeirão Preto | X34: 4ª Vara Cível | Y34: Extinto | Z34: 44785 | AA34: 45048 | AB34: =IFERROR(IF(Z34<>"",IF(AA34="",CONCATENATE(DATEDIF(Z34,TODAY(),"D")," dias"),CONCATENATE(DATEDIF(Z34,AA34,"D")," dias")),""),"") -> 263 dias | AD34: https://esaj.tjsp.jus.br/cpopg/show.do?processo.codigo=E2000NUZ60000&processo.foro=506&processo.numero=1035727-71.2022.8.26.0506 | AF34: =DATEDIF(TODAY(),U34,"D") -> #NUM! | AG34: =IFERROR(IF(Z34<>"",IF(AA34="",DATEDIF(Z34,TODAY(),"D"),DATEDIF(Z34,AA34,"D")),""),"") -> 263 | AI34: =IF(I34<>"",IF(F34<>"",CONCATENATE(I34," - ",G34," (",F34,")"),CONCATENATE(I34," - ",G34)),"") -> Brilho Auto Center - Dissolução e Liquidação de Sociedade (1035727-71.2022.8.26.0506) | AJ34: =IF(I34<>"",IF(F34<>"",CONCATENATE(I34," - ",G34," (",F34,")"),CONCATENATE(I34," - ",G34)),"") -> Brilho Auto Center - Dissolução e Liquidação de Sociedade (1035727-71.2022.8.26.0506)
B35: 29 | C35: Encerrado | D35: Judicial | E35: Fase de Sentença | F35: 0000171-21.2022.8.26.0572 | G35: Cumprimento de sentença | H35: Pessoa Jurídica | I35: Supermercados Big Compra Ltda. | J35: Requerido | K35: Patricia Alves dos Santos | L35: Requerente | M35: FERES JUNQUEIRA NAJM | N35: 15000 | S35: =IF(O35<>0,IF(P35<>0,SUM(P35+Q35*O35+O35*R35),IF(Q35<>0,SUM(P35+Q35*O35+O35*R35),"")),IF(P35<>0,SUM(P35+Q35*N35+N35*R35),IF(Q35<>0,SUM(P35+Q35*N35+N35*R35),""))) | T35: Não | V35: 1ª Instância | W35: São Joaquim da Barra | X35: 2ª Vara Cível | Y35: Concluso para Despacho | Z35: 44595 | AB35: =IFERROR(IF(Z35<>"",IF(AA35="",CONCATENATE(DATEDIF(Z35,TODAY(),"D")," dias"),CONCATENATE(DATEDIF(Z35,AA35,"D")," dias")),""),"") -> 1484 dias | AD35: https://esaj.tjsp.jus.br/cpopg/show.do?processo.codigo=FW0002KAK0000&processo.foro=572&processo.numero=0000171-21.2022.8.26.0572 | AF35: =DATEDIF(TODAY(),U35,"D") -> #NUM! | AG35: =IFERROR(IF(Z35<>"",IF(AA35="",DATEDIF(Z35,TODAY(),"D"),DATEDIF(Z35,AA35,"D")),""),"") -> 1484 | AI35: =IF(I35<>"",IF(F35<>"",CONCATENATE(I35," - ",G35," (",F35,")"),CONCATENATE(I35," - ",G35)),"") -> Supermercados Big Compra Ltda. - Cumprimento de sentença (0000171-21.2022.8.26.0572) | AJ35: =IF(I35<>"",IF(F35<>"",CONCATENATE(I35," - ",G35," (",F35,")"),CONCATENATE(I35," - ",G35)),"") -> Supermercados Big Compra Ltda. - Cumprimento de sentença (0000171-21.2022.8.26.0572)
B36: 30 | C36: Encerrado | D36: Judicial | E36: Fase de Sentença | F36: 1014765-61.2021.8.26.0506 | G36: Ação Civil Pública | H36: Pessoa Jurídica | I36: Supermercados Big Compra Ltda. | J36: Requerido | K36: Ministério Público do Estado de São Paulo | L36: Requerente | M36: FERES JUNQUEIRA NAJM | N36: 2000000 | S36: =IF(O36<>0,IF(P36<>0,SUM(P36+Q36*O36+O36*R36),IF(Q36<>0,SUM(P36+Q36*O36+O36*R36),"")),IF(P36<>0,SUM(P36+Q36*N36+N36*R36),IF(Q36<>0,SUM(P36+Q36*N36+N36*R36),""))) | T36: Não | V36: 1ª Instância | W36: Ribeirão Preto | X36: 2ª Vara Cível | Y36: Extinto | Z36: 44314 | AA36: 45008 | AB36: =IFERROR(IF(Z36<>"",IF(AA36="",CONCATENATE(DATEDIF(Z36,TODAY(),"D")," dias"),CONCATENATE(DATEDIF(Z36,AA36,"D")," dias")),""),"") -> 694 dias | AC36: Acordo | AD36: https://esaj.tjsp.jus.br/cpopg/show.do?processo.codigo=E2000KVYD0000&processo.foro=506&processo.numero=1014765-61.2021.8.26.0506 | AF36: =DATEDIF(TODAY(),U36,"D") -> #NUM! | AG36: =IFERROR(IF(Z36<>"",IF(AA36="",DATEDIF(Z36,TODAY(),"D"),DATEDIF(Z36,AA36,"D")),""),"") -> 694 | AI36: =IF(I36<>"",IF(F36<>"",CONCATENATE(I36," - ",G36," (",F36,")"),CONCATENATE(I36," - ",G36)),"") -> Supermercados Big Compra Ltda. - Ação Civil Pública (1014765-61.2021.8.26.0506) | AJ36: =IF(I36<>"",IF(F36<>"",CONCATENATE(I36," - ",G36," (",F36,")"),CONCATENATE(I36," - ",G36)),"") -> Supermercados Big Compra Ltda. - Ação Civil Pública (1014765-61.2021.8.26.0506)
B37: 31 | C37: Encerrado | D37: Judicial | E37: Fase de Produção de Provas | F37: 1044093-02.2022.8.26.0506 | G37: Seguro / Remoção / Vaga Técnica | H37: Pessoa Jurídica | I37: Pepe Oficina | J37: Requerente | K37: HDI Seguros S/A | L37: Requerido | M37: FERES JUNQUEIRA NAJM | N37: 4800 | S37: =IF(O37<>0,IF(P37<>0,SUM(P37+Q37*O37+O37*R37),IF(Q37<>0,SUM(P37+Q37*O37+O37*R37),"")),IF(P37<>0,SUM(P37+Q37*N37+N37*R37),IF(Q37<>0,SUM(P37+Q37*N37+N37*R37),""))) | T37: Não | V37: 1ª Instância | W37: Ribeirão Preto | X37: 8ª Vara Cível | Y37: Aguardando a decisão do Juiz - 1ª Instância | Z37: 44896 | AA37: 45414 | AB37: =IFERROR(IF(Z37<>"",IF(AA37="",CONCATENATE(DATEDIF(Z37,TODAY(),"D")," dias"),CONCATENATE(DATEDIF(Z37,AA37,"D")," dias")),""),"") -> 518 dias | AD37: https://esaj.tjsp.jus.br/cpopg/show.do?processo.codigo=E2000O7KO0000&processo.foro=506&processo.numero=1044093-02.2022.8.26.0506 | AF37: =DATEDIF(TODAY(),U37,"D") -> #NUM! | AG37: =IFERROR(IF(Z37<>"",IF(AA37="",DATEDIF(Z37,TODAY(),"D"),DATEDIF(Z37,AA37,"D")),""),"") -> 518 | AI37: =IF(I37<>"",IF(F37<>"",CONCATENATE(I37," - ",G37," (",F37,")"),CONCATENATE(I37," - ",G37)),"") -> Pepe Oficina - Seguro / Remoção / Vaga Técnica (1044093-02.2022.8.26.0506) | AJ37: =IF(I37<>"",IF(F37<>"",CONCATENATE(I37," - ",G37," (",F37,")"),CONCATENATE(I37," - ",G37)),"") -> Pepe Oficina - Seguro / Remoção / Vaga Técnica (1044093-02.2022.8.26.0506)
B38: 32 | C38: Ativo | D38: Judicial | E38: Fase de Produção de Provas | F38: 1003735-88.2022.8.26.0572 | G38: Ação Indenizatória | H38: Pessoa Jurídica | I38: Supermercados Big Compra Ltda. | J38: Requerido | K38: Tiago Martins Alexandre da Silva | L38: Requerente | M38: FERES JUNQUEIRA NAJM | N38: 6021.98 | S38: =IF(O38<>0,IF(P38<>0,SUM(P38+Q38*O38+O38*R38),IF(Q38<>0,SUM(P38+Q38*O38+O38*R38),"")),IF(P38<>0,SUM(P38+Q38*N38+N38*R38),IF(Q38<>0,SUM(P38+Q38*N38+N38*R38),""))) | T38: Não | V38: 1ª Instância | W38: São Joaquim da Barra | X38: 2ª Vara Cível | Y38: Aguardando a realização da Perícia - Petição de juntada feita. Perita não se manifestou | Z38: 44882 | AB38: =IFERROR(IF(Z38<>"",IF(AA38="",CONCATENATE(DATEDIF(Z38,TODAY(),"D")," dias"),CONCATENATE(DATEDIF(Z38,AA38,"D")," dias")),""),"") -> 1197 dias | AD38: https://esaj.tjsp.jus.br/cpopg/show.do?processo.codigo=FW0002PYK0000&processo.foro=572&processo.numero=1003735-88.2022.8.26.0572 | AF38: =DATEDIF(TODAY(),U38,"D") -> #NUM! | AG38: =IFERROR(IF(Z38<>"",IF(AA38="",DATEDIF(Z38,TODAY(),"D"),DATEDIF(Z38,AA38,"D")),""),"") -> 1197 | AI38: =IF(I38<>"",IF(F38<>"",CONCATENATE(I38," - ",G38," (",F38,")"),CONCATENATE(I38," - ",G38)),"") -> Supermercados Big Compra Ltda. - Ação Indenizatória (1003735-88.2022.8.26.0572) | AJ38: =IF(I38<>"",IF(F38<>"",CONCATENATE(I38," - ",G38," (",F38,")"),CONCATENATE(I38," - ",G38)),"") -> Supermercados Big Compra Ltda. - Ação Indenizatória (1003735-88.2022.8.26.0572)
B39: 33 | C39: Encerrado | D39: Judicial | E39: Fase de Contestação | F39: 1052312-04.2022.8.26.0506 | G39: Ação Monitória | H39: Pessoa Jurídica | I39: Pepe Oficina | J39: Requerente | K39: Antônio Carlos Principessa Junior | L39: Embargante | M39: FERES JUNQUEIRA NAJM | N39: 6944.7 | S39: =IF(O39<>0,IF(P39<>0,SUM(P39+Q39*O39+O39*R39),IF(Q39<>0,SUM(P39+Q39*O39+O39*R39),"")),IF(P39<>0,SUM(P39+Q39*N39+N39*R39),IF(Q39<>0,SUM(P39+Q39*N39+N39*R39),""))) | T39: Não | V39: Tribunal de Justiça - São Paulo | W39: Ribeirão Preto | X39: 3ª Vara Cível | Y39: Feito o Agravo em Resp | Z39: 44888 | AB39: =IFERROR(IF(Z39<>"",IF(AA39="",CONCATENATE(DATEDIF(Z39,TODAY(),"D")," dias"),CONCATENATE(DATEDIF(Z39,AA39,"D")," dias")),""),"") -> 1191 dias | AD39: https://esaj.tjsp.jus.br/cpopg/show.do?processo.codigo=E2000OJDL0000&processo.foro=506&processo.numero=1052312-04.2022.8.26.0506 | AF39: =DATEDIF(TODAY(),U39,"D") -> #NUM! | AG39: =IFERROR(IF(Z39<>"",IF(AA39="",DATEDIF(Z39,TODAY(),"D"),DATEDIF(Z39,AA39,"D")),""),"") -> 1191 | AI39: =IF(I39<>"",IF(F39<>"",CONCATENATE(I39," - ",G39," (",F39,")"),CONCATENATE(I39," - ",G39)),"") -> Pepe Oficina - Ação Monitória (1052312-04.2022.8.26.0506) | AJ39: =IF(I39<>"",IF(F39<>"",CONCATENATE(I39," - ",G39," (",F39,")"),CONCATENATE(I39," - ",G39)),"") -> Pepe Oficina - Ação Monitória (1052312-04.2022.8.26.0506)
B40: 34 | C40: Encerrado | D40: Judicial | E40: Fase Inicial | F40: 1003462-79.2023.8.26.0506 | G40: Ação de Cumprimento de Garantia | H40: Pessoa Jurídica | I40: Pepe Oficina | J40: Autor | K40: Chigado Pneumatic Brasil Ltda. | L40: Réu | M40: FERES JUNQUEIRA NAJM | N40: 949.79 | S40: =IF(O40<>0,IF(P40<>0,SUM(P40+Q40*O40+O40*R40),IF(Q40<>0,SUM(P40+Q40*O40+O40*R40),"")),IF(P40<>0,SUM(P40+Q40*N40+N40*R40),IF(Q40<>0,SUM(P40+Q40*N40+N40*R40),""))) | T40: Não | V40: 1ª Instância | W40: Ribeirão Preto | X40: Juizado Especial Cível | Y40: Aguardando a extinção do processo | Z40: 44957 | AB40: =IFERROR(IF(Z40<>"",IF(AA40="",CONCATENATE(DATEDIF(Z40,TODAY(),"D")," dias"),CONCATENATE(DATEDIF(Z40,AA40,"D")," dias")),""),"") -> 1122 dias | AD40: https://esaj.tjsp.jus.br/cpopg/show.do?processo.codigo=E2000OXQM0000&processo.foro=506&processo.numero=1003462-79.2023.8.26.0506 | AF40: =DATEDIF(TODAY(),U40,"D") -> #NUM! | AG40: =IFERROR(IF(Z40<>"",IF(AA40="",DATEDIF(Z40,TODAY(),"D"),DATEDIF(Z40,AA40,"D")),""),"") -> 1122 | AI40: =IF(I40<>"",IF(F40<>"",CONCATENATE(I40," - ",G40," (",F40,")"),CONCATENATE(I40," - ",G40)),"") -> Pepe Oficina - Ação de Cumprimento de Garantia (1003462-79.2023.8.26.0506) | AJ40: =IF(I40<>"",IF(F40<>"",CONCATENATE(I40," - ",G40," (",F40,")"),CONCATENATE(I40," - ",G40)),"") -> Pepe Oficina - Ação de Cumprimento de Garantia (1003462-79.2023.8.26.0506)
B41: 35 | C41: Encerrado | D41: Judicial | E41: Fase Inicial | F41: 0004874-47.2018.8.13.0329 | G41: Dissolução e Liquidação de Sociedade | H41: Pessoa Jurídica | I41: New Truck Comércio de Peças e Funilaria Ltda. | J41: Autor | K41: Associação Imperial Paulista Proteção Automotiva | L41: Requerido | M41: FERES JUNQUEIRA NAJM | S41: =IF(O41<>0,IF(P41<>0,SUM(P41+Q41*O41+O41*R41),IF(Q41<>0,SUM(P41+Q41*O41+O41*R41),"")),IF(P41<>0,SUM(P41+Q41*N41+N41*R41),IF(Q41<>0,SUM(P41+Q41*N41+N41*R41),""))) | T41: Não | V41: 1ª Instância | W41: Minas Gerais | Y41: Arquivado Definitivamente - Extinto | AA41: 45072 | AB41: =IFERROR(IF(Z41<>"",IF(AA41="",CONCATENATE(DATEDIF(Z41,TODAY(),"D")," dias"),CONCATENATE(DATEDIF(Z41,AA41,"D")," dias")),""),"") | AD41: https://pje-consulta-publica.tjmg.jus.br/pje/ConsultaPublica/DetalheProcessoConsultaPublica/listView.seam?ca=2ab5cd883fa2879c658851801c83892e5673fabd47590f8a | AF41: =DATEDIF(TODAY(),U41,"D") -> #NUM! | AG41: =IFERROR(IF(Z41<>"",IF(AA41="",DATEDIF(Z41,TODAY(),"D"),DATEDIF(Z41,AA41,"D")),""),"") | AI41: =IF(I41<>"",IF(F41<>"",CONCATENATE(I41," - ",G41," (",F41,")"),CONCATENATE(I41," - ",G41)),"") -> New Truck Comércio de Peças e Funilaria Ltda. - Dissolução e Liquidação de Sociedade (0004874-47.2018.8.13.0329) | AJ41: =IF(I41<>"",IF(F41<>"",CONCATENATE(I41," - ",G41," (",F41,")"),CONCATENATE(I41," - ",G41)),"") -> New Truck Comércio de Peças e Funilaria Ltda. - Dissolução e Liquidação de Sociedade (0004874-47.2018.8.13.0329)
B42: 36 | C42: Ativo | D42: Judicial | E42: Fase Inicial | F42: 5269532-14.2022..8.13.0024 | G42: Reconvenção | H42: Pessoa Jurídica | I42: New Truck Comércio de Peças e Funilaria Ltda. | J42: Requerido | K42: Beneficios Blue | L42: Requerente | M42: FERES JUNQUEIRA NAJM | S42: =IF(O42<>0,IF(P42<>0,SUM(P42+Q42*O42+O42*R42),IF(Q42<>0,SUM(P42+Q42*O42+O42*R42),"")),IF(P42<>0,SUM(P42+Q42*N42+N42*R42),IF(Q42<>0,SUM(P42+Q42*N42+N42*R42),""))) | T42: Não | W42: Minas Gerais | Y42: Concluso para sentença | AB42: =IFERROR(IF(Z42<>"",IF(AA42="",CONCATENATE(DATEDIF(Z42,TODAY(),"D")," dias"),CONCATENATE(DATEDIF(Z42,AA42,"D")," dias")),""),"") | AF42: =DATEDIF(TODAY(),U42,"D") -> #NUM! | AG42: =IFERROR(IF(Z42<>"",IF(AA42="",DATEDIF(Z42,TODAY(),"D"),DATEDIF(Z42,AA42,"D")),""),"") | AI42: =IF(I42<>"",IF(F42<>"",CONCATENATE(I42," - ",G42," (",F42,")"),CONCATENATE(I42," - ",G42)),"") -> New Truck Comércio de Peças e Funilaria Ltda. - Reconvenção (5269532-14.2022..8.13.0024) | AJ42: =IF(I42<>"",IF(F42<>"",CONCATENATE(I42," - ",G42," (",F42,")"),CONCATENATE(I42," - ",G42)),"") -> New Truck Comércio de Peças e Funilaria Ltda. - Reconvenção (5269532-14.2022..8.13.0024)
B43: 37 | C43: Ativo | D43: Judicial | E43: Fase de Execução | F43: 1066730-69.2020.8.26.0100 | G43: Dissolução e Liquidação de Sociedade | H43: Pessoa Jurídica | I43: New Truck Comércio de Peças e Funilaria Ltda. | J43: Requerente | K43: Ctr. Itaborai - Centro de tratamento de residuos Itaborai | L43: Requerido | M43: FERES JUNQUEIRA NAJM | N43: 8.2391981e+08 | S43: =IF(O43<>0,IF(P43<>0,SUM(P43+Q43*O43+O43*R43),IF(Q43<>0,SUM(P43+Q43*O43+O43*R43),"")),IF(P43<>0,SUM(P43+Q43*N43+N43*R43),IF(Q43<>0,SUM(P43+Q43*N43+N43*R43),""))) | T43: Não | V43: 1ª Instância | W43: São Paulo | X43: Vara de Falências e Recuperação | Y43: Aguardando o despacho do Juiz | Z43: 44041 | AB43: =IFERROR(IF(Z43<>"",IF(AA43="",CONCATENATE(DATEDIF(Z43,TODAY(),"D")," dias"),CONCATENATE(DATEDIF(Z43,AA43,"D")," dias")),""),"") -> 2038 dias | AD43: https://esaj.tjsp.jus.br/cpopg/show.do?processo.codigo=2S001ABF50000&processo.foro=100&processo.numero=1066730-69.2020.8.26.0100 | AF43: =DATEDIF(TODAY(),U43,"D") -> #NUM! | AG43: =IFERROR(IF(Z43<>"",IF(AA43="",DATEDIF(Z43,TODAY(),"D"),DATEDIF(Z43,AA43,"D")),""),"") -> 2038 | AI43: =IF(I43<>"",IF(F43<>"",CONCATENATE(I43," - ",G43," (",F43,")"),CONCATENATE(I43," - ",G43)),"") -> New Truck Comércio de Peças e Funilaria Ltda. - Dissolução e Liquidação de Sociedade (1066730-69.2020.8.26.0100) | AJ43: =IF(I43<>"",IF(F43<>"",CONCATENATE(I43," - ",G43," (",F43,")"),CONCATENATE(I43," - ",G43)),"") -> New Truck Comércio de Peças e Funilaria Ltda. - Dissolução e Liquidação de Sociedade (1066730-69.2020.8.26.0100)
B44: 38 | C44: Ativo | D44: Judicial | E44: Fase Inicial | F44: 1004265-62.2023.8.26.0506 | G44: Ação de Cumprimento de Garantia | H44: Pessoa Jurídica | I44: Regina Célia Guarita Crochiquia e Outros | J44: Requerente | K44: Hyundai Caoa do Brasil Ltda | L44: Requerido | M44: FERES JUNQUEIRA NAJM | N44: 33151.27 | S44: =IF(O44<>0,IF(P44<>0,SUM(P44+Q44*O44+O44*R44),IF(Q44<>0,SUM(P44+Q44*O44+O44*R44),"")),IF(P44<>0,SUM(P44+Q44*N44+N44*R44),IF(Q44<>0,SUM(P44+Q44*N44+N44*R44),""))) | T44: Não | V44: 1ª Instância | W44: Ribeirão Preto | X44: 7ª Vara Cível | Y44: Aguardando pronunciamento do CEJUSC | Z44: 44963 | AB44: =IFERROR(IF(Z44<>"",IF(AA44="",CONCATENATE(DATEDIF(Z44,TODAY(),"D")," dias"),CONCATENATE(DATEDIF(Z44,AA44,"D")," dias")),""),"") -> 1116 dias | AD44: https://esaj.tjsp.jus.br/cpopg/show.do?processo.codigo=E2000OYWO0000&processo.foro=506&processo.numero=1004265-62.2023.8.26.0506 | AF44: =DATEDIF(TODAY(),U44,"D") -> #NUM! | AG44: =IFERROR(IF(Z44<>"",IF(AA44="",DATEDIF(Z44,TODAY(),"D"),DATEDIF(Z44,AA44,"D")),""),"") -> 1116 | AI44: =IF(I44<>"",IF(F44<>"",CONCATENATE(I44," - ",G44," (",F44,")"),CONCATENATE(I44," - ",G44)),"") -> Regina Célia Guarita Crochiquia e Outros - Ação de Cumprimento de Garantia (1004265-62.2023.8.26.0506) | AJ44: =IF(I44<>"",IF(F44<>"",CONCATENATE(I44," - ",G44," (",F44,")"),CONCATENATE(I44," - ",G44)),"") -> Regina Célia Guarita Crochiquia e Outros - Ação de Cumprimento de Garantia (1004265-62.2023.8.26.0506)
B45: 39 | C45: Encerrado | D45: Judicial | E45: Fase de Recurso | F45: 1000168-91.2023.8.26.0288 | G45: Ação Indenizatória | H45: Pessoa Jurídica | I45: Supermercados Big Compra Ltda. | J45: Requerido | K45: Ester Luchesi Hermenegildo | L45: Requerente | M45: FERES JUNQUEIRA NAJM | N45: 30000 | S45: =IF(O45<>0,IF(P45<>0,SUM(P45+Q45*O45+O45*R45),IF(Q45<>0,SUM(P45+Q45*O45+O45*R45),"")),IF(P45<>0,SUM(P45+Q45*N45+N45*R45),IF(Q45<>0,SUM(P45+Q45*N45+N45*R45),""))) | T45: Sim | V45: 1ª Instância | W45: Ituverava | X45: 1ª Vara Cível | Y45: Em Agravo em Resp | Z45: 44951 | AB45: =IFERROR(IF(Z45<>"",IF(AA45="",CONCATENATE(DATEDIF(Z45,TODAY(),"D")," dias"),CONCATENATE(DATEDIF(Z45,AA45,"D")," dias")),""),"") -> 1128 dias | AD45: https://esaj.tjsp.jus.br/cpopg/show.do?processo.codigo=8000028P70000&processo.foro=288&processo.numero=1000168-91.2023.8.26.0288 | AF45: =DATEDIF(TODAY(),U45,"D") -> #NUM! | AG45: =IFERROR(IF(Z45<>"",IF(AA45="",DATEDIF(Z45,TODAY(),"D"),DATEDIF(Z45,AA45,"D")),""),"") -> 1128 | AI45: =IF(I45<>"",IF(F45<>"",CONCATENATE(I45," - ",G45," (",F45,")"),CONCATENATE(I45," - ",G45)),"") -> Supermercados Big Compra Ltda. - Ação Indenizatória (1000168-91.2023.8.26.0288) | AJ45: =IF(I45<>"",IF(F45<>"",CONCATENATE(I45," - ",G45," (",F45,")"),CONCATENATE(I45," - ",G45)),"") -> Supermercados Big Compra Ltda. - Ação Indenizatória (1000168-91.2023.8.26.0288)
B46: 40 | C46: Ativo | D46: Judicial | E46: Concluso para Decisão | F46: 1030859-10.2022.8.26.0196 | G46: Ação Indenizatória | H46: Pessoa Jurídica | I46: Supermercados Big Compra Ltda. | J46: Requerido | K46: Cassio Roberto Pinto | L46: Requerente | M46: FERES JUNQUEIRA NAJM | N46: 12200 | S46: =IF(O46<>0,IF(P46<>0,SUM(P46+Q46*O46+O46*R46),IF(Q46<>0,SUM(P46+Q46*O46+O46*R46),"")),IF(P46<>0,SUM(P46+Q46*N46+N46*R46),IF(Q46<>0,SUM(P46+Q46*N46+N46*R46),""))) | T46: Sim | V46: 1ª Instância | W46: Franca | X46: 1ª Vara Cível | Y46: Prazo em aberto para manifestação sobre pesquisas. | Z46: 44891 | AB46: =IFERROR(IF(Z46<>"",IF(AA46="",CONCATENATE(DATEDIF(Z46,TODAY(),"D")," dias"),CONCATENATE(DATEDIF(Z46,AA46,"D")," dias")),""),"") -> 1188 dias | AD46: https://esaj.tjsp.jus.br/cpopg/show.do?processo.codigo=5G000EKFI0000&processo.foro=196&processo.numero=1030859-10.2022.8.26.0196 | AF46: =DATEDIF(TODAY(),U46,"D") -> #NUM! | AG46: =IFERROR(IF(Z46<>"",IF(AA46="",DATEDIF(Z46,TODAY(),"D"),DATEDIF(Z46,AA46,"D")),""),"") -> 1188 | AI46: =IF(I46<>"",IF(F46<>"",CONCATENATE(I46," - ",G46," (",F46,")"),CONCATENATE(I46," - ",G46)),"") -> Supermercados Big Compra Ltda. - Ação Indenizatória ( 1030859-10.2022.8.26.0196) | AJ46: =IF(I46<>"",IF(F46<>"",CONCATENATE(I46," - ",G46," (",F46,")"),CONCATENATE(I46," - ",G46)),"") -> Supermercados Big Compra Ltda. - Ação Indenizatória ( 1030859-10.2022.8.26.0196)
B47: 41 | C47: Encerrado | D47: Judicial | E47: Fase Inicial | F47: 1000876-65.2023.8.26.0572 | G47: Ação Indenizatória | H47: Pessoa Física | I47: Ariane dos Santos | J47: Autor | K47: Porto Seguro Companhia de Seguros Gerais | L47: Réu | M47: FERES JUNQUEIRA NAJM | N47: 10000 | S47: =IF(O47<>0,IF(P47<>0,SUM(P47+Q47*O47+O47*R47),IF(Q47<>0,SUM(P47+Q47*O47+O47*R47),"")),IF(P47<>0,SUM(P47+Q47*N47+N47*R47),IF(Q47<>0,SUM(P47+Q47*N47+N47*R47),""))) | T47: Sim | U47: 45069 | V47: 1ª Instância | W47: São Joaquim da Barra | X47: Juizado Especial Cível | Y47: Aguardando a contestação do réu | Z47: 45002 | AB47: =IFERROR(IF(Z47<>"",IF(AA47="",CONCATENATE(DATEDIF(Z47,TODAY(),"D")," dias"),CONCATENATE(DATEDIF(Z47,AA47,"D")," dias")),""),"") -> 1077 dias | AD47: https://esaj.tjsp.jus.br/cpopg/show.do?processo.codigo=FW0002T5W0000&processo.foro=572&processo.numero=1000876-65.2023.8.26.0572 | AF47: =DATEDIF(TODAY(),U47,"D") -> #NUM! | AG47: =IFERROR(IF(Z47<>"",IF(AA47="",DATEDIF(Z47,TODAY(),"D"),DATEDIF(Z47,AA47,"D")),""),"") -> 1077 | AI47: =IF(I47<>"",IF(F47<>"",CONCATENATE(I47," - ",G47," (",F47,")"),CONCATENATE(I47," - ",G47)),"") -> Ariane dos Santos - Ação Indenizatória (1000876-65.2023.8.26.0572) | AJ47: =IF(I47<>"",IF(F47<>"",CONCATENATE(I47," - ",G47," (",F47,")"),CONCATENATE(I47," - ",G47)),"") -> Ariane dos Santos - Ação Indenizatória (1000876-65.2023.8.26.0572)
B48: 42 | C48: Ativo | D48: Judicial | E48: Fase de Execução | F48: 0004512-60.2023.8.26.0506 | G48: Cumprimento de sentença | H48: Pessoa Física | I48: Danielle Contin Nader | J48: Autor | K48: Cipreste Residencial Incorporadora Imobiliária Ltda. | L48: Réu | M48: FERES JUNQUEIRA NAJM | N48: 5089 | S48: =IF(O48<>0,IF(P48<>0,SUM(P48+Q48*O48+O48*R48),IF(Q48<>0,SUM(P48+Q48*O48+O48*R48),"")),IF(P48<>0,SUM(P48+Q48*N48+N48*R48),IF(Q48<>0,SUM(P48+Q48*N48+N48*R48),""))) | T48: Não | V48: 1ª Instância | W48: Ribeirão Preto | X48: 9ª Vara Cível | Y48: Prazo Suspenso - retorno 22/04/2024 | Z48: 44999 | AB48: =IFERROR(IF(Z48<>"",IF(AA48="",CONCATENATE(DATEDIF(Z48,TODAY(),"D")," dias"),CONCATENATE(DATEDIF(Z48,AA48,"D")," dias")),""),"") -> 1080 dias | AD48: https://esaj.tjsp.jus.br/cpopg/show.do?processo.codigo=E2000P7HZ0000&processo.foro=506&processo.numero=0004512-60.2023.8.26.0506 | AF48: =DATEDIF(TODAY(),U48,"D") -> #NUM! | AG48: =IFERROR(IF(Z48<>"",IF(AA48="",DATEDIF(Z48,TODAY(),"D"),DATEDIF(Z48,AA48,"D")),""),"") -> 1080 | AI48: =IF(I48<>"",IF(F48<>"",CONCATENATE(I48," - ",G48," (",F48,")"),CONCATENATE(I48," - ",G48)),"") -> Danielle Contin Nader - Cumprimento de sentença (0004512-60.2023.8.26.0506) | AJ48: =IF(I48<>"",IF(F48<>"",CONCATENATE(I48," - ",G48," (",F48,")"),CONCATENATE(I48," - ",G48)),"") -> Danielle Contin Nader - Cumprimento de sentença (0004512-60.2023.8.26.0506)
B49: 43 | C49: Ativo | D49: Judicial | E49: Fase de Execução | F49: 0005440-11.2023.8.26.0506 | G49: Cumprimento de sentença | H49: Pessoa Física | I49: Daniel Alexandre Picão Alves | J49: Autor | K49: Ricardo Ferreira Barbosa | L49: Réu | M49: FERES JUNQUEIRA NAJM | N49: 3050.21 | S49: =IF(O49<>0,IF(P49<>0,SUM(P49+Q49*O49+O49*R49),IF(Q49<>0,SUM(P49+Q49*O49+O49*R49),"")),IF(P49<>0,SUM(P49+Q49*N49+N49*R49),IF(Q49<>0,SUM(P49+Q49*N49+N49*R49),""))) | T49: Não | V49: 1ª Instância | W49: Ribeirão Preto | X49: Juizado Especial Cível | Y49: Foi emitida a ordem de penhora e avaliação de um bem do executado | Z49: 45007 | AB49: =IFERROR(IF(Z49<>"",IF(AA49="",CONCATENATE(DATEDIF(Z49,TODAY(),"D")," dias"),CONCATENATE(DATEDIF(Z49,AA49,"D")," dias")),""),"") -> 1072 dias | AD49: https://esaj.tjsp.jus.br/cpopg/show.do?processo.codigo=E2000PA6N0000&processo.foro=506&processo.numero=0005440-11.2023.8.26.0506 | AF49: =DATEDIF(TODAY(),U49,"D") -> #NUM! | AG49: =IFERROR(IF(Z49<>"",IF(AA49="",DATEDIF(Z49,TODAY(),"D"),DATEDIF(Z49,AA49,"D")),""),"") -> 1072 | AI49: =IF(I49<>"",IF(F49<>"",CONCATENATE(I49," - ",G49," (",F49,")"),CONCATENATE(I49," - ",G49)),"") -> Daniel Alexandre Picão Alves - Cumprimento de sentença (0005440-11.2023.8.26.0506) | AJ49: =IF(I49<>"",IF(F49<>"",CONCATENATE(I49," - ",G49," (",F49,")"),CONCATENATE(I49," - ",G49)),"") -> Daniel Alexandre Picão Alves - Cumprimento de sentença (0005440-11.2023.8.26.0506)
B50: 44 | C50: Ativo | D50: Judicial | E50: Fase de Sentença | F50: 0010161-66.2021.5.15.0042 | G50: Reclamação Trabalhista | H50: Pessoa Física | I50: Eleanderson Marcos de Souza Santos | J50: Reclamante | K50: Alliage S/A Industrias Medico Odontologico | L50: Reclamado | M50: ADRIANO LOURENÇO MORAIS DOS SANTOS | N50: 76852.6 | S50: =IF(O50<>0,IF(P50<>0,SUM(P50+Q50*O50+O50*R50),IF(Q50<>0,SUM(P50+Q50*O50+O50*R50),"")),IF(P50<>0,SUM(P50+Q50*N50+N50*R50),IF(Q50<>0,SUM(P50+Q50*N50+N50*R50),""))) | T50: Não | V50: TRT da 15ª Região - Sao Paulo/Campinas | W50: Ribeirão Preto | X50: 2ª Vara Trabalhista | Y50: Foram homologados os cálculos | Z50: 44242 | AB50: =IFERROR(IF(Z50<>"",IF(AA50="",CONCATENATE(DATEDIF(Z50,TODAY(),"D")," dias"),CONCATENATE(DATEDIF(Z50,AA50,"D")," dias")),""),"") -> 1837 dias | AD50: https://pje.trt15.jus.br/pjekz/processo/2816141/detalhe | AF50: =DATEDIF(TODAY(),U50,"D") -> #NUM! | AG50: =IFERROR(IF(Z50<>"",IF(AA50="",DATEDIF(Z50,TODAY(),"D"),DATEDIF(Z50,AA50,"D")),""),"") -> 1837 | AI50: =IF(I50<>"",IF(F50<>"",CONCATENATE(I50," - ",G50," (",F50,")"),CONCATENATE(I50," - ",G50)),"") -> Eleanderson Marcos de Souza Santos - Reclamação Trabalhista (0010161-66.2021.5.15.0042) | AJ50: =IF(I50<>"",IF(F50<>"",CONCATENATE(I50," - ",G50," (",F50,")"),CONCATENATE(I50," - ",G50)),"") -> Eleanderson Marcos de Souza Santos - Reclamação Trabalhista (0010161-66.2021.5.15.0042)
B51: 45 | C51: Encerrado | D51: Judicial | E51: Fase de Sentença | F51: 0010294-40.2021.5.15.0097 | G51: Reclamação Trabalhista | H51: Pessoa Física | I51: Alessandro de Moura | J51: Reclamante | K51: Fort Fic Serviços e Portaria e Outros | L51: Reclamado | M51: ADRIANO LOURENÇO MORAIS DOS SANTOS | N51: 90173.38 | S51: =IF(O51<>0,IF(P51<>0,SUM(P51+Q51*O51+O51*R51),IF(Q51<>0,SUM(P51+Q51*O51+O51*R51),"")),IF(P51<>0,SUM(P51+Q51*N51+N51*R51),IF(Q51<>0,SUM(P51+Q51*N51+N51*R51),""))) | T51: Não | V51: TRT da 15ª Região - Sao Paulo/Campinas | W51: Jundiaí | X51: 5ª Vara do Trabalho | Y51: Acordo Homologado na Audiência | Z51: 44250 | AA51: 44776 | AB51: =IFERROR(IF(Z51<>"",IF(AA51="",CONCATENATE(DATEDIF(Z51,TODAY(),"D")," dias"),CONCATENATE(DATEDIF(Z51,AA51,"D")," dias")),""),"") -> 526 dias | AC51: Acordo | AD51: https://pje.trt15.jus.br/pjekz/processo/2822382/detalhe | AF51: =DATEDIF(TODAY(),U51,"D") -> #NUM! | AG51: =IFERROR(IF(Z51<>"",IF(AA51="",DATEDIF(Z51,TODAY(),"D"),DATEDIF(Z51,AA51,"D")),""),"") -> 526 | AI51: =IF(I51<>"",IF(F51<>"",CONCATENATE(I51," - ",G51," (",F51,")"),CONCATENATE(I51," - ",G51)),"") -> Alessandro de Moura - Reclamação Trabalhista (0010294-40.2021.5.15.0097) | AJ51: =IF(I51<>"",IF(F51<>"",CONCATENATE(I51," - ",G51," (",F51,")"),CONCATENATE(I51," - ",G51)),"") -> Alessandro de Moura - Reclamação Trabalhista (0010294-40.2021.5.15.0097)
B52: 46 | C52: Encerrado | D52: Judicial | E52: Fase de Sentença | F52: 0010338-17.2021.5.15.0097 | G52: Reclamação Trabalhista | H52: Pessoa Física | I52: Edgar Dreger | J52: Reclamante | K52: Associação Residencial Fazenda Alvorada | L52: Reclamado | M52: ADRIANO LOURENÇO MORAIS DOS SANTOS | N52: 118398.23 | O52: 33000 | S52: =IF(O52<>0,IF(P52<>0,SUM(P52+Q52*O52+O52*R52),IF(Q52<>0,SUM(P52+Q52*O52+O52*R52),"")),IF(P52<>0,SUM(P52+Q52*N52+N52*R52),IF(Q52<>0,SUM(P52+Q52*N52+N52*R52),""))) | T52: Não | V52: TRT da 15ª Região - Sao Paulo/Campinas | W52: Tietê | X52: Vara do Tietê | Y52: Acordo Homologado na Audiência | Z52: 44259 | AA52: 44872 | AB52: =IFERROR(IF(Z52<>"",IF(AA52="",CONCATENATE(DATEDIF(Z52,TODAY(),"D")," dias"),CONCATENATE(DATEDIF(Z52,AA52,"D")," dias")),""),"") -> 613 dias | AC52: Acordo | AF52: =DATEDIF(TODAY(),U52,"D") -> #NUM! | AG52: =IFERROR(IF(Z52<>"",IF(AA52="",DATEDIF(Z52,TODAY(),"D"),DATEDIF(Z52,AA52,"D")),""),"") -> 613 | AI52: =IF(I52<>"",IF(F52<>"",CONCATENATE(I52," - ",G52," (",F52,")"),CONCATENATE(I52," - ",G52)),"") -> Edgar Dreger - Reclamação Trabalhista (0010338-17.2021.5.15.0097) | AJ52: =IF(I52<>"",IF(F52<>"",CONCATENATE(I52," - ",G52," (",F52,")"),CONCATENATE(I52," - ",G52)),"") -> Edgar Dreger - Reclamação Trabalhista (0010338-17.2021.5.15.0097)
B53: 47 | C53: Encerrado | D53: Judicial | E53: Fase Recursal | F53: 0010885-02.2021.5.15.0097 | G53: Reclamação Trabalhista | H53: Pessoa Física | I53: Luzia Inagaki | J53: Reclamante | K53: Centerlar Comércio de Utilidades Ltda | L53: Reclamado | M53: ADRIANO LOURENÇO MORAIS DOS SANTOS | N53: 26341.94 | O53: 20000 | S53: =IF(O53<>0,IF(P53<>0,SUM(P53+Q53*O53+O53*R53),IF(Q53<>0,SUM(P53+Q53*O53+O53*R53),"")),IF(P53<>0,SUM(P53+Q53*N53+N53*R53),IF(Q53<>0,SUM(P53+Q53*N53+N53*R53),""))) | T53: Não | V53: TRT da 15ª Região - Sao Paulo/Campinas | W53: Jundiaí | X53: 4ª Vara do Trabalho | Y53: Arquivado | Z53: 44322 | AB53: =IFERROR(IF(Z53<>"",IF(AA53="",CONCATENATE(DATEDIF(Z53,TODAY(),"D")," dias"),CONCATENATE(DATEDIF(Z53,AA53,"D")," dias")),""),"") -> 1757 dias | AC53: Procedente | AD53: https://pje.trt15.jus.br/pjekz/processo/2880526/detalhe | AF53: =DATEDIF(TODAY(),U53,"D") -> #NUM! | AG53: =IFERROR(IF(Z53<>"",IF(AA53="",DATEDIF(Z53,TODAY(),"D"),DATEDIF(Z53,AA53,"D")),""),"") -> 1757 | AI53: =IF(I53<>"",IF(F53<>"",CONCATENATE(I53," - ",G53," (",F53,")"),CONCATENATE(I53," - ",G53)),"") -> Luzia Inagaki - Reclamação Trabalhista (0010885-02.2021.5.15.0097) | AJ53: =IF(I53<>"",IF(F53<>"",CONCATENATE(I53," - ",G53," (",F53,")"),CONCATENATE(I53," - ",G53)),"") -> Luzia Inagaki - Reclamação Trabalhista (0010885-02.2021.5.15.0097)
B54: 48 | C54: Encerrado | D54: Judicial | E54: Fase de Sentença | F54: 1000700-58.2021.5.02.0319 | G54: Reclamação Trabalhista | H54: Pessoa Física | I54: Alcir Santos Simões Junior | J54: Reclamante | K54: Sancargo Logistica de Cargas Ltda | L54: Reclamado | M54: ADRIANO LOURENÇO MORAIS DOS SANTOS | N54: 21457.94 | S54: =IF(O54<>0,IF(P54<>0,SUM(P54+Q54*O54+O54*R54),IF(Q54<>0,SUM(P54+Q54*O54+O54*R54),"")),IF(P54<>0,SUM(P54+Q54*N54+N54*R54),IF(Q54<>0,SUM(P54+Q54*N54+N54*R54),""))) | T54: Não | V54: TRT da 15ª Região - Sao Paulo/Campinas | W54: Guarulhos | X54: 9ª Vara do Trabalho | Y54: Improcedente | Z54: 44311 | AA54: 44401 | AB54: =IFERROR(IF(Z54<>"",IF(AA54="",CONCATENATE(DATEDIF(Z54,TODAY(),"D")," dias"),CONCATENATE(DATEDIF(Z54,AA54,"D")," dias")),""),"") -> 90 dias | AC54: Improcedente | AF54: =DATEDIF(TODAY(),U54,"D") -> #NUM! | AG54: =IFERROR(IF(Z54<>"",IF(AA54="",DATEDIF(Z54,TODAY(),"D"),DATEDIF(Z54,AA54,"D")),""),"") -> 90 | AI54: =IF(I54<>"",IF(F54<>"",CONCATENATE(I54," - ",G54," (",F54,")"),CONCATENATE(I54," - ",G54)),"") -> Alcir Santos Simões Junior - Reclamação Trabalhista (1000700-58.2021.5.02.0319) | AJ54: =IF(I54<>"",IF(F54<>"",CONCATENATE(I54," - ",G54," (",F54,")"),CONCATENATE(I54," - ",G54)),"") -> Alcir Santos Simões Junior - Reclamação Trabalhista (1000700-58.2021.5.02.0319)
B55: 49 | C55: Ativo | D55: Judicial | E55: Fase de Sentença | F55: 0011573-44.2021.5.15.0135 | G55: Reclamação Trabalhista | H55: Pessoa Física | I55: Ademilson Moreira de Souza | J55: Reclamante | K55: Votorantim Cimentos S/A | L55: Reclamado | M55: ADRIANO LOURENÇO MORAIS DOS SANTOS | N55: 143396.69 | S55: =IF(O55<>0,IF(P55<>0,SUM(P55+Q55*O55+O55*R55),IF(Q55<>0,SUM(P55+Q55*O55+O55*R55),"")),IF(P55<>0,SUM(P55+Q55*N55+N55*R55),IF(Q55<>0,SUM(P55+Q55*N55+N55*R55),""))) | T55: Não | V55: TRT da 15ª Região - Sao Paulo/Campinas | W55: Sorocaba | X55: 4ª Vara do Trabalho | Y55: Apresentadas contrarrazões de RO. Aguardando decisão. | Z55: 44488 | AB55: =IFERROR(IF(Z55<>"",IF(AA55="",CONCATENATE(DATEDIF(Z55,TODAY(),"D")," dias"),CONCATENATE(DATEDIF(Z55,AA55,"D")," dias")),""),"") -> 1591 dias | AD55: https://pje.trt15.jus.br/pjekz/processo/3006244/detalhe | AF55: =DATEDIF(TODAY(),U55,"D") -> #NUM! | AG55: =IFERROR(IF(Z55<>"",IF(AA55="",DATEDIF(Z55,TODAY(),"D"),DATEDIF(Z55,AA55,"D")),""),"") -> 1591 | AI55: =IF(I55<>"",IF(F55<>"",CONCATENATE(I55," - ",G55," (",F55,")"),CONCATENATE(I55," - ",G55)),"") -> Ademilson Moreira de Souza - Reclamação Trabalhista (0011573-44.2021.5.15.0135) | AJ55: =IF(I55<>"",IF(F55<>"",CONCATENATE(I55," - ",G55," (",F55,")"),CONCATENATE(I55," - ",G55)),"") -> Ademilson Moreira de Souza - Reclamação Trabalhista (0011573-44.2021.5.15.0135)
B56: 50 | C56: Ativo | D56: Judicial | E56: Fase de Execução | F56: 0011108-90.2021.5.15.0052 | G56: Reclamação Trabalhista | H56: Pessoa Física | I56: Micaela Da Silva Gomes | J56: Reclamante | K56: Brazão de Paula e Domingos Ltda | L56: Reclamado | M56: ADRIANO LOURENÇO MORAIS DOS SANTOS | N56: 20060.53 | S56: =IF(O56<>0,IF(P56<>0,SUM(P56+Q56*O56+O56*R56),IF(Q56<>0,SUM(P56+Q56*O56+O56*R56),"")),IF(P56<>0,SUM(P56+Q56*N56+N56*R56),IF(Q56<>0,SUM(P56+Q56*N56+N56*R56),""))) | T56: Não | V56: TRT da 15ª Região - Sao Paulo/Campinas | W56: Ituverava | X56: Vara de Ituverava | Y56: Prosseguiu para Execução | Z56: 44532 | AB56: =IFERROR(IF(Z56<>"",IF(AA56="",CONCATENATE(DATEDIF(Z56,TODAY(),"D")," dias"),CONCATENATE(DATEDIF(Z56,AA56,"D")," dias")),""),"") -> 1547 dias | AD56: https://pje.trt15.jus.br/pjekz/processo/3045022/detalhe | AF56: =DATEDIF(TODAY(),U56,"D") -> #NUM! | AG56: =IFERROR(IF(Z56<>"",IF(AA56="",DATEDIF(Z56,TODAY(),"D"),DATEDIF(Z56,AA56,"D")),""),"") -> 1547 | AI56: =IF(I56<>"",IF(F56<>"",CONCATENATE(I56," - ",G56," (",F56,")"),CONCATENATE(I56," - ",G56)),"") -> Micaela Da Silva Gomes - Reclamação Trabalhista (0011108-90.2021.5.15.0052) | AJ56: =IF(I56<>"",IF(F56<>"",CONCATENATE(I56," - ",G56," (",F56,")"),CONCATENATE(I56," - ",G56)),"") -> Micaela Da Silva Gomes - Reclamação Trabalhista (0011108-90.2021.5.15.0052)
B57: 51 | C57: Ativo | D57: Judicial | E57: Fase Inicial | F57: 0010703-50.2022.5.15.0042 | G57: Reclamação Trabalhista | H57: Pessoa Física | I57: Letícia Campos Jorge | J57: Reclamante | K57: Bravsec - Serviços Auxiliadores de Transportes Aéreo Eireli | L57: Reclamado | M57: ADRIANO LOURENÇO MORAIS DOS SANTOS | N57: 17421.73 | S57: =IF(O57<>0,IF(P57<>0,SUM(P57+Q57*O57+O57*R57),IF(Q57<>0,SUM(P57+Q57*O57+O57*R57),"")),IF(P57<>0,SUM(P57+Q57*N57+N57*R57),IF(Q57<>0,SUM(P57+Q57*N57+N57*R57),""))) | T57: Não | V57: TRT da 15ª Região - Sao Paulo/Campinas | W57: Ribeirão Preto | X57: 2ª Vara do Trabalho | Y57: Réu manifestoou massa falida. Vide processo nº 0219667-14.2022.819.0001 | Z57: 44680 | AB57: =IFERROR(IF(Z57<>"",IF(AA57="",CONCATENATE(DATEDIF(Z57,TODAY(),"D")," dias"),CONCATENATE(DATEDIF(Z57,AA57,"D")," dias")),""),"") -> 1399 dias | AD57: https://pje.trt15.jus.br/pjekz/processo/3212615/detalhe | AF57: =DATEDIF(TODAY(),U57,"D") -> #NUM! | AG57: =IFERROR(IF(Z57<>"",IF(AA57="",DATEDIF(Z57,TODAY(),"D"),DATEDIF(Z57,AA57,"D")),""),"") -> 1399 | AI57: =IF(I57<>"",IF(F57<>"",CONCATENATE(I57," - ",G57," (",F57,")"),CONCATENATE(I57," - ",G57)),"") -> Letícia Campos Jorge - Reclamação Trabalhista (0010703-50.2022.5.15.0042) | AJ57: =IF(I57<>"",IF(F57<>"",CONCATENATE(I57," - ",G57," (",F57,")"),CONCATENATE(I57," - ",G57)),"") -> Letícia Campos Jorge - Reclamação Trabalhista (0010703-50.2022.5.15.0042)
B58: 52 | C58: Encerrado | D58: Judicial | E58: Fase de Audiência | F58: 0010992-49.2022.5.15.0117 | G58: Reclamação Trabalhista | H58: Pessoa Jurídica | I58: Supermercados Big Compra Ltda. | J58: Reclamado | K58: Douglas Felippe Ventresche | L58: Reclamante | M58: ADRIANO LOURENÇO MORAIS DOS SANTOS | N58: 215165.3 | S58: =IF(O58<>0,IF(P58<>0,SUM(P58+Q58*O58+O58*R58),IF(Q58<>0,SUM(P58+Q58*O58+O58*R58),"")),IF(P58<>0,SUM(P58+Q58*N58+N58*R58),IF(Q58<>0,SUM(P58+Q58*N58+N58*R58),""))) | T58: Não | V58: TRT da 15ª Região - Sao Paulo/Campinas | W58: São Joaquim da Barra | X58: Vara de SJ. Da Barra | Y58: Audiência agendada | Z58: 44740 | AB58: =IFERROR(IF(Z58<>"",IF(AA58="",CONCATENATE(DATEDIF(Z58,TODAY(),"D")," dias"),CONCATENATE(DATEDIF(Z58,AA58,"D")," dias")),""),"") -> 1339 dias | AD58: https://pje.trt15.jus.br/pjekz/processo/3279091/detalhe | AF58: =DATEDIF(TODAY(),U58,"D") -> #NUM! | AG58: =IFERROR(IF(Z58<>"",IF(AA58="",DATEDIF(Z58,TODAY(),"D"),DATEDIF(Z58,AA58,"D")),""),"") -> 1339 | AI58: =IF(I58<>"",IF(F58<>"",CONCATENATE(I58," - ",G58," (",F58,")"),CONCATENATE(I58," - ",G58)),"") -> Supermercados Big Compra Ltda. - Reclamação Trabalhista (0010992-49.2022.5.15.0117) | AJ58: =IF(I58<>"",IF(F58<>"",CONCATENATE(I58," - ",G58," (",F58,")"),CONCATENATE(I58," - ",G58)),"") -> Supermercados Big Compra Ltda. - Reclamação Trabalhista (0010992-49.2022.5.15.0117)
B59: 53 | C59: Encerrado | D59: Judicial | E59: Fase de Audiência | F59: 0011237-75.2022.5.15.0015 | G59: Reclamação Trabalhista | H59: Pessoa Jurídica | I59: Supermercados Big Compra Ltda. | J59: Reclamado | K59: Robson Henrique Dos Santos | L59: Reclamante | M59: ADRIANO LOURENÇO MORAIS DOS SANTOS | N59: 257500.49 | S59: =IF(O59<>0,IF(P59<>0,SUM(P59+Q59*O59+O59*R59),IF(Q59<>0,SUM(P59+Q59*O59+O59*R59),"")),IF(P59<>0,SUM(P59+Q59*N59+N59*R59),IF(Q59<>0,SUM(P59+Q59*N59+N59*R59),""))) | T59: Não | V59: TRT da 15ª Região - Sao Paulo/Campinas | W59: Franca | X59: Vara do Trabalho de Franca | Y59: Audiência agendada | Z59: 44728 | AB59: =IFERROR(IF(Z59<>"",IF(AA59="",CONCATENATE(DATEDIF(Z59,TODAY(),"D")," dias"),CONCATENATE(DATEDIF(Z59,AA59,"D")," dias")),""),"") -> 1351 dias | AD59: https://pje.trt15.jus.br/pjekz/processo/3266457/detalhe | AF59: =DATEDIF(TODAY(),U59,"D") -> #NUM! | AG59: =IFERROR(IF(Z59<>"",IF(AA59="",DATEDIF(Z59,TODAY(),"D"),DATEDIF(Z59,AA59,"D")),""),"") -> 1351 | AI59: =IF(I59<>"",IF(F59<>"",CONCATENATE(I59," - ",G59," (",F59,")"),CONCATENATE(I59," - ",G59)),"") -> Supermercados Big Compra Ltda. - Reclamação Trabalhista (0011237-75.2022.5.15.0015) | AJ59: =IF(I59<>"",IF(F59<>"",CONCATENATE(I59," - ",G59," (",F59,")"),CONCATENATE(I59," - ",G59)),"") -> Supermercados Big Compra Ltda. - Reclamação Trabalhista (0011237-75.2022.5.15.0015)
B60: 54 | C60: Ativo | D60: Judicial | E60: Fase de Sentença | F60: 0012342-90.2022.5.15.0111 | G60: Reclamação Trabalhista | H60: Pessoa Física | I60: Cristiano Alves Dos Santos | J60: Reclamante | K60: Calblock Industria de Promoldados de Concreto Ltda | L60: Reclamado | M60: ADRIANO LOURENÇO MORAIS DOS SANTOS | N60: 129105 | S60: =IF(O60<>0,IF(P60<>0,SUM(P60+Q60*O60+O60*R60),IF(Q60<>0,SUM(P60+Q60*O60+O60*R60),"")),IF(P60<>0,SUM(P60+Q60*N60+N60*R60),IF(Q60<>0,SUM(P60+Q60*N60+N60*R60),""))) | T60: Não | V60: TRT da 15ª Região - Sao Paulo/Campinas | W60: Tietê | X60: Vara do trabalho de Tietê | Y60: Audiência agendada | Z60: 44887 | AB60: =IFERROR(IF(Z60<>"",IF(AA60="",CONCATENATE(DATEDIF(Z60,TODAY(),"D")," dias"),CONCATENATE(DATEDIF(Z60,AA60,"D")," dias")),""),"") -> 1192 dias | AD60: https://pje.trt15.jus.br/pjekz/processo/3442105/detalhe | AF60: =DATEDIF(TODAY(),U60,"D") -> #NUM! | AG60: =IFERROR(IF(Z60<>"",IF(AA60="",DATEDIF(Z60,TODAY(),"D"),DATEDIF(Z60,AA60,"D")),""),"") -> 1192 | AI60: =IF(I60<>"",IF(F60<>"",CONCATENATE(I60," - ",G60," (",F60,")"),CONCATENATE(I60," - ",G60)),"") -> Cristiano Alves Dos Santos - Reclamação Trabalhista (0012342-90.2022.5.15.0111) | AJ60: =IF(I60<>"",IF(F60<>"",CONCATENATE(I60," - ",G60," (",F60,")"),CONCATENATE(I60," - ",G60)),"") -> Cristiano Alves Dos Santos - Reclamação Trabalhista (0012342-90.2022.5.15.0111)
B61: 55 | C61: Encerrado | D61: Judicial | E61: Fase de Sentença | F61: 0011566-31.2022.5.15.0066 | G61: Reclamação Trabalhista | H61: Pessoa Jurídica | I61: Supermercados Big Compra Ltda. | J61: Reclamado | K61: Matheus Ubine da Silva | L61: Reclamante | M61: ADRIANO LOURENÇO MORAIS DOS SANTOS | N61: 87536.35 | S61: =IF(O61<>0,IF(P61<>0,SUM(P61+Q61*O61+O61*R61),IF(Q61<>0,SUM(P61+Q61*O61+O61*R61),"")),IF(P61<>0,SUM(P61+Q61*N61+N61*R61),IF(Q61<>0,SUM(P61+Q61*N61+N61*R61),""))) | T61: Não | V61: TRT da 15ª Região - Sao Paulo/Campinas | W61: Ribeirão Preto | X61: 9ª Vara do Trabalho | Y61: Acordo Homologado na Audiência | Z61: 44833 | AA61: 44885 | AB61: =IFERROR(IF(Z61<>"",IF(AA61="",CONCATENATE(DATEDIF(Z61,TODAY(),"D")," dias"),CONCATENATE(DATEDIF(Z61,AA61,"D")," dias")),""),"") -> 52 dias | AC61: Acordo | AF61: =DATEDIF(TODAY(),U61,"D") -> #NUM! | AG61: =IFERROR(IF(Z61<>"",IF(AA61="",DATEDIF(Z61,TODAY(),"D"),DATEDIF(Z61,AA61,"D")),""),"") -> 52 | AI61: =IF(I61<>"",IF(F61<>"",CONCATENATE(I61," - ",G61," (",F61,")"),CONCATENATE(I61," - ",G61)),"") -> Supermercados Big Compra Ltda. - Reclamação Trabalhista (0011566-31.2022.5.15.0066) | AJ61: =IF(I61<>"",IF(F61<>"",CONCATENATE(I61," - ",G61," (",F61,")"),CONCATENATE(I61," - ",G61)),"") -> Supermercados Big Compra Ltda. - Reclamação Trabalhista (0011566-31.2022.5.15.0066)
B62: 56 | C62: Encerrado | D62: Judicial | E62: Fase de Audiência | F62: 0011766-38.2022.5.15.0066 | G62: Reclamação Trabalhista | H62: Pessoa Jurídica | I62: Hit Car Centro Automotivo LITDA. | J62: Reclamado | K62: Eduardo Ferreira Farizatto | L62: Reclamante | M62: ADRIANO LOURENÇO MORAIS DOS SANTOS | N62: 23616 | S62: =IF(O62<>0,IF(P62<>0,SUM(P62+Q62*O62+O62*R62),IF(Q62<>0,SUM(P62+Q62*O62+O62*R62),"")),IF(P62<>0,SUM(P62+Q62*N62+N62*R62),IF(Q62<>0,SUM(P62+Q62*N62+N62*R62),""))) | T62: Não | V62: TRT da 15ª Região - Sao Paulo/Campinas | W62: Ribeirão Preto | X62: 3ª Vara do Trabalho | Y62: Acordo Homologado na Audiência | Z62: 44869 | AA62: 44986 | AB62: =IFERROR(IF(Z62<>"",IF(AA62="",CONCATENATE(DATEDIF(Z62,TODAY(),"D")," dias"),CONCATENATE(DATEDIF(Z62,AA62,"D")," dias")),""),"") -> 117 dias | AC62: Acordo | AD62: https://pje.trt15.jus.br/pjekz/processo/3426395/detalhe | AF62: =DATEDIF(TODAY(),U62,"D") -> #NUM! | AG62: =IFERROR(IF(Z62<>"",IF(AA62="",DATEDIF(Z62,TODAY(),"D"),DATEDIF(Z62,AA62,"D")),""),"") -> 117 | AI62: =IF(I62<>"",IF(F62<>"",CONCATENATE(I62," - ",G62," (",F62,")"),CONCATENATE(I62," - ",G62)),"") -> Hit Car Centro Automotivo LITDA. - Reclamação Trabalhista (0011766-38.2022.5.15.0066) | AJ62: =IF(I62<>"",IF(F62<>"",CONCATENATE(I62," - ",G62," (",F62,")"),CONCATENATE(I62," - ",G62)),"") -> Hit Car Centro Automotivo LITDA. - Reclamação Trabalhista (0011766-38.2022.5.15.0066)
B63: 57 | C63: Ativo | D63: Judicial | E63: Fase de Audiência | F63: 0010572-07.2023.5.15.0021 | G63: Reclamação Trabalhista | H63: Pessoa Física | I63: Ariane Frare | J63: Reclamante | K63: Lenita de Lourdes Oliveira Rocha Saciloto - ME | L63: Reclamado | M63: ADRIANO LOURENÇO MORAIS DOS SANTOS | N63: 96103.84 | S63: =IF(O63<>0,IF(P63<>0,SUM(P63+Q63*O63+O63*R63),IF(Q63<>0,SUM(P63+Q63*O63+O63*R63),"")),IF(P63<>0,SUM(P63+Q63*N63+N63*R63),IF(Q63<>0,SUM(P63+Q63*N63+N63*R63),""))) | T63: Não | V63: TRT da 15ª Região - Sao Paulo/Campinas | W63: Jundiaí | X63: 2ª Vara do Trabalho | Y63: Concluso para sentença | Z63: 45014 | AB63: =IFERROR(IF(Z63<>"",IF(AA63="",CONCATENATE(DATEDIF(Z63,TODAY(),"D")," dias"),CONCATENATE(DATEDIF(Z63,AA63,"D")," dias")),""),"") -> 1065 dias | AD63: https://pje.trt15.jus.br/pjekz/processo/3557276/detalhe | AF63: =DATEDIF(TODAY(),U63,"D") -> #NUM! | AG63: =IFERROR(IF(Z63<>"",IF(AA63="",DATEDIF(Z63,TODAY(),"D"),DATEDIF(Z63,AA63,"D")),""),"") -> 1065 | AI63: =IF(I63<>"",IF(F63<>"",CONCATENATE(I63," - ",G63," (",F63,")"),CONCATENATE(I63," - ",G63)),"") -> Ariane Frare - Reclamação Trabalhista (0010572-07.2023.5.15.0021) | AJ63: =IF(I63<>"",IF(F63<>"",CONCATENATE(I63," - ",G63," (",F63,")"),CONCATENATE(I63," - ",G63)),"") -> Ariane Frare - Reclamação Trabalhista (0010572-07.2023.5.15.0021)
B64: 58 | C64: Ativo | D64: Judicial | E64: Fase Inicial | F64: 1017186-53.2023.8.26.0506 | G64: Seguro / Remoção / Vaga Técnica | H64: Pessoa Jurídica | I64: André Luís Massaro | J64: Autor | K64: HDI Seguros S/A | L64: Réu | M64: FERES JUNQUEIRA NAJM | N64: 58080 | S64: =IF(O64<>0,IF(P64<>0,SUM(P64+Q64*O64+O64*R64),IF(Q64<>0,SUM(P64+Q64*O64+O64*R64),"")),IF(P64<>0,SUM(P64+Q64*N64+N64*R64),IF(Q64<>0,SUM(P64+Q64*N64+N64*R64),""))) | T64: Não | V64: 1ª Instância | W64: Ribeirão Preto | X64: 3ª Vara Cível | Y64: Aguardando decisão em processo diverso | Z64: 45041 | AB64: =IFERROR(IF(Z64<>"",IF(AA64="",CONCATENATE(DATEDIF(Z64,TODAY(),"D")," dias"),CONCATENATE(DATEDIF(Z64,AA64,"D")," dias")),""),"") -> 1038 dias | AD64: https://esaj.tjsp.jus.br/cpopg/show.do?processo.codigo=E2000PEZC0000&processo.foro=506&processo.numero=1017186-53.2023.8.26.0506 | AF64: =DATEDIF(TODAY(),U64,"D") -> #NUM! | AG64: =IFERROR(IF(Z64<>"",IF(AA64="",DATEDIF(Z64,TODAY(),"D"),DATEDIF(Z64,AA64,"D")),""),"") -> 1038 | AI64: =IF(I64<>"",IF(F64<>"",CONCATENATE(I64," - ",G64," (",F64,")"),CONCATENATE(I64," - ",G64)),"") -> André Luís Massaro - Seguro / Remoção / Vaga Técnica (1017186-53.2023.8.26.0506) | AJ64: =IF(I64<>"",IF(F64<>"",CONCATENATE(I64," - ",G64," (",F64,")"),CONCATENATE(I64," - ",G64)),"") -> André Luís Massaro - Seguro / Remoção / Vaga Técnica (1017186-53.2023.8.26.0506)
B65: 59 | C65: Ativo | D65: Judicial | E65: Fase de Audiência | F65: 0013034-94.2022.5.15.0077 | G65: Reclamação Trabalhista | H65: Pessoa Física | I65: Aline Cristina da Silva | J65: Reclamante | K65: Innara Industria Nacional de Aramados Ltda | L65: Reclamado | M65: ADRIANO LOURENÇO MORAIS DOS SANTOS | N65: 59901.2 | S65: =IF(O65<>0,IF(P65<>0,SUM(P65+Q65*O65+O65*R65),IF(Q65<>0,SUM(P65+Q65*O65+O65*R65),"")),IF(P65<>0,SUM(P65+Q65*N65+N65*R65),IF(Q65<>0,SUM(P65+Q65*N65+N65*R65),""))) | T65: Não | V65: TRT da 15ª Região - Sao Paulo/Campinas | W65: Indaiatuba | X65: Vara do Trabalho Indaiatuba | Y65: Houve intimação sobre o acórdão proferido. Aguardando despacho | Z65: 44914 | AB65: =IFERROR(IF(Z65<>"",IF(AA65="",CONCATENATE(DATEDIF(Z65,TODAY(),"D")," dias"),CONCATENATE(DATEDIF(Z65,AA65,"D")," dias")),""),"") -> 1165 dias | AD65: https://pje.trt15.jus.br/pjekz/processo/3467932/detalhe | AF65: =DATEDIF(TODAY(),U65,"D") -> #NUM! | AG65: =IFERROR(IF(Z65<>"",IF(AA65="",DATEDIF(Z65,TODAY(),"D"),DATEDIF(Z65,AA65,"D")),""),"") -> 1165 | AI65: =IF(I65<>"",IF(F65<>"",CONCATENATE(I65," - ",G65," (",F65,")"),CONCATENATE(I65," - ",G65)),"") -> Aline Cristina da Silva - Reclamação Trabalhista (0013034-94.2022.5.15.0077) | AJ65: =IF(I65<>"",IF(F65<>"",CONCATENATE(I65," - ",G65," (",F65,")"),CONCATENATE(I65," - ",G65)),"") -> Aline Cristina da Silva - Reclamação Trabalhista (0013034-94.2022.5.15.0077)
B66: 60 | C66: Ativo | D66: Judicial | E66: Fase Recursal | F66: 1001478-32.2021.5.02.0059 | G66: Reclamação Trabalhista | H66: Pessoa Física | I66: Paulo Artur da Silva | J66: Reclamante | K66: Transpass Transportes de Passageiros Ltda. | L66: Reclamada | M66: ADRIANO LOURENÇO MORAIS DOS SANTOS | N66: 442152.94 | S66: =IF(O66<>0,IF(P66<>0,SUM(P66+Q66*O66+O66*R66),IF(Q66<>0,SUM(P66+Q66*O66+O66*R66),"")),IF(P66<>0,SUM(P66+Q66*N66+N66*R66),IF(Q66<>0,SUM(P66+Q66*N66+N66*R66),""))) | T66: Não | V66: Tribunal de Justiça - São Paulo | W66: Tietê | X66: Vara do Tietê | Y66: Pagamento do art. 916, CPC | Z66: 44503 | AB66: =IFERROR(IF(Z66<>"",IF(AA66="",CONCATENATE(DATEDIF(Z66,TODAY(),"D")," dias"),CONCATENATE(DATEDIF(Z66,AA66,"D")," dias")),""),"") -> 1576 dias | AC66: Parcialmente Procedente | AD66: https://pje.tst.jus.br/consultaprocessual/detalhe-processo/1001478-32.2021.5.02.0059/3#d6a4b59 | AF66: =DATEDIF(TODAY(),U66,"D") -> #NUM! | AG66: =IFERROR(IF(Z66<>"",IF(AA66="",DATEDIF(Z66,TODAY(),"D"),DATEDIF(Z66,AA66,"D")),""),"") -> 1576 | AI66: =IF(I66<>"",IF(F66<>"",CONCATENATE(I66," - ",G66," (",F66,")"),CONCATENATE(I66," - ",G66)),"") -> Paulo Artur da Silva - Reclamação Trabalhista (1001478-32.2021.5.02.0059) | AJ66: =IF(I66<>"",IF(F66<>"",CONCATENATE(I66," - ",G66," (",F66,")"),CONCATENATE(I66," - ",G66)),"") -> Paulo Artur da Silva - Reclamação Trabalhista (1001478-32.2021.5.02.0059)
B67: 62 | C67: Ativo | D67: Judicial | E67: Fase Inicial | F67: 0010703-50.2022.5.15.0042 | G67: Reclamação Trabalhista | H67: Pessoa Física | I67: Letícia Campos Jorge | J67: Reclamante | K67: Bravsec - Serviços Auxiliadores de Transportes Aéreo Eireli | L67: Reclamado | M67: ADRIANO LOURENÇO MORAIS DOS SANTOS | N67: 17421.73 | S67: =IF(O67<>0,IF(P67<>0,SUM(P67+Q67*O67+O67*R67),IF(Q67<>0,SUM(P67+Q67*O67+O67*R67),"")),IF(P67<>0,SUM(P67+Q67*N67+N67*R67),IF(Q67<>0,SUM(P67+Q67*N67+N67*R67),""))) | T67: Não | V67: TRT da 15ª Região - Sao Paulo/Campinas | W67: Ribeirão Preto | X67: 2ª do Trabalho de Ribeirão Preto | Y67: Aguardando a audiência inicial | Z67: 44680 | AB67: =IFERROR(IF(Z67<>"",IF(AA67="",CONCATENATE(DATEDIF(Z67,TODAY(),"D")," dias"),CONCATENATE(DATEDIF(Z67,AA67,"D")," dias")),""),"") -> 1399 dias | AD67: https://pje.trt15.jus.br/pjekz/processo/3212615/detalhe | AF67: =DATEDIF(TODAY(),U67,"D") -> #NUM! | AG67: =IFERROR(IF(Z67<>"",IF(AA67="",DATEDIF(Z67,TODAY(),"D"),DATEDIF(Z67,AA67,"D")),""),"") -> 1399 | AI67: =IF(I67<>"",IF(F67<>"",CONCATENATE(I67," - ",G67," (",F67,")"),CONCATENATE(I67," - ",G67)),"") -> Letícia Campos Jorge - Reclamação Trabalhista (0010703-50.2022.5.15.0042) | AJ67: =IF(I67<>"",IF(F67<>"",CONCATENATE(I67," - ",G67," (",F67,")"),CONCATENATE(I67," - ",G67)),"") -> Letícia Campos Jorge - Reclamação Trabalhista (0010703-50.2022.5.15.0042)
B68: 63 | C68: Ativo | D68: Judicial | E68: Fase Inicial | F68: 1011289-04.2023.8.26.0196 | G68: Seguro / Remoção / Vaga Técnica | H68: Pessoa Jurídica | I68: Renew - Sistemas de Recuperação e Polimento Automotivo Ltda. | J68: Autor | K68: Bradesco Seguros S/A | L68: Réu | M68: FERES JUNQUEIRA NAJM | N68: 14700 | S68: =IF(O68<>0,IF(P68<>0,SUM(P68+Q68*O68+O68*R68),IF(Q68<>0,SUM(P68+Q68*O68+O68*R68),"")),IF(P68<>0,SUM(P68+Q68*N68+N68*R68),IF(Q68<>0,SUM(P68+Q68*N68+N68*R68),""))) | T68: Não | V68: 1ª Instância | W68: Franca | X68: 3ª Vara Cível | Y68: Foram emitidas as certidões de trânsito em julgado e de remessa. Aguardando despacho | Z68: 45062 | AB68: =IFERROR(IF(Z68<>"",IF(AA68="",CONCATENATE(DATEDIF(Z68,TODAY(),"D")," dias"),CONCATENATE(DATEDIF(Z68,AA68,"D")," dias")),""),"") -> 1017 dias | AD68: https://esaj.tjsp.jus.br/cpopg/show.do?processo.codigo=5G000F80V0000&processo.foro=196&processo.numero=1011289-04.2023.8.26.0196 | AF68: =DATEDIF(TODAY(),U68,"D") -> #NUM! | AG68: =IFERROR(IF(Z68<>"",IF(AA68="",DATEDIF(Z68,TODAY(),"D"),DATEDIF(Z68,AA68,"D")),""),"") -> 1017 | AI68: =IF(I68<>"",IF(F68<>"",CONCATENATE(I68," - ",G68," (",F68,")"),CONCATENATE(I68," - ",G68)),"") -> Renew - Sistemas de Recuperação e Polimento Automotivo Ltda. - Seguro / Remoção / Vaga Técnica (1011289-04.2023.8.26.0196) | AJ68: =IF(I68<>"",IF(F68<>"",CONCATENATE(I68," - ",G68," (",F68,")"),CONCATENATE(I68," - ",G68)),"") -> Renew - Sistemas de Recuperação e Polimento Automotivo Ltda. - Seguro / Remoção / Vaga Técnica (1011289-04.2023.8.26.0196)
B69: 64 | C69: Ativo | D69: Judicial | E69: Fase de Contestação | F69: 1016709-30.2023.8.26.0506 | G69: Ação Indenizatória | H69: Pessoa Jurídica | I69: Pepe Oficina | J69: Requerido | K69: Gustavo Dechechi Inojossa | L69: Requerente | M69: FERES JUNQUEIRA NAJM | N69: 24750.54 | S69: =IF(O69<>0,IF(P69<>0,SUM(P69+Q69*O69+O69*R69),IF(Q69<>0,SUM(P69+Q69*O69+O69*R69),"")),IF(P69<>0,SUM(P69+Q69*N69+N69*R69),IF(Q69<>0,SUM(P69+Q69*N69+N69*R69),""))) | T69: Sim | V69: 1ª Instância | W69: Ribeirão Preto | X69: 7ª Vara Cível | Y69: Decisão intima para exibição de documentos | Z69: 45036 | AB69: =IFERROR(IF(Z69<>"",IF(AA69="",CONCATENATE(DATEDIF(Z69,TODAY(),"D")," dias"),CONCATENATE(DATEDIF(Z69,AA69,"D")," dias")),""),"") -> 1043 dias | AF69: =DATEDIF(TODAY(),U69,"D") -> #NUM! | AG69: =IFERROR(IF(Z69<>"",IF(AA69="",DATEDIF(Z69,TODAY(),"D"),DATEDIF(Z69,AA69,"D")),""),"") -> 1043 | AI69: =IF(I69<>"",IF(F69<>"",CONCATENATE(I69," - ",G69," (",F69,")"),CONCATENATE(I69," - ",G69)),"") -> Pepe Oficina - Ação Indenizatória (1016709-30.2023.8.26.0506) | AJ69: =IF(I69<>"",IF(F69<>"",CONCATENATE(I69," - ",G69," (",F69,")"),CONCATENATE(I69," - ",G69)),"") -> Pepe Oficina - Ação Indenizatória (1016709-30.2023.8.26.0506)
B70: 65 | C70: Ativo | D70: Judicial | E70: Fase Inicial | F70: 1015049-58.2023.8.26.0196 | G70: Seguro / Remoção / Vaga Técnica | H70: Pessoa Jurídica | I70: Renew - Sistemas de Recuperação e Polimento Automotivo Ltda. | J70: Requerente | K70: HDI Seguros S/A | L70: Requerido | M70: FERES JUNQUEIRA NAJM | N70: 10500 | S70: =IF(O70<>0,IF(P70<>0,SUM(P70+Q70*O70+O70*R70),IF(Q70<>0,SUM(P70+Q70*O70+O70*R70),"")),IF(P70<>0,SUM(P70+Q70*N70+N70*R70),IF(Q70<>0,SUM(P70+Q70*N70+N70*R70),""))) | T70: Não | V70: 1ª Instância | W70: Franca | X70: 2ª Vara Cível | Y70: Aguardando despacho do Juiz | Z70: 45104 | AB70: =IFERROR(IF(Z70<>"",IF(AA70="",CONCATENATE(DATEDIF(Z70,TODAY(),"D")," dias"),CONCATENATE(DATEDIF(Z70,AA70,"D")," dias")),""),"") -> 975 dias | AD70: https://esaj.tjsp.jus.br/cpopg/show.do?processo.codigo=5G000FD7R0000&processo.foro=196&processo.numero=1015049-58.2023.8.26.0196 | AF70: =DATEDIF(TODAY(),U70,"D") -> #NUM! | AG70: =IFERROR(IF(Z70<>"",IF(AA70="",DATEDIF(Z70,TODAY(),"D"),DATEDIF(Z70,AA70,"D")),""),"") -> 975 | AI70: =IF(I70<>"",IF(F70<>"",CONCATENATE(I70," - ",G70," (",F70,")"),CONCATENATE(I70," - ",G70)),"") -> Renew - Sistemas de Recuperação e Polimento Automotivo Ltda. - Seguro / Remoção / Vaga Técnica (1015049-58.2023.8.26.0196) | AJ70: =IF(I70<>"",IF(F70<>"",CONCATENATE(I70," - ",G70," (",F70,")"),CONCATENATE(I70," - ",G70)),"") -> Renew - Sistemas de Recuperação e Polimento Automotivo Ltda. - Seguro / Remoção / Vaga Técnica (1015049-58.2023.8.26.0196)
B71: 66 | C71: Encerrado | D71: Judicial | E71: Fase Inicial | F71: 1001927-14.2023.8.26.0572 | G71: Ação Indenizatória | H71: Pessoa Jurídica | I71: Supermercados Big Compra Ltda. | J71: Requerido | K71: Maria da Aparecida Rosa de Faria | L71: Requerente | M71: FERES JUNQUEIRA NAJM | N71: 20000 | S71: =IF(O71<>0,IF(P71<>0,SUM(P71+Q71*O71+O71*R71),IF(Q71<>0,SUM(P71+Q71*O71+O71*R71),"")),IF(P71<>0,SUM(P71+Q71*N71+N71*R71),IF(Q71<>0,SUM(P71+Q71*N71+N71*R71),""))) | T71: Não | V71: 1ª Instância | W71: São Joaquim da Barra | X71: Juizado Especial Cível | Y71: Arquivado | Z71: 45085 | AB71: =IFERROR(IF(Z71<>"",IF(AA71="",CONCATENATE(DATEDIF(Z71,TODAY(),"D")," dias"),CONCATENATE(DATEDIF(Z71,AA71,"D")," dias")),""),"") -> 994 dias | AD71: https://esaj.tjsp.jus.br/cpopg/show.do?processo.codigo=FW0002V240000&processo.foro=572&processo.numero=1001927-14.2023.8.26.0572 | AF71: =DATEDIF(TODAY(),U71,"D") -> #NUM! | AG71: =IFERROR(IF(Z71<>"",IF(AA71="",DATEDIF(Z71,TODAY(),"D"),DATEDIF(Z71,AA71,"D")),""),"") -> 994 | AI71: =IF(I71<>"",IF(F71<>"",CONCATENATE(I71," - ",G71," (",F71,")"),CONCATENATE(I71," - ",G71)),"") -> Supermercados Big Compra Ltda. - Ação Indenizatória (1001927-14.2023.8.26.0572) | AJ71: =IF(I71<>"",IF(F71<>"",CONCATENATE(I71," - ",G71," (",F71,")"),CONCATENATE(I71," - ",G71)),"") -> Supermercados Big Compra Ltda. - Ação Indenizatória (1001927-14.2023.8.26.0572)
B72: 67 | C72: Ativo | D72: Judicial | E72: Fase de Sentença | F72: 1014827-90.2023.8.26.0196 | G72: Medida Cautelar | H72: Pessoa Jurídica | I72: Supermercados Big Compra Ltda. | J72: Requerente | K72: Fundação de Proteção e Defesa do Consumidor | L72: Requerido | M72: FERES JUNQUEIRA NAJM | N72: 35408.41 | S72: =IF(O72<>0,IF(P72<>0,SUM(P72+Q72*O72+O72*R72),IF(Q72<>0,SUM(P72+Q72*O72+O72*R72),"")),IF(P72<>0,SUM(P72+Q72*N72+N72*R72),IF(Q72<>0,SUM(P72+Q72*N72+N72*R72),""))) | T72: Não | V72: 1ª Instância | W72: Franca | X72: Vara da Fazenda Pública | Y72: Autos remetidos ao TJ devido à apelação | Z72: 45100 | AB72: =IFERROR(IF(Z72<>"",IF(AA72="",CONCATENATE(DATEDIF(Z72,TODAY(),"D")," dias"),CONCATENATE(DATEDIF(Z72,AA72,"D")," dias")),""),"") -> 979 dias | AD72: https://esaj.tjsp.jus.br/cpopg/show.do?processo.codigo=5G000FCVQ0000&processo.foro=196&processo.numero=1014827-90.2023.8.26.0196 | AF72: =DATEDIF(TODAY(),U72,"D") -> #NUM! | AG72: =IFERROR(IF(Z72<>"",IF(AA72="",DATEDIF(Z72,TODAY(),"D"),DATEDIF(Z72,AA72,"D")),""),"") -> 979 | AI72: =IF(I72<>"",IF(F72<>"",CONCATENATE(I72," - ",G72," (",F72,")"),CONCATENATE(I72," - ",G72)),"") -> Supermercados Big Compra Ltda. - Medida Cautelar (1014827-90.2023.8.26.0196) | AJ72: =IF(I72<>"",IF(F72<>"",CONCATENATE(I72," - ",G72," (",F72,")"),CONCATENATE(I72," - ",G72)),"") -> Supermercados Big Compra Ltda. - Medida Cautelar (1014827-90.2023.8.26.0196)
B73: 68 | C73: Encerrado | D73: Judicial | E73: Fase Inicial | F73: 1030980-44.2023.8.26.0506 | G73: Medida Cautelar | H73: Pessoa Física | I73: Álvaro de Souza Rodriguês Pinheiro | J73: Requerente | K73: Unaerp - SEB COC | L73: Requerido | M73: FERES JUNQUEIRA NAJM | N73: 1000 | S73: =IF(O73<>0,IF(P73<>0,SUM(P73+Q73*O73+O73*R73),IF(Q73<>0,SUM(P73+Q73*O73+O73*R73),"")),IF(P73<>0,SUM(P73+Q73*N73+N73*R73),IF(Q73<>0,SUM(P73+Q73*N73+N73*R73),""))) | T73: Sim | V73: 1ª Instância | W73: Ribeirão Preto | X73: 9ª Vara Cível | Y73: Arquivado | Z73: 45117 | AB73: =IFERROR(IF(Z73<>"",IF(AA73="",CONCATENATE(DATEDIF(Z73,TODAY(),"D")," dias"),CONCATENATE(DATEDIF(Z73,AA73,"D")," dias")),""),"") -> 962 dias | AD73: https://esaj.tjsp.jus.br/cpopg/show.do?processo.codigo=E2000PVPJ0000&processo.foro=506&processo.numero=1030980-44.2023.8.26.0506 | AF73: =DATEDIF(TODAY(),U73,"D") -> #NUM! | AG73: =IFERROR(IF(Z73<>"",IF(AA73="",DATEDIF(Z73,TODAY(),"D"),DATEDIF(Z73,AA73,"D")),""),"") -> 962 | AI73: =IF(I73<>"",IF(F73<>"",CONCATENATE(I73," - ",G73," (",F73,")"),CONCATENATE(I73," - ",G73)),"") -> Álvaro de Souza Rodriguês Pinheiro - Medida Cautelar (1030980-44.2023.8.26.0506) | AJ73: =IF(I73<>"",IF(F73<>"",CONCATENATE(I73," - ",G73," (",F73,")"),CONCATENATE(I73," - ",G73)),"") -> Álvaro de Souza Rodriguês Pinheiro - Medida Cautelar (1030980-44.2023.8.26.0506)
B74: 69 | C74: Encerrado | D74: Judicial | E74: Fase Inicial | F74: 1033636-71.2023.8.26.0506 | G74: Medida Cautelar | H74: Pessoa Física | I74: Tomas Yung Joon Kim | J74: Requerente | K74: Centro Médico de Ribeirão Preto - Associação Paulista de Médico | L74: Requerido | M74: FERES JUNQUEIRA NAJM | N74: 1000 | S74: =IF(O74<>0,IF(P74<>0,SUM(P74+Q74*O74+O74*R74),IF(Q74<>0,SUM(P74+Q74*O74+O74*R74),"")),IF(P74<>0,SUM(P74+Q74*N74+N74*R74),IF(Q74<>0,SUM(P74+Q74*N74+N74*R74),""))) | T74: Não | V74: 1ª Instância | W74: Ribeirão Preto | X74: 5ª Vara Cível | Y74: Arquivado | Z74: 45128 | AB74: =IFERROR(IF(Z74<>"",IF(AA74="",CONCATENATE(DATEDIF(Z74,TODAY(),"D")," dias"),CONCATENATE(DATEDIF(Z74,AA74,"D")," dias")),""),"") -> 951 dias | AD74: https://esaj.tjsp.jus.br/cpopg/show.do?processo.codigo=E2000PYO90000&processo.foro=506&processo.numero=1033636-71.2023.8.26.0506 | AF74: =DATEDIF(TODAY(),U74,"D") -> #NUM! | AG74: =IFERROR(IF(Z74<>"",IF(AA74="",DATEDIF(Z74,TODAY(),"D"),DATEDIF(Z74,AA74,"D")),""),"") -> 951 | AI74: =IF(I74<>"",IF(F74<>"",CONCATENATE(I74," - ",G74," (",F74,")"),CONCATENATE(I74," - ",G74)),"") -> Tomas Yung Joon Kim - Medida Cautelar (1033636-71.2023.8.26.0506) | AJ74: =IF(I74<>"",IF(F74<>"",CONCATENATE(I74," - ",G74," (",F74,")"),CONCATENATE(I74," - ",G74)),"") -> Tomas Yung Joon Kim - Medida Cautelar (1033636-71.2023.8.26.0506)
B75: 70 | C75: Encerrado | D75: Judicial | E75: Fase Inicial | F75: 1034217-86.2023.8.26.0506 | G75: Seguro / Remoção / Vaga Técnica | H75: Pessoa Jurídica | I75: Pepe Oficina | J75: Autor | K75: Mapfre Seguros Gerais S/A | L75: Réu | M75: FERES JUNQUEIRA NAJM | N75: 3200 | S75: =IF(O75<>0,IF(P75<>0,SUM(P75+Q75*O75+O75*R75),IF(Q75<>0,SUM(P75+Q75*O75+O75*R75),"")),IF(P75<>0,SUM(P75+Q75*N75+N75*R75),IF(Q75<>0,SUM(P75+Q75*N75+N75*R75),""))) | T75: Não | V75: 1ª Instância | W75: Ribeirão Preto | X75: 2ª Vara Cível | Y75: Aguardando a extinção e arquivamento do processo | Z75: 45132 | AB75: =IFERROR(IF(Z75<>"",IF(AA75="",CONCATENATE(DATEDIF(Z75,TODAY(),"D")," dias"),CONCATENATE(DATEDIF(Z75,AA75,"D")," dias")),""),"") -> 947 dias | AC75: Acordo | AD75: https://esaj.tjsp.jus.br/cpopg/show.do?processo.codigo=E2000PZAE0000&processo.foro=506&processo.numero=1034217-86.2023.8.26.0506 | AF75: =DATEDIF(TODAY(),U75,"D") -> #NUM! | AG75: =IFERROR(IF(Z75<>"",IF(AA75="",DATEDIF(Z75,TODAY(),"D"),DATEDIF(Z75,AA75,"D")),""),"") -> 947 | AI75: =IF(I75<>"",IF(F75<>"",CONCATENATE(I75," - ",G75," (",F75,")"),CONCATENATE(I75," - ",G75)),"") -> Pepe Oficina - Seguro / Remoção / Vaga Técnica (1034217-86.2023.8.26.0506) | AJ75: =IF(I75<>"",IF(F75<>"",CONCATENATE(I75," - ",G75," (",F75,")"),CONCATENATE(I75," - ",G75)),"") -> Pepe Oficina - Seguro / Remoção / Vaga Técnica (1034217-86.2023.8.26.0506)
B76: 71 | C76: Encerrado | D76: Judicial | E76: Fase Inicial | F76: 1013033-34.2023.8.26.0196 | G76: Ação Monitória | H76: Pessoa Jurídica | I76: Renew - Sistemas de Recuperação e Polimento Automotivo Ltda. | J76: Autor | K76: Grande São Paulo Com Peças Ltda. EP. | L76: Réu | M76: FERES JUNQUEIRA NAJM | N76: 4000 | S76: =IF(O76<>0,IF(P76<>0,SUM(P76+Q76*O76+O76*R76),IF(Q76<>0,SUM(P76+Q76*O76+O76*R76),"")),IF(P76<>0,SUM(P76+Q76*N76+N76*R76),IF(Q76<>0,SUM(P76+Q76*N76+N76*R76),""))) | T76: =IF(P76<>0,IF(Q76<>0,SUM(Q76+R76*P76+P76*S76),IF(R76<>0,SUM(Q76+R76*P76+P76*S76),"")),IF(Q76<>0,SUM(Q76+R76*O76+O76*S76),IF(R76<>0,SUM(Q76+R76*O76+O76*S76),""))) | V76: 1ª Instância | W76: Ribeirão Preto | X76: Foro Regional de Ipiranga/SP | Y76: Arquivado | Z76: 45079 | AB76: =IFERROR(IF(Z76<>"",IF(AA76="",CONCATENATE(DATEDIF(Z76,TODAY(),"D")," dias"),CONCATENATE(DATEDIF(Z76,AA76,"D")," dias")),""),"") -> 1000 dias | AD76: https://esaj.tjsp.jus.br/cpopg/show.do?processo.codigo=5G000FAH50000&processo.foro=196&conversationId=&cbPesquisa=NMPARTE&dadosConsulta.valorConsulta=Renew&cdForo=196&paginaConsulta=1 | AF76: =DATEDIF(TODAY(),U76,"D") -> #NUM! | AG76: =IFERROR(IF(Z76<>"",IF(AA76="",DATEDIF(Z76,TODAY(),"D"),DATEDIF(Z76,AA76,"D")),""),"") -> 1000 | AI76: =IF(I76<>"",IF(F76<>"",CONCATENATE(I76," - ",G76," (",F76,")"),CONCATENATE(I76," - ",G76)),"") -> Renew - Sistemas de Recuperação e Polimento Automotivo Ltda. - Ação Monitória (1013033-34.2023.8.26.0196) | AJ76: =IF(I76<>"",IF(F76<>"",CONCATENATE(I76," - ",G76," (",F76,")"),CONCATENATE(I76," - ",G76)),"") -> Renew - Sistemas de Recuperação e Polimento Automotivo Ltda. - Ação Monitória (1013033-34.2023.8.26.0196)
B77: 72 | C77: Encerrado | D77: Judicial | E77: Fase Recursal | F77: 2202912-49.2023.8.26.0000 | G77: Agravo de Instrumento | H77: Pessoa Física | I77: Tomas Yung Joon Kim | J77: Agravante | K77: Centro Médico de Ribeirão Preto - Associação Paulista de Médico | L77: Agravado | M77: FERES JUNQUEIRA NAJM | N77: 1000 | S77: =IF(O77<>0,IF(P77<>0,SUM(P77+Q77*O77+O77*R77),IF(Q77<>0,SUM(P77+Q77*O77+O77*R77),"")),IF(P77<>0,SUM(P77+Q77*N77+N77*R77),IF(Q77<>0,SUM(P77+Q77*N77+N77*R77),""))) | T77: Não | V77: Tribunal de Justiça - São Paulo | W77: São Paulo | X77: 2ª Câmara de Direito Privado | Y77: Julgado | Z77: 45142 | AB77: =IFERROR(IF(Z77<>"",IF(AA77="",CONCATENATE(DATEDIF(Z77,TODAY(),"D")," dias"),CONCATENATE(DATEDIF(Z77,AA77,"D")," dias")),""),"") -> 937 dias | AD77: https://esaj.tjsp.jus.br/cposg/search.do?conversationId=&paginaConsulta=0&cbPesquisa=NUMPROC&numeroDigitoAnoUnificado=2202912-49.2023&foroNumeroUnificado=0000&dePesquisaNuUnificado=2202912-49.2023.8.26.0000&dePesquisaNuUnificado=UNIFICADO&dePesquisa=&tipoNuProcesso=UNIFICADO | AF77: =DATEDIF(TODAY(),U77,"D") -> #NUM! | AG77: =IFERROR(IF(Z77<>"",IF(AA77="",DATEDIF(Z77,TODAY(),"D"),DATEDIF(Z77,AA77,"D")),""),"") -> 937 | AI77: =IF(I77<>"",IF(F77<>"",CONCATENATE(I77," - ",G77," (",F77,")"),CONCATENATE(I77," - ",G77)),"") -> Tomas Yung Joon Kim - Agravo de Instrumento (2202912-49.2023.8.26.0000) | AJ77: =IF(I77<>"",IF(F77<>"",CONCATENATE(I77," - ",G77," (",F77,")"),CONCATENATE(I77," - ",G77)),"") -> Tomas Yung Joon Kim - Agravo de Instrumento (2202912-49.2023.8.26.0000)
B78: 73 | C78: Encerrado | D78: Judicial | E78: Fase de Execução | F78: 0009051-50.2022.8.26.0071 | G78: Ação de Cumprimento | H78: Pessoa Física | I78: Ricardo Henrique Queiroz de Souza | J78: Réu | K78: Associação Ranieri de Educação e Cultura | L78: Autor | M78: FERES JUNQUEIRA NAJM | N78: 8062.64 | S78: =IF(O78<>0,IF(P78<>0,SUM(P78+Q78*O78+O78*R78),IF(Q78<>0,SUM(P78+Q78*O78+O78*R78),"")),IF(P78<>0,SUM(P78+Q78*N78+N78*R78),IF(Q78<>0,SUM(P78+Q78*N78+N78*R78),""))) | V78: 1ª Instância | W78: Bauru | X78: 4ª Vara Cível | Y78: Protocolar uma petição de impugnação da penhora | Z78: 44742 | AB78: =IFERROR(IF(Z78<>"",IF(AA78="",CONCATENATE(DATEDIF(Z78,TODAY(),"D")," dias"),CONCATENATE(DATEDIF(Z78,AA78,"D")," dias")),""),"") -> 1337 dias | AD78: https://esaj.tjsp.jus.br/cpopg/show.do?processo.codigo=1Z000HYHF0000&processo.foro=71&processo.numero=0009051-50.2022.8.26.0071 | AF78: =DATEDIF(TODAY(),U78,"D") -> #NUM! | AG78: =IFERROR(IF(Z78<>"",IF(AA78="",DATEDIF(Z78,TODAY(),"D"),DATEDIF(Z78,AA78,"D")),""),"") -> 1337 | AI78: =IF(I78<>"",IF(F78<>"",CONCATENATE(I78," - ",G78," (",F78,")"),CONCATENATE(I78," - ",G78)),"") -> Ricardo Henrique Queiroz de Souza - Ação de Cumprimento (0009051-50.2022.8.26.0071) | AJ78: =IF(I78<>"",IF(F78<>"",CONCATENATE(I78," - ",G78," (",F78,")"),CONCATENATE(I78," - ",G78)),"") -> Ricardo Henrique Queiroz de Souza - Ação de Cumprimento (0009051-50.2022.8.26.0071)
B79: 74 | C79: Encerrado | D79: Judicial | E79: Fase Recursal | F79: 2201021-90.2023.8.26.0000 | G79: Agravo de Instrumento | H79: Pessoa Física | I79: Álvaro de Souza Rodriguês Pinheiro | J79: Agravante | K79: Unaerp - SEB COC | L79: Agravado | M79: FERES JUNQUEIRA NAJM | N79: 1000 | S79: =IF(O79<>0,IF(P79<>0,SUM(P79+Q79*O79+O79*R79),IF(Q79<>0,SUM(P79+Q79*O79+O79*R79),"")),IF(P79<>0,SUM(P79+Q79*N79+N79*R79),IF(Q79<>0,SUM(P79+Q79*N79+N79*R79),""))) | T79: Não | V79: Tribunal de Justiça - São Paulo | W79: São Paulo | X79: 7ª Câmara de Direito Privado | Y79: Julgado | Z79: 45141 | AB79: =IFERROR(IF(Z79<>"",IF(AA79="",CONCATENATE(DATEDIF(Z79,TODAY(),"D")," dias"),CONCATENATE(DATEDIF(Z79,AA79,"D")," dias")),""),"") -> 938 dias | AD79: https://esaj.tjsp.jus.br/cposg/search.do?conversationId=&paginaConsulta=0&cbPesquisa=NUMPROC&numeroDigitoAnoUnificado=2201021-90.2023&foroNumeroUnificado=0000&dePesquisaNuUnificado=2201021-90.2023.8.26.0000&dePesquisaNuUnificado=UNIFICADO&dePesquisa=&tipoNuProcesso=UNIFICADO# | AF79: =DATEDIF(TODAY(),U79,"D") -> #NUM! | AG79: =IFERROR(IF(Z79<>"",IF(AA79="",DATEDIF(Z79,TODAY(),"D"),DATEDIF(Z79,AA79,"D")),""),"") -> 938 | AI79: =IF(I79<>"",IF(F79<>"",CONCATENATE(I79," - ",G79," (",F79,")"),CONCATENATE(I79," - ",G79)),"") -> Álvaro de Souza Rodriguês Pinheiro - Agravo de Instrumento (2201021-90.2023.8.26.0000) | AJ79: =IF(I79<>"",IF(F79<>"",CONCATENATE(I79," - ",G79," (",F79,")"),CONCATENATE(I79," - ",G79)),"") -> Álvaro de Souza Rodriguês Pinheiro - Agravo de Instrumento (2201021-90.2023.8.26.0000)
B80: 75 | C80: Ativo | D80: Judicial | E80: Fase Recursal | F80: 1037465-60.2023.8.26.0506 | G80: Ação Regressiva | H80: Pessoa Jurídica | I80: Pepe Oficina | J80: Autor | K80: Mistui Sumitomo Seguros S/A | L80: Réu | M80: FERES JUNQUEIRA NAJM | N80: 2198.31 | S80: =IF(O80<>0,IF(P80<>0,SUM(P80+Q80*O80+O80*R80),IF(Q80<>0,SUM(P80+Q80*O80+O80*R80),"")),IF(P80<>0,SUM(P80+Q80*N80+N80*R80),IF(Q80<>0,SUM(P80+Q80*N80+N80*R80),""))) | T80: Não | V80: 1ª Instância | W80: Ribeirão Preto | X80: 5ª Vara Cível | Y80: Concluso para sentença | Z80: 45147 | AB80: =IFERROR(IF(Z80<>"",IF(AA80="",CONCATENATE(DATEDIF(Z80,TODAY(),"D")," dias"),CONCATENATE(DATEDIF(Z80,AA80,"D")," dias")),""),"") -> 932 dias | AD80: https://esaj.tjsp.jus.br/cpopg/show.do?processo.codigo=E2000Q2YY0000&processo.foro=506&processo.numero=1037465-60.2023.8.26.0506 | AF80: =DATEDIF(TODAY(),U80,"D") -> #NUM! | AG80: =IFERROR(IF(Z80<>"",IF(AA80="",DATEDIF(Z80,TODAY(),"D"),DATEDIF(Z80,AA80,"D")),""),"") -> 932 | AI80: =IF(I80<>"",IF(F80<>"",CONCATENATE(I80," - ",G80," (",F80,")"),CONCATENATE(I80," - ",G80)),"") -> Pepe Oficina - Ação Regressiva (1037465-60.2023.8.26.0506) | AJ80: =IF(I80<>"",IF(F80<>"",CONCATENATE(I80," - ",G80," (",F80,")"),CONCATENATE(I80," - ",G80)),"") -> Pepe Oficina - Ação Regressiva (1037465-60.2023.8.26.0506)
B81: 76 | C81: Encerrado | D81: Judicial | E81: Fase Inicial | F81: 1037354-76.2023.8.26.0506 | G81: Ação de Cobrança | H81: Pessoa Física | I81: Adalgisa Pereira Silveira | J81: Autor | K81: Tokio Marine Seguradora S/A | L81: Réu | M81: FERES JUNQUEIRA NAJM | N81: 11807 | S81: =IF(O81<>0,IF(P81<>0,SUM(P81+Q81*O81+O81*R81),IF(Q81<>0,SUM(P81+Q81*O81+O81*R81),"")),IF(P81<>0,SUM(P81+Q81*N81+N81*R81),IF(Q81<>0,SUM(P81+Q81*N81+N81*R81),""))) | T81: Não | V81: 1ª Instância | W81: Ribeirão Preto | X81: 1ª Vara Cível | Y81: Aguardando o arquivamento e extinção | Z81: 45147 | AB81: =IFERROR(IF(Z81<>"",IF(AA81="",CONCATENATE(DATEDIF(Z81,TODAY(),"D")," dias"),CONCATENATE(DATEDIF(Z81,AA81,"D")," dias")),""),"") -> 932 dias | AD81: https://esaj.tjsp.jus.br/cpopg/show.do?processo.codigo=E2000Q2UP0000&processo.foro=506&processo.numero=1037354-76.2023.8.26.0506 | AF81: =DATEDIF(TODAY(),U81,"D") -> #NUM! | AG81: =IFERROR(IF(Z81<>"",IF(AA81="",DATEDIF(Z81,TODAY(),"D"),DATEDIF(Z81,AA81,"D")),""),"") -> 932 | AI81: =IF(I81<>"",IF(F81<>"",CONCATENATE(I81," - ",G81," (",F81,")"),CONCATENATE(I81," - ",G81)),"") -> Adalgisa Pereira Silveira - Ação de Cobrança (1037354-76.2023.8.26.0506) | AJ81: =IF(I81<>"",IF(F81<>"",CONCATENATE(I81," - ",G81," (",F81,")"),CONCATENATE(I81," - ",G81)),"") -> Adalgisa Pereira Silveira - Ação de Cobrança (1037354-76.2023.8.26.0506)
B82: 77 | C82: Encerrado | D82: Judicial | E82: Fase Inicial | F82: 0010367-10.2023.5.15.0075 | G82: Reclamação Trabalhista | H82: Pessoa Jurídica | I82: Sofiati e Salgado Hotel Ltda-ME | J82: Reclamado | K82: Liliane da Silva Barros | L82: Reclamante | M82: ADRIANO LOURENÇO MORAIS DOS SANTOS | N82: 12470.09 | S82: =IF(O82<>0,IF(P82<>0,SUM(P82+Q82*O82+O82*R82),IF(Q82<>0,SUM(P82+Q82*O82+O82*R82),"")),IF(P82<>0,SUM(P82+Q82*N82+N82*R82),IF(Q82<>0,SUM(P82+Q82*N82+N82*R82),""))) | T82: Não | V82: 1ª Instância | W82: Batatais | X82: Vara do Trabalho de Batatais | Y82: Arquivado | Z82: 45035 | AB82: =IFERROR(IF(Z82<>"",IF(AA82="",CONCATENATE(DATEDIF(Z82,TODAY(),"D")," dias"),CONCATENATE(DATEDIF(Z82,AA82,"D")," dias")),""),"") -> 1044 dias | AD82: https://pje.trt15.jus.br/pjekz/processo/3579025/detalhe | AF82: =DATEDIF(TODAY(),U82,"D") -> #NUM! | AG82: =IFERROR(IF(Z82<>"",IF(AA82="",DATEDIF(Z82,TODAY(),"D"),DATEDIF(Z82,AA82,"D")),""),"") -> 1044 | AI82: =IF(I82<>"",IF(F82<>"",CONCATENATE(I82," - ",G82," (",F82,")"),CONCATENATE(I82," - ",G82)),"") -> Sofiati e Salgado Hotel Ltda-ME - Reclamação Trabalhista (0010367-10.2023.5.15.0075) | AJ82: =IF(I82<>"",IF(F82<>"",CONCATENATE(I82," - ",G82," (",F82,")"),CONCATENATE(I82," - ",G82)),"") -> Sofiati e Salgado Hotel Ltda-ME - Reclamação Trabalhista (0010367-10.2023.5.15.0075)
B83: 78 | C83: Ativo | D83: Judicial | E83: Fase Recursal | F83: 1039803-07.2023.8.26.0506 | G83: Declaração de Inexistência de Débito | H83: Pessoa Jurídica | I83: Supermercados Big Compra Ltda. | J83: Autor | K83: Di Casa Acabamentos Ltda. | L83: Requerido | M83: FERES JUNQUEIRA NAJM | N83: 32720 | S83: =IF(O83<>0,IF(P83<>0,SUM(P83+Q83*O83+O83*R83),IF(Q83<>0,SUM(P83+Q83*O83+O83*R83),"")),IF(P83<>0,SUM(P83+Q83*N83+N83*R83),IF(Q83<>0,SUM(P83+Q83*N83+N83*R83),""))) | V83: 1ª Instância | W83: Ribeirão Preto | X83: 1ª Vara Cível | Y83: Feita a contestação. Aguardando despacho do Juiz | Z83: 45160 | AB83: =IFERROR(IF(Z83<>"",IF(AA83="",CONCATENATE(DATEDIF(Z83,TODAY(),"D")," dias"),CONCATENATE(DATEDIF(Z83,AA83,"D")," dias")),""),"") -> 919 dias | AD83: https://esaj.tjsp.jus.br/cpopg/show.do?processo.codigo=E2000Q5P90000&processo.foro=506&processo.numero=1039803-07.2023.8.26.0506 | AF83: =DATEDIF(TODAY(),U83,"D") -> #NUM! | AG83: =IFERROR(IF(Z83<>"",IF(AA83="",DATEDIF(Z83,TODAY(),"D"),DATEDIF(Z83,AA83,"D")),""),"") -> 919 | AI83: =IF(I83<>"",IF(F83<>"",CONCATENATE(I83," - ",G83," (",F83,")"),CONCATENATE(I83," - ",G83)),"") -> Supermercados Big Compra Ltda. - Declaração de Inexistência de Débito (1039803-07.2023.8.26.0506) | AJ83: =IF(I83<>"",IF(F83<>"",CONCATENATE(I83," - ",G83," (",F83,")"),CONCATENATE(I83," - ",G83)),"") -> Supermercados Big Compra Ltda. - Declaração de Inexistência de Débito (1039803-07.2023.8.26.0506)
B84: 79 | C84: Ativo | D84: Judicial | E84: Fase de Produção de Provas | F84: 1018847-27.2023.8.26.0196 | G84: Declaração de Inexistência de Débito | H84: Pessoa Jurídica | I84: Supermercados Big Compra Ltda. | J84: Réu | K84: Marciana de Paula Dawis | L84: Requerente | M84: FERES JUNQUEIRA NAJM | N84: 26789.65 | S84: =IF(O84<>0,IF(P84<>0,SUM(P84+Q84*O84+O84*R84),IF(Q84<>0,SUM(P84+Q84*O84+O84*R84),"")),IF(P84<>0,SUM(P84+Q84*N84+N84*R84),IF(Q84<>0,SUM(P84+Q84*N84+N84*R84),""))) | T84: Não | V84: 1ª Instância | W84: Franca | X84: 3ª Vara Cível | Y84: Suspenso por IRDR | Z84: 45140 | AB84: =IFERROR(IF(Z84<>"",IF(AA84="",CONCATENATE(DATEDIF(Z84,TODAY(),"D")," dias"),CONCATENATE(DATEDIF(Z84,AA84,"D")," dias")),""),"") -> 939 dias | AD84: https://esaj.tjsp.jus.br/cpopg/show.do?processo.codigo=5G000FHRE0000&processo.foro=196&conversationId=&cbPesquisa=NMPARTE&dadosConsulta.valorConsulta=Supermercado+Big+Compra&cdForo=-1&paginaConsulta=1 | AF84: =DATEDIF(TODAY(),U84,"D") -> #NUM! | AG84: =IFERROR(IF(Z84<>"",IF(AA84="",DATEDIF(Z84,TODAY(),"D"),DATEDIF(Z84,AA84,"D")),""),"") -> 939 | AI84: =IF(I84<>"",IF(F84<>"",CONCATENATE(I84," - ",G84," (",F84,")"),CONCATENATE(I84," - ",G84)),"") -> Supermercados Big Compra Ltda. - Declaração de Inexistência de Débito (1018847-27.2023.8.26.0196) | AJ84: =IF(I84<>"",IF(F84<>"",CONCATENATE(I84," - ",G84," (",F84,")"),CONCATENATE(I84," - ",G84)),"") -> Supermercados Big Compra Ltda. - Declaração de Inexistência de Débito (1018847-27.2023.8.26.0196)
B85: 80 | C85: Encerrado | D85: Judicial | E85: Fase de Sentença | F85: 1018365-37.2014.8.26.0506 | G85: Divórcio Consensual | H85: Pessoa Jurídica | I85: Mister Ottani | J85: Réu | K85: Ana Paula Ottani | L85: Autor | M85: FERES JUNQUEIRA NAJM | N85: 10000 | S85: =IF(O85<>0,IF(P85<>0,SUM(P85+Q85*O85+O85*R85),IF(Q85<>0,SUM(P85+Q85*O85+O85*R85),"")),IF(P85<>0,SUM(P85+Q85*N85+N85*R85),IF(Q85<>0,SUM(P85+Q85*N85+N85*R85),""))) | T85: Não | V85: 1ª Instância | W85: Ribeirão Preto | X85: 2ª Vara da Família e Sucessões | Y85: Aguardando o arquivamento e extinção | Z85: 41806 | AB85: =IFERROR(IF(Z85<>"",IF(AA85="",CONCATENATE(DATEDIF(Z85,TODAY(),"D")," dias"),CONCATENATE(DATEDIF(Z85,AA85,"D")," dias")),""),"") -> 4273 dias | AD85: https://esaj.tjsp.jus.br/cpopg/show.do?processo.codigo=E20004VON0000&processo.foro=506&processo.numero=1018365-37.2014.8.26.0506 | AF85: =DATEDIF(TODAY(),U85,"D") -> #NUM! | AG85: =IFERROR(IF(Z85<>"",IF(AA85="",DATEDIF(Z85,TODAY(),"D"),DATEDIF(Z85,AA85,"D")),""),"") -> 4273 | AI85: =IF(I85<>"",IF(F85<>"",CONCATENATE(I85," - ",G85," (",F85,")"),CONCATENATE(I85," - ",G85)),"") -> Mister Ottani - Divórcio Consensual (1018365-37.2014.8.26.0506) | AJ85: =IF(I85<>"",IF(F85<>"",CONCATENATE(I85," - ",G85," (",F85,")"),CONCATENATE(I85," - ",G85)),"") -> Mister Ottani - Divórcio Consensual (1018365-37.2014.8.26.0506)
B86: 81 | C86: Ativo | D86: Judicial | E86: Fase Inicial | F86: 0011145-07.2023.5.15.0066 | G86: Reclamação Trabalhista | H86: Pessoa Física | I86: Cleide Patrícia Dias Cardoso | J86: Reclamante | K86: Antônio Carlos Cabero | L86: Reclamado | M86: ADRIANO LOURENÇO MORAIS DOS SANTOS | N86: 19000 | S86: =IF(O86<>0,IF(P86<>0,SUM(P86+Q86*O86+O86*R86),IF(Q86<>0,SUM(P86+Q86*O86+O86*R86),"")),IF(P86<>0,SUM(P86+Q86*N86+N86*R86),IF(Q86<>0,SUM(P86+Q86*N86+N86*R86),""))) | T86: Não | V86: 1ª Instância | W86: Ribeirão Preto | X86: 4ª Vara do Trabalho | Y86: Citada a ré. Aguardando audiência. | Z86: 45128 | AB86: =IFERROR(IF(Z86<>"",IF(AA86="",CONCATENATE(DATEDIF(Z86,TODAY(),"D")," dias"),CONCATENATE(DATEDIF(Z86,AA86,"D")," dias")),""),"") -> 951 dias | AD86: https://pje.trt15.jus.br/consultaprocessual/detalhe-processo/0011145-07.2023.5.15.0066/1#fa732a1 | AF86: =DATEDIF(TODAY(),U86,"D") -> #NUM! | AG86: =IFERROR(IF(Z86<>"",IF(AA86="",DATEDIF(Z86,TODAY(),"D"),DATEDIF(Z86,AA86,"D")),""),"") -> 951 | AI86: =IF(I86<>"",IF(F86<>"",CONCATENATE(I86," - ",G86," (",F86,")"),CONCATENATE(I86," - ",G86)),"") -> Cleide Patrícia Dias Cardoso - Reclamação Trabalhista (0011145-07.2023.5.15.0066) | AJ86: =IF(I86<>"",IF(F86<>"",CONCATENATE(I86," - ",G86," (",F86,")"),CONCATENATE(I86," - ",G86)),"") -> Cleide Patrícia Dias Cardoso - Reclamação Trabalhista (0011145-07.2023.5.15.0066)
B87: 82 | C87: Ativo | D87: Judicial | E87: Fase Inicial | F87: 1023662-67.2023.8.26.0196 | G87: Seguro / Remoção / Vaga Técnica | H87: Pessoa Jurídica | I87: R. C. Nascimento | J87: Autor | K87: Porto Seguro Companhia de Seguros Gerais | L87: Réu | M87: FERES JUNQUEIRA NAJM | N87: 9600 | S87: =IF(O87<>0,IF(P87<>0,SUM(P87+Q87*O87+O87*R87),IF(Q87<>0,SUM(P87+Q87*O87+O87*R87),"")),IF(P87<>0,SUM(P87+Q87*N87+N87*R87),IF(Q87<>0,SUM(P87+Q87*N87+N87*R87),""))) | T87: Sim | V87: 1ª Instância | W87: Franca | X87: 1ª Vara Cível | Y87: Aguardando despacho do Juiz | Z87: 45191 | AB87: =IFERROR(IF(Z87<>"",IF(AA87="",CONCATENATE(DATEDIF(Z87,TODAY(),"D")," dias"),CONCATENATE(DATEDIF(Z87,AA87,"D")," dias")),""),"") -> 888 dias | AD87: https://esaj.tjsp.jus.br/cpopg/show.do?processo.codigo=5G000FNO10000&processo.foro=196&processo.numero=1023662-67.2023.8.26.0196 | AF87: =DATEDIF(TODAY(),U87,"D") -> #NUM! | AG87: =IFERROR(IF(Z87<>"",IF(AA87="",DATEDIF(Z87,TODAY(),"D"),DATEDIF(Z87,AA87,"D")),""),"") -> 888 | AI87: =IF(I87<>"",IF(F87<>"",CONCATENATE(I87," - ",G87," (",F87,")"),CONCATENATE(I87," - ",G87)),"") -> R. C. Nascimento - Seguro / Remoção / Vaga Técnica (1023662-67.2023.8.26.0196) | AJ87: =IF(I87<>"",IF(F87<>"",CONCATENATE(I87," - ",G87," (",F87,")"),CONCATENATE(I87," - ",G87)),"") -> R. C. Nascimento - Seguro / Remoção / Vaga Técnica (1023662-67.2023.8.26.0196)
B88: 83 | C88: Ativo | D88: Judicial | E88: Fase Inicial | F88: 1049242-42.2023.8.26.0506 | G88: Declaração de Inexistência de Débito | H88: Pessoa Jurídica | I88: Auto Posto Zerrenner | J88: Autor | K88: Fundação de Proteção e Defesa do Consumidor | L88: Réu | M88: FERES JUNQUEIRA NAJM | N88: 41049.41 | S88: =IF(O88<>0,IF(P88<>0,SUM(P88+Q88*O88+O88*R88),IF(Q88<>0,SUM(P88+Q88*O88+O88*R88),"")),IF(P88<>0,SUM(P88+Q88*N88+N88*R88),IF(Q88<>0,SUM(P88+Q88*N88+N88*R88),""))) | T88: Não | V88: 1ª Instância | W88: Ribeirão Preto | X88: 2ª Vara da Fazenda Pública | Y88: Concluso para decisão | Z88: 45201 | AB88: =IFERROR(IF(Z88<>"",IF(AA88="",CONCATENATE(DATEDIF(Z88,TODAY(),"D")," dias"),CONCATENATE(DATEDIF(Z88,AA88,"D")," dias")),""),"") -> 878 dias | AD88: https://esaj.tjsp.jus.br/cpopg/show.do?processo.codigo=E2000QG6O0000&processo.foro=506&processo.numero=1049242-42.2023.8.26.0506 | AF88: =DATEDIF(TODAY(),U88,"D") -> #NUM! | AG88: =IFERROR(IF(Z88<>"",IF(AA88="",DATEDIF(Z88,TODAY(),"D"),DATEDIF(Z88,AA88,"D")),""),"") -> 878 | AI88: =IF(I88<>"",IF(F88<>"",CONCATENATE(I88," - ",G88," (",F88,")"),CONCATENATE(I88," - ",G88)),"") -> Auto Posto Zerrenner - Declaração de Inexistência de Débito (1049242-42.2023.8.26.0506) | AJ88: =IF(I88<>"",IF(F88<>"",CONCATENATE(I88," - ",G88," (",F88,")"),CONCATENATE(I88," - ",G88)),"") -> Auto Posto Zerrenner - Declaração de Inexistência de Débito (1049242-42.2023.8.26.0506)
B89: 84 | C89: Ativo | D89: Judicial | E89: Fase Inicial | F89: 1057419-92.2023.8.26.0506 | G89: Ação de Cobrança | H89: Pessoa Jurídica | I89: Brilho Auto Center | J89: Autor | K89: Rodrigo Ribeiro Barboza | L89: Réu | M89: FERES JUNQUEIRA NAJM | N89: 32805.42 | S89: =IF(O89<>0,IF(P89<>0,SUM(P89+Q89*O89+O89*R89),IF(Q89<>0,SUM(P89+Q89*O89+O89*R89),"")),IF(P89<>0,SUM(P89+Q89*N89+N89*R89),IF(Q89<>0,SUM(P89+Q89*N89+N89*R89),""))) | T89: Não | V89: 1ª Instância | W89: Ribeirão Preto | X89: 1ª Vara Cível | Y89: AR negativo. Aguardando despacho. | Z89: 45231 | AB89: =IFERROR(IF(Z89<>"",IF(AA89="",CONCATENATE(DATEDIF(Z89,TODAY(),"D")," dias"),CONCATENATE(DATEDIF(Z89,AA89,"D")," dias")),""),"") -> 848 dias | AD89: https://esaj.tjsp.jus.br/cpopg/show.do?processo.codigo=E2000QOTY0000&processo.foro=506&conversationId=&cbPesquisa=NMPARTE&dadosConsulta.valorConsulta=Brilho+Auto+Center&cdForo=-1&paginaConsulta=1 | AF89: =DATEDIF(TODAY(),U89,"D") -> #NUM! | AG89: =IFERROR(IF(Z89<>"",IF(AA89="",DATEDIF(Z89,TODAY(),"D"),DATEDIF(Z89,AA89,"D")),""),"") -> 848 | AI89: =IF(I89<>"",IF(F89<>"",CONCATENATE(I89," - ",G89," (",F89,")"),CONCATENATE(I89," - ",G89)),"") -> Brilho Auto Center - Ação de Cobrança (1057419-92.2023.8.26.0506) | AJ89: =IF(I89<>"",IF(F89<>"",CONCATENATE(I89," - ",G89," (",F89,")"),CONCATENATE(I89," - ",G89)),"") -> Brilho Auto Center - Ação de Cobrança (1057419-92.2023.8.26.0506)
B90: 85 | C90: Ativo | D90: Judicial | E90: Fase Inicial | F90: 1057392-12.2023.8.26.0506 | G90: Ação de Cobrança | H90: Pessoa Jurídica | I90: Brilho Auto Center | J90: Autor | K90: TC Log Transportes Ltda. | L90: Réu | M90: FERES JUNQUEIRA NAJM | N90: 3497.77 | S90: =IF(O90<>0,IF(P90<>0,SUM(P90+Q90*O90+O90*R90),IF(Q90<>0,SUM(P90+Q90*O90+O90*R90),"")),IF(P90<>0,SUM(P90+Q90*N90+N90*R90),IF(Q90<>0,SUM(P90+Q90*N90+N90*R90),""))) | T90: Sim | V90: 1ª Instância | W90: Ribeirão Preto | X90: 6ª Vara Cível | Y90: AR negtivo. Prazo aberto para manifestação. | Z90: 45231 | AB90: =IFERROR(IF(Z90<>"",IF(AA90="",CONCATENATE(DATEDIF(Z90,TODAY(),"D")," dias"),CONCATENATE(DATEDIF(Z90,AA90,"D")," dias")),""),"") -> 848 dias | AD90: https://esaj.tjsp.jus.br/cpopg/show.do?processo.codigo=E2000QORH0000&processo.foro=506&conversationId=&cbPesquisa=NMPARTE&dadosConsulta.valorConsulta=Brilho+Auto+Center&cdForo=-1&paginaConsulta=1 | AF90: =DATEDIF(TODAY(),U90,"D") -> #NUM! | AG90: =IFERROR(IF(Z90<>"",IF(AA90="",DATEDIF(Z90,TODAY(),"D"),DATEDIF(Z90,AA90,"D")),""),"") -> 848 | AI90: =IF(I90<>"",IF(F90<>"",CONCATENATE(I90," - ",G90," (",F90,")"),CONCATENATE(I90," - ",G90)),"") -> Brilho Auto Center - Ação de Cobrança (1057392-12.2023.8.26.0506) | AJ90: =IF(I90<>"",IF(F90<>"",CONCATENATE(I90," - ",G90," (",F90,")"),CONCATENATE(I90," - ",G90)),"") -> Brilho Auto Center - Ação de Cobrança (1057392-12.2023.8.26.0506)
B91: 86 | C91: Encerrado | D91: Administrativo | E91: Fase inicial | F91: 000565.2023.15.006-9 | G91: Denúncia | H91: Pessoa Jurídica | I91: André Luís Massaro | J91: Réu | K91: Ministério Público do Trabalho do Estado de São Paulo | L91: Autor | M91: ADRIANO LOURENÇO MORAIS DOS SANTOS | S91: =IF(O91<>0,IF(P91<>0,SUM(P91+Q91*O91+O91*R91),IF(Q91<>0,SUM(P91+Q91*O91+O91*R91),"")),IF(P91<>0,SUM(P91+Q91*N91+N91*R91),IF(Q91<>0,SUM(P91+Q91*N91+N91*R91),""))) | T91: Não | W91: Ribeirão Preto | Y91: Encaminhamento ao Membro | Z91: 45153 | AB91: =IFERROR(IF(Z91<>"",IF(AA91="",CONCATENATE(DATEDIF(Z91,TODAY(),"D")," dias"),CONCATENATE(DATEDIF(Z91,AA91,"D")," dias")),""),"") -> 926 dias | AD91: https://peticionamento.prt15.mpt.mp.br/default/exibeprocedimento# | AF91: =DATEDIF(TODAY(),U91,"D") -> #NUM! | AG91: =IFERROR(IF(Z91<>"",IF(AA91="",DATEDIF(Z91,TODAY(),"D"),DATEDIF(Z91,AA91,"D")),""),"") -> 926 | AI91: =IF(I91<>"",IF(F91<>"",CONCATENATE(I91," - ",G91," (",F91,")"),CONCATENATE(I91," - ",G91)),"") -> André Luís Massaro - Denúncia (000565.2023.15.006-9) | AJ91: =IF(I91<>"",IF(F91<>"",CONCATENATE(I91," - ",G91," (",F91,")"),CONCATENATE(I91," - ",G91)),"") -> André Luís Massaro - Denúncia (000565.2023.15.006-9)
B92: 87 | C92: Ativo | D92: Judicial | E92: Fase de Contestação | F92: 1052459-93.2023.8.26.0506 | G92: Ação Indenizatória | H92: Pessoa Física | I92: Gabriel Szurkalo Pantoni | J92: Réu | K92: Luis Ricardo Moreira Santos | L92: Autor | M92: FERES JUNQUEIRA NAJM | N92: 13212 | S92: =IF(O92<>0,IF(P92<>0,SUM(P92+Q92*O92+O92*R92),IF(Q92<>0,SUM(P92+Q92*O92+O92*R92),"")),IF(P92<>0,SUM(P92+Q92*N92+N92*R92),IF(Q92<>0,SUM(P92+Q92*N92+N92*R92),""))) | T92: Não | V92: 1ª Instância | W92: Ribeirão Preto | X92: 3ª Vara Cível | Y92: Contestação protocolada - aguardando réplica da autora | Z92: 45210 | AB92: =IFERROR(IF(Z92<>"",IF(AA92="",CONCATENATE(DATEDIF(Z92,TODAY(),"D")," dias"),CONCATENATE(DATEDIF(Z92,AA92,"D")," dias")),""),"") -> 869 dias | AD92: https://esaj.tjsp.jus.br/cpopg/show.do?processo.codigo=E2000QJHG0000&processo.foro=506&processo.numero=1052459-93.2023.8.26.0506 | AF92: =DATEDIF(TODAY(),U92,"D") -> #NUM! | AG92: =IFERROR(IF(Z92<>"",IF(AA92="",DATEDIF(Z92,TODAY(),"D"),DATEDIF(Z92,AA92,"D")),""),"") -> 869 | AI92: =IF(I92<>"",IF(F92<>"",CONCATENATE(I92," - ",G92," (",F92,")"),CONCATENATE(I92," - ",G92)),"") -> Gabriel Szurkalo Pantoni - Ação Indenizatória (1052459-93.2023.8.26.0506 ) | AJ92: =IF(I92<>"",IF(F92<>"",CONCATENATE(I92," - ",G92," (",F92,")"),CONCATENATE(I92," - ",G92)),"") -> Gabriel Szurkalo Pantoni - Ação Indenizatória (1052459-93.2023.8.26.0506 )
B93: 88 | C93: Ativo | D93: Judicial | E93: Fase Inicial | F93: 0011229-22.2023.5.15.0126 | G93: Reclamação Trabalhista | H93: Pessoa Física | I93: Jonathan Feliciano Lima | J93: Reclamante | K93: BrasWell Papel e Celulose Ltda. | L93: Reclamado | M93: ADRIANO LOURENÇO MORAIS DOS SANTOS | N93: 140382.8 | S93: =IF(O93<>0,IF(P93<>0,SUM(P93+Q93*O93+O93*R93),IF(Q93<>0,SUM(P93+Q93*O93+O93*R93),"")),IF(P93<>0,SUM(P93+Q93*N93+N93*R93),IF(Q93<>0,SUM(P93+Q93*N93+N93*R93),""))) | T93: Não | V93: 1ª Instância | W93: Ribeirão Preto | X93: 2ª Vara trabalhista de Paulínia | Y93: Exsclarecimentos sobre o laudo apresentados. Aguardando despacho | Z93: 45210 | AB93: =IFERROR(IF(Z93<>"",IF(AA93="",CONCATENATE(DATEDIF(Z93,TODAY(),"D")," dias"),CONCATENATE(DATEDIF(Z93,AA93,"D")," dias")),""),"") -> 869 dias | AD93: https://pje.trt15.jus.br/consultaprocessual/detalhe-processo/0011229-22.2023.5.15.0126/1#a055c14 | AF93: =DATEDIF(TODAY(),U93,"D") -> #NUM! | AG93: =IFERROR(IF(Z93<>"",IF(AA93="",DATEDIF(Z93,TODAY(),"D"),DATEDIF(Z93,AA93,"D")),""),"") -> 869 | AI93: =IF(I93<>"",IF(F93<>"",CONCATENATE(I93," - ",G93," (",F93,")"),CONCATENATE(I93," - ",G93)),"") -> Jonathan Feliciano Lima - Reclamação Trabalhista (0011229-22.2023.5.15.0126) | AJ93: =IF(I93<>"",IF(F93<>"",CONCATENATE(I93," - ",G93," (",F93,")"),CONCATENATE(I93," - ",G93)),"") -> Jonathan Feliciano Lima - Reclamação Trabalhista (0011229-22.2023.5.15.0126)
B94: 89 | C94: Ativo | D94: Judicial | E94: Fase Inicial | F94: 1061812-60.2023.8.26.0506 | G94: Ação de Desejo (Cobrança de alugueis) | H94: Pessoa Física | I94: Tomas Yung Joon Kim | J94: Autor | K94: Natália Gomes Cardoso | L94: Réu | M94: FERES JUNQUEIRA NAJM | N94: 9617.02 | S94: =IF(O94<>0,IF(P94<>0,SUM(P94+Q94*O94+O94*R94),IF(Q94<>0,SUM(P94+Q94*O94+O94*R94),"")),IF(P94<>0,SUM(P94+Q94*N94+N94*R94),IF(Q94<>0,SUM(P94+Q94*N94+N94*R94),""))) | T94: Não | V94: 1ª Instância | W94: Ribeirão Preto | X94: 10ª Vara Cível | Y94: Feita a manifestação sobre os documentos novos - aguardando decisão | Z94: 45260 | AB94: =IFERROR(IF(Z94<>"",IF(AA94="",CONCATENATE(DATEDIF(Z94,TODAY(),"D")," dias"),CONCATENATE(DATEDIF(Z94,AA94,"D")," dias")),""),"") -> 819 dias | AD94: https://esaj.tjsp.jus.br/cpopg/show.do?processo.codigo=E2000QUHP0000&processo.foro=506&processo.numero=1061812-60.2023.8.26.0506 | AF94: =DATEDIF(TODAY(),U94,"D") -> #NUM! | AG94: =IFERROR(IF(Z94<>"",IF(AA94="",DATEDIF(Z94,TODAY(),"D"),DATEDIF(Z94,AA94,"D")),""),"") -> 819 | AI94: =IF(I94<>"",IF(F94<>"",CONCATENATE(I94," - ",G94," (",F94,")"),CONCATENATE(I94," - ",G94)),"") -> Tomas Yung Joon Kim - Ação de Desejo (Cobrança de alugueis) (1061812-60.2023.8.26.0506) | AJ94: =IF(I94<>"",IF(F94<>"",CONCATENATE(I94," - ",G94," (",F94,")"),CONCATENATE(I94," - ",G94)),"") -> Tomas Yung Joon Kim - Ação de Desejo (Cobrança de alugueis) (1061812-60.2023.8.26.0506)
B95: 90 | C95: Encerrado | D95: Judicial | E95: Fase Inicial | F95: 1029977-14.2023.8.26.0196 | G95: Seguro / Remoção / Vaga Técnica | H95: Pessoa Jurídica | I95: Oficina Classe A | J95: Autor | K95: Sompo Seguros S/A | L95: Réu | M95: FERES JUNQUEIRA NAJM | N95: 9880 | S95: =IF(O95<>0,IF(P95<>0,SUM(P95+Q95*O95+O95*R95),IF(Q95<>0,SUM(P95+Q95*O95+O95*R95),"")),IF(P95<>0,SUM(P95+Q95*N95+N95*R95),IF(Q95<>0,SUM(P95+Q95*N95+N95*R95),""))) | T95: Sim | V95: 1ª Instância | W95: Ribeirão Preto | X95: Juizado Especial Cível | Y95: Concluso para sentença | Z95: 45261 | AB95: =IFERROR(IF(Z95<>"",IF(AA95="",CONCATENATE(DATEDIF(Z95,TODAY(),"D")," dias"),CONCATENATE(DATEDIF(Z95,AA95,"D")," dias")),""),"") -> 818 dias | AD95: https://esaj.tjsp.jus.br/cpopg/show.do?processo.codigo=5G000FVHY0000&processo.foro=196&processo.numero=1029977-14.2023.8.26.0196 | AF95: =DATEDIF(TODAY(),U95,"D") -> #NUM! | AG95: =IFERROR(IF(Z95<>"",IF(AA95="",DATEDIF(Z95,TODAY(),"D"),DATEDIF(Z95,AA95,"D")),""),"") -> 818 | AI95: =IF(I95<>"",IF(F95<>"",CONCATENATE(I95," - ",G95," (",F95,")"),CONCATENATE(I95," - ",G95)),"") -> Oficina Classe A - Seguro / Remoção / Vaga Técnica (1029977-14.2023.8.26.0196) | AJ95: =IF(I95<>"",IF(F95<>"",CONCATENATE(I95," - ",G95," (",F95,")"),CONCATENATE(I95," - ",G95)),"") -> Oficina Classe A - Seguro / Remoção / Vaga Técnica (1029977-14.2023.8.26.0196)
B96: 91 | C96: Encerrado | D96: Judicial | E96: Fase de Conciliação | F96: 1059081-91.2023.8.26.0506 | G96: Ação de Cobrança | H96: Pessoa Jurídica | I96: Renove Casa & Design | J96: Réu | K96: Sicoob Cocred | L96: Autor | M96: FERES JUNQUEIRA NAJM | N96: 15367.61 | S96: =IF(O96<>0,IF(P96<>0,SUM(P96+Q96*O96+O96*R96),IF(Q96<>0,SUM(P96+Q96*O96+O96*R96),"")),IF(P96<>0,SUM(P96+Q96*N96+N96*R96),IF(Q96<>0,SUM(P96+Q96*N96+N96*R96),""))) | T96: Não | V96: 1ª Instância | W96: Ribeirão Preto | X96: 3ª Vara Cível | Y96: Arquivado | Z96: 45244 | AB96: =IFERROR(IF(Z96<>"",IF(AA96="",CONCATENATE(DATEDIF(Z96,TODAY(),"D")," dias"),CONCATENATE(DATEDIF(Z96,AA96,"D")," dias")),""),"") -> 835 dias | AD96: https://esaj.tjsp.jus.br/cpopg/show.do?processo.codigo=E2000QQU90000&processo.foro=506&processo.numero=1059081-91.2023.8.26.0506 | AF96: =DATEDIF(TODAY(),U96,"D") -> #NUM! | AG96: =IFERROR(IF(Z96<>"",IF(AA96="",DATEDIF(Z96,TODAY(),"D"),DATEDIF(Z96,AA96,"D")),""),"") -> 835 | AI96: =IF(I96<>"",IF(F96<>"",CONCATENATE(I96," - ",G96," (",F96,")"),CONCATENATE(I96," - ",G96)),"") -> Renove Casa & Design - Ação de Cobrança (1059081-91.2023.8.26.0506) | AJ96: =IF(I96<>"",IF(F96<>"",CONCATENATE(I96," - ",G96," (",F96,")"),CONCATENATE(I96," - ",G96)),"") -> Renove Casa & Design - Ação de Cobrança (1059081-91.2023.8.26.0506)
B97: 92 | C97: Encerrado | D97: Judicial | E97: Fase de Sentença | F97: 1063138-55.2023.8.26.0506 | G97: Seguro / Remoção / Vaga Técnica | H97: Pessoa Jurídica | I97: Pepe Oficina | J97: Autor | K97: Bradesco Seguros S/A | L97: Réu | M97: FERES JUNQUEIRA NAJM | N97: 1250 | S97: =IF(O97<>0,IF(P97<>0,SUM(P97+Q97*O97+O97*R97),IF(Q97<>0,SUM(P97+Q97*O97+O97*R97),"")),IF(P97<>0,SUM(P97+Q97*N97+N97*R97),IF(Q97<>0,SUM(P97+Q97*N97+N97*R97),""))) | T97: Sim | V97: 1ª Instância | W97: Ribeirão Preto | X97: 6ª Vara Cível | Y97: Aguardando despacho do Juiz | Z97: 45267 | AB97: =IFERROR(IF(Z97<>"",IF(AA97="",CONCATENATE(DATEDIF(Z97,TODAY(),"D")," dias"),CONCATENATE(DATEDIF(Z97,AA97,"D")," dias")),""),"") -> 812 dias | AD97: Portal de Serviços e-SAJ (tjsp.jus.br) | AF97: =DATEDIF(TODAY(),U97,"D") -> #NUM! | AG97: =IFERROR(IF(Z97<>"",IF(AA97="",DATEDIF(Z97,TODAY(),"D"),DATEDIF(Z97,AA97,"D")),""),"") -> 812 | AI97: =IF(I97<>"",IF(F97<>"",CONCATENATE(I97," - ",G97," (",F97,")"),CONCATENATE(I97," - ",G97)),"") -> Pepe Oficina - Seguro / Remoção / Vaga Técnica (1063138-55.2023.8.26.0506) | AJ97: =IF(I97<>"",IF(F97<>"",CONCATENATE(I97," - ",G97," (",F97,")"),CONCATENATE(I97," - ",G97)),"") -> Pepe Oficina - Seguro / Remoção / Vaga Técnica (1063138-55.2023.8.26.0506)
B98: 93 | C98: Encerrado | D98: Administrativo | E98: Fase Recursal | F98: 54558-D8.2021.0.0.5023 | G98: Processo Administrativo Sancionatório | H98: Pessoa Jurídica | I98: Supermercados Big Compra Ltda. | J98: Autuado | K98: Fundação de Proteção e Defesa do Consumidor | L98: Fiscalizadora | M98: FERES JUNQUEIRA NAJM | N98: 16917.3 | S98: =IF(O98<>0,IF(P98<>0,SUM(P98+Q98*O98+O98*R98),IF(Q98<>0,SUM(P98+Q98*O98+O98*R98),"")),IF(P98<>0,SUM(P98+Q98*N98+N98*R98),IF(Q98<>0,SUM(P98+Q98*N98+N98*R98),""))) | T98: Não | W98: São Paulo | AB98: =IFERROR(IF(Z98<>"",IF(AA98="",CONCATENATE(DATEDIF(Z98,TODAY(),"D")," dias"),CONCATENATE(DATEDIF(Z98,AA98,"D")," dias")),""),"") | AF98: =DATEDIF(TODAY(),U98,"D") -> #NUM! | AG98: =IFERROR(IF(Z98<>"",IF(AA98="",DATEDIF(Z98,TODAY(),"D"),DATEDIF(Z98,AA98,"D")),""),"") | AI98: =IF(I98<>"",IF(F98<>"",CONCATENATE(I98," - ",G98," (",F98,")"),CONCATENATE(I98," - ",G98)),"") -> Supermercados Big Compra Ltda. - Processo Administrativo Sancionatório (54558-D8.2021.0.0.5023) | AJ98: =IF(I98<>"",IF(F98<>"",CONCATENATE(I98," - ",G98," (",F98,")"),CONCATENATE(I98," - ",G98)),"") -> Supermercados Big Compra Ltda. - Processo Administrativo Sancionatório (54558-D8.2021.0.0.5023)
B99: 94 | C99: Encerrado | D99: Administrativo | E99: Fase de Contestação | F99: 66533-D8.2023.0.0.4435 | G99: Processo Administrativo Sancionatório | H99: Pessoa Jurídica | I99: Supermercados Big Compra Ltda. | J99: Autuado | K99: Fundação de Proteção e Defesa do Consumidor | L99: Fiscalizadora | M99: FERES JUNQUEIRA NAJM | N99: 37594 | S99: =IF(O99<>0,IF(P99<>0,SUM(P99+Q99*O99+O99*R99),IF(Q99<>0,SUM(P99+Q99*O99+O99*R99),"")),IF(P99<>0,SUM(P99+Q99*N99+N99*R99),IF(Q99<>0,SUM(P99+Q99*N99+N99*R99),""))) | T99: Não | W99: São Paulo | AB99: =IFERROR(IF(Z99<>"",IF(AA99="",CONCATENATE(DATEDIF(Z99,TODAY(),"D")," dias"),CONCATENATE(DATEDIF(Z99,AA99,"D")," dias")),""),"") | AF99: =DATEDIF(TODAY(),U99,"D") -> #NUM! | AG99: =IFERROR(IF(Z99<>"",IF(AA99="",DATEDIF(Z99,TODAY(),"D"),DATEDIF(Z99,AA99,"D")),""),"") | AI99: =IF(I99<>"",IF(F99<>"",CONCATENATE(I99," - ",G99," (",F99,")"),CONCATENATE(I99," - ",G99)),"") -> Supermercados Big Compra Ltda. - Processo Administrativo Sancionatório (66533-D8.2023.0.0.4435) | AJ99: =IF(I99<>"",IF(F99<>"",CONCATENATE(I99," - ",G99," (",F99,")"),CONCATENATE(I99," - ",G99)),"") -> Supermercados Big Compra Ltda. - Processo Administrativo Sancionatório (66533-D8.2023.0.0.4435)
B100: 95 | C100: Encerrado | D100: Judicial | E100: Fase Inicial | F100: 1008073-41.2024.8.26.0506 | G100: Seguro / Remoção / Vaga Técnica | H100: Pessoa Jurídica | I100: Pepe Oficina | J100: Autor | K100: Zurich Minas Brasil S/A | L100: Réu | M100: ADRIANO LOURENÇO MORAIS DOS SANTOS | N100: 3500 | S100: =IF(O100<>0,IF(P100<>0,SUM(P100+Q100*O100+O100*R100),IF(Q100<>0,SUM(P100+Q100*O100+O100*R100),"")),IF(P100<>0,SUM(P100+Q100*N100+N100*R100),IF(Q100<>0,SUM(P100+Q100*N100+N100*R100),""))) | T100: Não | V100: 1ª Instância | W100: Ribeirão Preto | X100: 2ª Vara Cível | Y100: Acordo homologado | Z100: 45344 | AB100: =IFERROR(IF(Z100<>"",IF(AA100="",CONCATENATE(DATEDIF(Z100,TODAY(),"D")," dias"),CONCATENATE(DATEDIF(Z100,AA100,"D")," dias")),""),"") -> 735 dias | AD100: https://esaj.tjsp.jus.br/cpopg/show.do?processo.codigo=E2000RA3Y0000&processo.foro=506&processo.numero=1008073-41.2024.8.26.0506 | AF100: =DATEDIF(TODAY(),U100,"D") -> #NUM! | AG100: =IFERROR(IF(Z100<>"",IF(AA100="",DATEDIF(Z100,TODAY(),"D"),DATEDIF(Z100,AA100,"D")),""),"") -> 735 | AI100: =IF(I100<>"",IF(F100<>"",CONCATENATE(I100," - ",G100," (",F100,")"),CONCATENATE(I100," - ",G100)),"") -> Pepe Oficina - Seguro / Remoção / Vaga Técnica (1008073-41.2024.8.26.0506) | AJ100: =IF(I100<>"",IF(F100<>"",CONCATENATE(I100," - ",G100," (",F100,")"),CONCATENATE(I100," - ",G100)),"") -> Pepe Oficina - Seguro / Remoção / Vaga Técnica (1008073-41.2024.8.26.0506)
B101: 96 | C101: Ativo | D101: Judicial | E101: Fase Inicial | F101: 0002921-29.2024.8.26.0506 | G101: Cumprimento de sentença | H101: Pessoa Física | I101: Álvaro de Souza Rodriguês Pinheiro | J101: Réu | K101: Laure, Defina Sociedade de Advogados | L101: Autor | M101: ADRIANO LOURENÇO MORAIS DOS SANTOS | N101: 1509.76 | S101: =IF(O101<>0,IF(P101<>0,SUM(P101+Q101*O101+O101*R101),IF(Q101<>0,SUM(P101+Q101*O101+O101*R101),"")),IF(P101<>0,SUM(P101+Q101*N101+N101*R101),IF(Q101<>0,SUM(P101+Q101*N101+N101*R101),""))) | T101: Não | V101: 1ª Instância | W101: Ribeirão Preto | X101: 9ª Vara Cível | Y101: Aguardando despacho do Juiz | Z101: 45327 | AB101: =IFERROR(IF(Z101<>"",IF(AA101="",CONCATENATE(DATEDIF(Z101,TODAY(),"D")," dias"),CONCATENATE(DATEDIF(Z101,AA101,"D")," dias")),""),"") -> 752 dias | AD101: https://esaj.tjsp.jus.br/pastadigital/abrirPastaProcessoDigital.do?nuProcesso=0002921-29.2024.8.26.0506&cdProcesso=E2000R98L0000&instanciaProcesso=pg&cdProcessoMaster=E2000PVPJ0000&cdForo=506&baseIndice=INDDS&nmAlias=PG5RPDS&tpOrigem=2&flOrigem=P&cdServico=190101&acessibilidade=false&ticket=qGMmVKZGIcOxLeEcjaB5R%2BLTVih7rgTpdIlXptR22FqPPvmEPdp4QzTVRetNZWNvB09eseWqE7Hg1bWrmnC825Elur%2Bk8m8uHYKEq9vnBjyeNMjz8Q%2BtpjRkZzFwu0h6uTd5gBE17nK8ACfcvdctvpXYmzgLD2nf%2FCm2bOvazir4fCSM5MploZgtEePPcRLEbaXRURa2dwayOVyAm4yh%2BFlDUL1ES4AGz09xbYvfFedM6GYGcfY229f9KdRiur%2BrbyMwDF9YYyPWDke96xqQavw2sCybMVhlVs8Y5ORud8kQNWRO0vKuXIXCaulQPMSjk8rtufVNzt1ymVvb6LM9DHmk%2FDPSD3WbGAaRZXT1mIcgIWZHXAAXTEM0eqSMng0cVuIKJKsnYnw2u%2Bz%2B2cdraXYfkG%2BTPVGkSPxyvnNbmrFDVyVFkLHqR9za%2FuKkiwNYd4BtXQFLbNsc32z71sJEksNZh7Ffd5vc%2FSgAjDl0YHpmMB2VUZi2NGN9ldVA9Ogr69Xkmb4zRJ3NJIC%2FdswmPsDzxIeMun87ypTtCfIYCz8%3D | AF101: =DATEDIF(TODAY(),U101,"D") -> #NUM! | AG101: =IFERROR(IF(Z101<>"",IF(AA101="",DATEDIF(Z101,TODAY(),"D"),DATEDIF(Z101,AA101,"D")),""),"") -> 752 | AI101: =IF(I101<>"",IF(F101<>"",CONCATENATE(I101," - ",G101," (",F101,")"),CONCATENATE(I101," - ",G101)),"") -> Álvaro de Souza Rodriguês Pinheiro - Cumprimento de sentença (0002921-29.2024.8.26.0506) | AJ101: =IF(I101<>"",IF(F101<>"",CONCATENATE(I101," - ",G101," (",F101,")"),CONCATENATE(I101," - ",G101)),"") -> Álvaro de Souza Rodriguês Pinheiro - Cumprimento de sentença (0002921-29.2024.8.26.0506)
B102: 97 | C102: Encerrado | D102: Administrativo | E102: Fase Inicial | F102: 66660-D8.2024.0.0.0727 | G102: Processo Administrativo Sancionatório | H102: Pessoa Jurídica | I102: Supermercados Big Compra Ltda. | J102: Autuado | K102: Fundação de Proteção e Defesa do Consumidor | L102: Fiscalizadora | M102: FERES JUNQUEIRA NAJM | N102: 150376 | S102: =IF(O102<>0,IF(P102<>0,SUM(P102+Q102*O102+O102*R102),IF(Q102<>0,SUM(P102+Q102*O102+O102*R102),"")),IF(P102<>0,SUM(P102+Q102*N102+N102*R102),IF(Q102<>0,SUM(P102+Q102*N102+N102*R102),""))) | T102: Não | V102: 1ª Instância | W102: São Paulo | Y102: Análise de Manifestação Preliminar | Z102: 45390 | AB102: =IFERROR(IF(Z102<>"",IF(AA102="",CONCATENATE(DATEDIF(Z102,TODAY(),"D")," dias"),CONCATENATE(DATEDIF(Z102,AA102,"D")," dias")),""),"") -> 689 dias | AF102: =DATEDIF(TODAY(),U102,"D") -> #NUM! | AG102: =IFERROR(IF(Z102<>"",IF(AA102="",DATEDIF(Z102,TODAY(),"D"),DATEDIF(Z102,AA102,"D")),""),"") -> 689 | AI102: =IF(I102<>"",IF(F102<>"",CONCATENATE(I102," - ",G102," (",F102,")"),CONCATENATE(I102," - ",G102)),"") -> Supermercados Big Compra Ltda. - Processo Administrativo Sancionatório (66660-D8.2024.0.0.0727) | AJ102: =IF(I102<>"",IF(F102<>"",CONCATENATE(I102," - ",G102," (",F102,")"),CONCATENATE(I102," - ",G102)),"") -> Supermercados Big Compra Ltda. - Processo Administrativo Sancionatório (66660-D8.2024.0.0.0727)
B103: 98 | C103: Encerrado | D103: Judicial | E103: Fase Inicial | F103: 1023115-33.2024.8.26.0506 | G103: Ação de Cobrança | H103: Pessoa Jurídica | I103: Hit Car Centro Automotivo LITDA. | J103: Autor | K103: AFSOL Energy Energia Fotovoltaica | L103: Réu | M103: FERES JUNQUEIRA NAJM | N103: 6000 | S103: =IF(O103<>0,IF(P103<>0,SUM(P103+Q103*O103+O103*R103),IF(Q103<>0,SUM(P103+Q103*O103+O103*R103),"")),IF(P103<>0,SUM(P103+Q103*N103+N103*R103),IF(Q103<>0,SUM(P103+Q103*N103+N103*R103),""))) | T103: Sim | V103: 1ª Instância | W103: Ribeirão Preto | X103: 9º Vara Cível | Y103: Aguardando despacho do Juiz | Z103: 45415 | AB103: =IFERROR(IF(Z103<>"",IF(AA103="",CONCATENATE(DATEDIF(Z103,TODAY(),"D")," dias"),CONCATENATE(DATEDIF(Z103,AA103,"D")," dias")),""),"") -> 664 dias | AD103: https://esaj.tjsp.jus.br/pastadigital/abrirPastaProcessoDigital.do?nuProcesso=1023115-33.2024.8.26.0506&cdProcesso=E2000RSGK0000&instanciaProcesso=pg&cdProcessoMaster=E2000RSGK0000&cdForo=506&baseIndice=INDDS&nmAlias=PG5RP&tpOrigem=2&flOrigem=P&cdServico=190101&acessibilidade=false&ticket=qGMmVKZGIcOxLeEcjaB5R56etG9PG6sC2ddHA0uWssC9jb5Wcfy3RoN41CKRmgXGWtxBWLLIkpdq44cvgLfXapElur%2Bk8m8uHYKEq9vnBjyeNMjz8Q%2BtpjRkZzFwu0h6uTd5gBE17nK8ACfcvdctvpXYmzgLD2nf%2FCm2bOvazir4fCSM5MploZgtEePPcRLEbaXRURa2dwayOVyAm4yh%2BFlDUL1ES4AGz09xbYvfFedM6GYGcfY229f9KdRiur%2BrbyMwDF9YYyPWDke96xqQavw2sCybMVhlVs8Y5ORud8kQNWRO0vKuXIXCaulQPMSjk8rtufVNzt1ymVvb6LM9DMeEVP5porWWb%2B045XkRJNcZGykHraBw0lI%2FmRtcUmb1repYMlFk3Q8rBOpLjBuhjSKKzmjwUwparkZQHEuZACnDSLaaQOoF7PmTh8tf4dV7xMShtjrcls8GPZwxnEF2sVYIWCwsQ5eeLJPmrFHeLCIHtpZlkRCO8aSm9%2FvZZTNaEB2rjLMtNuhuObBFsoCiCA%3D%3D | AF103: =DATEDIF(TODAY(),U103,"D") -> #NUM! | AG103: =IFERROR(IF(Z103<>"",IF(AA103="",DATEDIF(Z103,TODAY(),"D"),DATEDIF(Z103,AA103,"D")),""),"") -> 664 | AI103: =IF(I103<>"",IF(F103<>"",CONCATENATE(I103," - ",G103," (",F103,")"),CONCATENATE(I103," - ",G103)),"") -> Hit Car Centro Automotivo LITDA. - Ação de Cobrança (1023115-33.2024.8.26.0506) | AJ103: =IF(I103<>"",IF(F103<>"",CONCATENATE(I103," - ",G103," (",F103,")"),CONCATENATE(I103," - ",G103)),"") -> Hit Car Centro Automotivo LITDA. - Ação de Cobrança (1023115-33.2024.8.26.0506)
B104: 99 | C104: Ativo | D104: Judicial | E104: Fase Inicial | F104: 0010460-19.2024.5.15.0113 | G104: Reclamação Trabalhista | H104: Pessoa Jurídica | I104: Renove Casa & Design | J104: Réu | K104: Mariana Pereira da Silva | L104: Autor | M104: ADRIANO LOURENÇO MORAIS DOS SANTOS | N104: 109355.82 | S104: =IF(O104<>0,IF(P104<>0,SUM(P104+Q104*O104+O104*R104),IF(Q104<>0,SUM(P104+Q104*O104+O104*R104),"")),IF(P104<>0,SUM(P104+Q104*N104+N104*R104),IF(Q104<>0,SUM(P104+Q104*N104+N104*R104),""))) | T104: Não | V104: 1ª Instância | W104: Ribeirão Preto | X104: 5ª Vara Trabalhista | Y104: Aguardando despacho do Juiz | Z104: 45369 | AB104: =IFERROR(IF(Z104<>"",IF(AA104="",CONCATENATE(DATEDIF(Z104,TODAY(),"D")," dias"),CONCATENATE(DATEDIF(Z104,AA104,"D")," dias")),""),"") -> 710 dias | AD104: https://pje.trt15.jus.br/pjekz/processo/3925122/detalhe | AF104: =DATEDIF(TODAY(),U104,"D") -> #NUM! | AG104: =IFERROR(IF(Z104<>"",IF(AA104="",DATEDIF(Z104,TODAY(),"D"),DATEDIF(Z104,AA104,"D")),""),"") -> 710 | AI104: =IF(I104<>"",IF(F104<>"",CONCATENATE(I104," - ",G104," (",F104,")"),CONCATENATE(I104," - ",G104)),"") -> Renove Casa & Design - Reclamação Trabalhista (0010460-19.2024.5.15.0113) | AJ104: =IF(I104<>"",IF(F104<>"",CONCATENATE(I104," - ",G104," (",F104,")"),CONCATENATE(I104," - ",G104)),"") -> Renove Casa & Design - Reclamação Trabalhista (0010460-19.2024.5.15.0113)
...

Sheet Proc-D
B4: SELECIONE O PROCESSO →
B5: STATUS | C5: =IF(D5<>0,D5,"-") -> #N/A | D5: =INDEX('Proc-G'!C7:C88401,MATCH($C$4,'Proc-G'!AI7:AI88401,0)) -> #N/A
B6: PRAZO EM ABERTO? | C6: =IF(D6<>0,IF(D6="Não","Não",CONCATENATE("Sim (",TEXT(E6,"dd/mm/aaaa"),")")),"-") -> #N/A | D6: =INDEX('Proc-G'!T7:T88401,MATCH($C$4,'Proc-G'!AI7:AI88401,0)) -> #N/A | E6: =INDEX('Proc-G'!U7:U88401,MATCH($C$4,'Proc-G'!AI7:AI88401,0)) -> #N/A
B7: TIPO | C7: =IF(D7<>0,D7,"-") -> #N/A | D7: =INDEX('Proc-G'!D7:D88401,MATCH($C$4,'Proc-G'!AI7:AI88401,0)) -> #N/A
B8: FASE | C8: =IF(D8<>0,D8,"-") -> #N/A | D8: =INDEX('Proc-G'!E7:E88401,MATCH($C$4,'Proc-G'!AI7:AI88401,0)) -> #N/A
B9: QUALIFICAÇÃO DO CLIENTE | C9: =IF(D9<>0,D9,"-") -> #N/A | D9: =INDEX('Proc-G'!J7:J88401,MATCH($C$4,'Proc-G'!AI7:AI88401,0)) -> #N/A
B10: OUTRO ENVOLVIDO | C10: =IF(D10<>0,CONCATENATE(D10,IF(E10=0,"",CONCATENATE(" (",E10,")"))),"-") -> #N/A | D10: =INDEX('Proc-G'!K7:K88401,MATCH($C$4,'Proc-G'!AI7:AI88401,0)) -> #N/A | E10: =INDEX('Proc-G'!L7:L88401,MATCH($C$4,'Proc-G'!AI7:AI88401,0)) -> #N/A
B11: ADVOGADO | C11: =IF(D11<>0,D11,"-") -> #N/A | D11: =INDEX('Proc-G'!M7:M8401,MATCH($C$4,'Proc-G'!AI7:AI8401,0)) -> #N/A
B12: VALOR DA CAUSA | C12: =IF(D12<>0,D12,"-") -> #N/A | D12: =INDEX('Proc-G'!N7:N8401,MATCH($C$4,'Proc-G'!AI7:AI8401,0)) -> #N/A
B13: VALOR DE HONORÁRIOS FIXOS EM R$ | C13: =IF(D13<>0,D13,"-") -> #N/A | D13: =INDEX('Proc-G'!P7:P8401,MATCH($C$4,'Proc-G'!AI7:AI8401,0)) -> #N/A
B14: VALOR DE HONORÁRIOS EM % | C14: =IF(D14<>0,D14,"-") -> #N/A | D14: =INDEX('Proc-G'!Q7:Q8401,MATCH($C$4,'Proc-G'!AI7:AI8401,0)) -> #N/A
B15: VALOR TOTAL DE HONORÁRIOS (FIXO + %) | C15: =IF(D15<>0,D15,"-") -> #N/A | D15: =INDEX('Proc-G'!S7:S8401,MATCH($C$4,'Proc-G'!AI7:AI8401,0)) -> #N/A
B16: INSTÂNCIA | C16: =IF(D16<>0,D16,"-") -> #N/A | D16: =INDEX('Proc-G'!V7:V8401,MATCH($C$4,'Proc-G'!AI7:AI8401,0)) -> #N/A
B17: COMARCA | C17: =IF(D17<>0,D17,"-") -> #N/A | D17: =INDEX('Proc-G'!W7:W8401,MATCH($C$4,'Proc-G'!AI7:AI8401,0)) -> #N/A
B18: VARA | C18: =IF(D18<>0,D18,"-") -> #N/A | D18: =INDEX('Proc-G'!X7:X8401,MATCH($C$4,'Proc-G'!AI7:AI8401,0)) -> #N/A
B19: OBSERVAÇÕES | C19: =IF(D19<>0,D19,"-") -> #N/A | D19: =INDEX('Proc-G'!Y7:Y8401,MATCH($C$4,'Proc-G'!AI7:AI8401,0)) -> #N/A
B20: TEMPO DE PROCESSO | C20: =IF(D20<>0,CONCATENATE("Início: ",TEXT(D20,"dd/mm/aaaa"),IF(E20=0,"",CONCATENATE(" - ","Encerramento: ",TEXT(E20,"dd/mm/aaaa")))," (",F20,")"),"-") -> #N/A | D20: =INDEX('Proc-G'!Z7:Z8401,MATCH($C$4,'Proc-G'!AI7:AI8401,0)) -> #N/A | E20: =INDEX('Proc-G'!AA7:AA8401,MATCH($C$4,'Proc-G'!AI7:AI8401,0)) -> #N/A | F20: =INDEX('Proc-G'!AB7:AB8401,MATCH($C$4,'Proc-G'!AI7:AI8401,0)) -> #N/A
B21: RESULTADO | C21: =IF(D21<>0,D21,"-") -> #N/A | D21: =INDEX('Proc-G'!AC7:AC8401,MATCH($C$4,'Proc-G'!AI7:AI8401,0)) -> #N/A
B22: LINK DO PROCESSO | C22: =IF(D22<>0,D22,"-") -> #N/A | D22: =INDEX('Proc-G'!AD7:AD8401,MATCH($C$4,'Proc-G'!AI7:AI8401,0)) -> #N/A
B23: LINK PARA PASTA DE DOCUMENTOS DIGITAL | C23: =IF(D23<>0,D23,"-") -> #N/A | D23: =INDEX('Proc-G'!AE7:AE8401,MATCH($C$4,'Proc-G'!AI7:AI8401,0)) -> #N/A
B25: MOVIMENTAÇÕES
B26: DATA | C26: MOVIMENTAÇÃO
B27: =IFERROR(VLOOKUP($C$4&ROW(A1),'Proc-M'!$A$5:$E$8402,5,0),"") | C27: =IFERROR(VLOOKUP($C$4&ROW(A1),'Proc-M'!$A$5:$E$8402,4,0),"")
B28: =IFERROR(VLOOKUP($C$4&ROW(A2),'Proc-M'!$A$5:$E$8402,5,0),"") | C28: =IFERROR(VLOOKUP($C$4&ROW(A2),'Proc-M'!$A$5:$E$8402,4,0),"")
B29: =IFERROR(VLOOKUP($C$4&ROW(A3),'Proc-M'!$A$5:$E$8402,5,0),"") | C29: =IFERROR(VLOOKUP($C$4&ROW(A3),'Proc-M'!$A$5:$E$8402,4,0),"")
B30: =IFERROR(VLOOKUP($C$4&ROW(A4),'Proc-M'!$A$5:$E$8402,5,0),"") | C30: =IFERROR(VLOOKUP($C$4&ROW(A4),'Proc-M'!$A$5:$E$8402,4,0),"")
B31: =IFERROR(VLOOKUP($C$4&ROW(A5),'Proc-M'!$A$5:$E$8402,5,0),"") | C31: =IFERROR(VLOOKUP($C$4&ROW(A5),'Proc-M'!$A$5:$E$8402,4,0),"")
B32: =IFERROR(VLOOKUP($C$4&ROW(A6),'Proc-M'!$A$5:$E$8402,5,0),"") | C32: =IFERROR(VLOOKUP($C$4&ROW(A6),'Proc-M'!$A$5:$E$8402,4,0),"")
B33: =IFERROR(VLOOKUP($C$4&ROW(A7),'Proc-M'!$A$5:$E$8402,5,0),"") | C33: =IFERROR(VLOOKUP($C$4&ROW(A7),'Proc-M'!$A$5:$E$8402,4,0),"")
B34: =IFERROR(VLOOKUP($C$4&ROW(A8),'Proc-M'!$A$5:$E$8402,5,0),"") | C34: =IFERROR(VLOOKUP($C$4&ROW(A8),'Proc-M'!$A$5:$E$8402,4,0),"")
B35: =IFERROR(VLOOKUP($C$4&ROW(A9),'Proc-M'!$A$5:$E$8402,5,0),"") | C35: =IFERROR(VLOOKUP($C$4&ROW(A9),'Proc-M'!$A$5:$E$8402,4,0),"")
B36: =IFERROR(VLOOKUP($C$4&ROW(A10),'Proc-M'!$A$5:$E$8402,5,0),"") | C36: =IFERROR(VLOOKUP($C$4&ROW(A10),'Proc-M'!$A$5:$E$8402,4,0),"")
B37: =IFERROR(VLOOKUP($C$4&ROW(A11),'Proc-M'!$A$5:$E$8402,5,0),"") | C37: =IFERROR(VLOOKUP($C$4&ROW(A11),'Proc-M'!$A$5:$E$8402,4,0),"")
B38: =IFERROR(VLOOKUP($C$4&ROW(A12),'Proc-M'!$A$5:$E$8402,5,0),"") | C38: =IFERROR(VLOOKUP($C$4&ROW(A12),'Proc-M'!$A$5:$E$8402,4,0),"")
... B44: =IFERROR(VLOOKUP($C$4&ROW(A18),'Proc-M'!$A$5:$E$8402,5,0),"") | C44: =IFERROR(VLOOKUP($C$4&ROW(A18),'Proc-M'!$A$5:$E$8402,4,0),"")
B45: =IFERROR(VLOOKUP($C$4&ROW(#REF!),'Proc-M'!$A$5:$E$8402,5,0),"") | C45: =IFERROR(VLOOKUP($C$4&ROW(#REF!),'Proc-M'!$A$5:$E$8402,4,0),"")
B46: =IFERROR(VLOOKUP($C$4&ROW(A19),'Proc-M'!$A$5:$E$8402,5,0),"") | C46: =IFERROR(VLOOKUP($C$4&ROW(A19),'Proc-M'!$A$5:$E$8402,4,0),"")
B47: =IFERROR(VLOOKUP($C$4&ROW(A20),'Proc-M'!$A$5:$E$8402,5,0),"") | C47: =IFERROR(VLOOKUP($C$4&ROW(A20),'Proc-M'!$A$5:$E$8402,4,0),"")
B48: =IFERROR(VLOOKUP($C$4&ROW(A22),'Proc-M'!$A$5:$E$8402,5,0),"") | C48: =IFERROR(VLOOKUP($C$4&ROW(A22),'Proc-M'!$A$5:$E$8402,4,0),"")
B49: =IFERROR(VLOOKUP($C$4&ROW(A23),'Proc-M'!$A$5:$E$8402,5,0),"") | C49: =IFERROR(VLOOKUP($C$4&ROW(A23),'Proc-M'!$A$5:$E$8402,4,0),"")
B50: =IFERROR(VLOOKUP($C$4&ROW(A24),'Proc-M'!$A$5:$E$8402,5,0),"") | C50: =IFERROR(VLOOKUP($C$4&ROW(A24),'Proc-M'!$A$5:$E$8402,4,0),"")
B51: =IFERROR(VLOOKUP($C$4&ROW(A25),'Proc-M'!$A$5:$E$8402,5,0),"") | C51: =IFERROR(VLOOKUP($C$4&ROW(A25),'Proc-M'!$A$5:$E$8402,4,0),"")
B52: =IFERROR(VLOOKUP($C$4&ROW(A26),'Proc-M'!$A$5:$E$8402,5,0),"") | C52: =IFERROR(VLOOKUP($C$4&ROW(A26),'Proc-M'!$A$5:$E$8402,4,0),"")
B53: =IFERROR(VLOOKUP($C$4&ROW(A27),'Proc-M'!$A$5:$E$8402,5,0),"") | C53: =IFERROR(VLOOKUP($C$4&ROW(A27),'Proc-M'!$A$5:$E$8402,4,0),"")
B54: =IFERROR(VLOOKUP($C$4&ROW(A28),'Proc-M'!$A$5:$E$8402,5,0),"") | C54: =IFERROR(VLOOKUP($C$4&ROW(A28),'Proc-M'!$A$5:$E$8402,4,0),"")
B55: =IFERROR(VLOOKUP($C$4&ROW(A29),'Proc-M'!$A$5:$E$8402,5,0),"") | C55: =IFERROR(VLOOKUP($C$4&ROW(A29),'Proc-M'!$A$5:$E$8402,4,0),"")
B56: =IFERROR(VLOOKUP($C$4&ROW(A30),'Proc-M'!$A$5:$E$8402,5,0),"") | C56: =IFERROR(VLOOKUP($C$4&ROW(A30),'Proc-M'!$A$5:$E$8402,4,0),"")
B57: =IFERROR(VLOOKUP($C$4&ROW(A31),'Proc-M'!$A$5:$E$8402,5,0),"") | C57: =IFERROR(VLOOKUP($C$4&ROW(A31),'Proc-M'!$A$5:$E$8402,4,0),"")
B58: =IFERROR(VLOOKUP($C$4&ROW(A32),'Proc-M'!$A$5:$E$8402,5,0),"") | C58: =IFERROR(VLOOKUP($C$4&ROW(A32),'Proc-M'!$A$5:$E$8402,4,0),"")
B59: =IFERROR(VLOOKUP($C$4&ROW(A33),'Proc-M'!$A$5:$E$8402,5,0),"") | C59: =IFERROR(VLOOKUP($C$4&ROW(A33),'Proc-M'!$A$5:$E$8402,4,0),"")
... B83: =IFERROR(VLOOKUP($C$4&ROW(A57),'Proc-M'!$A$5:$E$8402,5,0),"") | C83: =IFERROR(VLOOKUP($C$4&ROW(A57),'Proc-M'!$A$5:$E$8402,4,0),"")

Sheet Proc-M
B4: # | C4: Processo Referência | D4: Movimentação | E4: Data
A5: =C5&COUNTIF($C$5:C5,C5) -> 0 | B5: 1
A6: =C6&COUNTIF($C$5:C6,C6) -> 0 | B6: 2
A7: =C7&COUNTIF($C$5:C7,C7) -> 0 | B7: 3
A8: =C8&COUNTIF($C$5:C8,C8) -> 0 | B8: 4
A9: =C9&COUNTIF($C$5:C9,C9) -> 0 | B9: 5
A10: =C10&COUNTIF($C$5:C10,C10) -> 0 | B10: 6
A11: =C11&COUNTIF($C$5:C11,C11) -> 0 | B11: 7
A12: =C12&COUNTIF($C$5:C12,C12) -> 0 | B12: 8
A13: =C13&COUNTIF($C$5:C13,C13) -> 0 | B13: 9
A14: =C14&COUNTIF($C$5:C14,C14) -> 0 | B14: 10
A15: =C15&COUNTIF($C$5:C15,C15) -> 0 | B15: 11
A16: =C16&COUNTIF($C$5:C16,C16) -> 0 | B16: 12
... A3060: =C3060&COUNTIF($C$5:C3060,C3060) -> 0 | B3060: 3056

Sheet P-Das1
H5: PROCESSOS POR ADVOGADO | O5: =COUNTIF('Proc-G'!C7:C8492,"Encerrado") -> 93 | P5: =SUM(O5:O6) -> 227
H6: =IF('Conf-G'!D5<>"",'Conf-G'!D5,"") -> ADRIANO LOURENÇO MORAIS DOS SANTOS | I6: =IF(H6<>"",COUNTIF('Proc-G'!M7:M1492,'P-Das1'!H6),"") -> 68 | O6: =COUNTIF('Proc-G'!C7:C8492,"Ativo") -> 134
H7: =IF('Conf-G'!D6<>"",'Conf-G'!D6,"") -> FERES JUNQUEIRA NAJM | I7: =IF(H7<>"",COUNTIF('Proc-G'!M7:M1492,'P-Das1'!H7),"") -> 143 | O7: =SUM('Proc-G'!S7:S8492) -> 22886.367
H8: =IF('Conf-G'!D7<>"",'Conf-G'!D7,"") | I8: =IF(H8<>"",COUNTIF('Proc-G'!M7:M1492,'P-Das1'!H8),"") | O8: =SUM('Proc-G'!N7:N8492) -> 8.3164662e+08
H9: =IF('Conf-G'!D8<>"",'Conf-G'!D8,"") | I9: =IF(H9<>"",COUNTIF('Proc-G'!M7:M1492,'P-Das1'!H9),"") | O9: =MAX('Proc-G'!N7:N8492) -> 8.2391981e+08
H10: =IF('Conf-G'!D9<>"",'Conf-G'!D9,"") | I10: =IF(H10<>"",COUNTIF('Proc-G'!M7:M1492,'P-Das1'!H10),"") | O10: =MAX('Proc-G'!S7:S8492) -> 1200
H11: =IF('Conf-G'!D10<>"",'Conf-G'!D10,"") | I11: =IF(H11<>"",COUNTIF('Proc-G'!M7:M1492,'P-Das1'!H11),"") | O11: =INT(AVERAGE('Proc-G'!AG7:AG8492)) -> 763 | P11: =CONCATENATE(O11," dias") -> 763 dias
D12: Resultado dos Processos | H12: =IF('Conf-G'!D11<>"",'Conf-G'!D11,"") | I12: =IF(H12<>"",COUNTIF('Proc-G'!M7:M1492,'P-Das1'!H12),"") | O12: Pessoa Física | P12: =COUNTIF('Proc-G'!H7:H8492,"Pessoa Física") -> 39
D13: Acordo | E13: =COUNTIF('Proc-G'!$AC$7:$AC$1492,D13) -> 8 | F13: =E13/SUM($E$13:$E$17) -> 0.44444444 | H13: =IF('Conf-G'!D12<>"",'Conf-G'!D12,"") | I13: =IF(H13<>"",COUNTIF('Proc-G'!M7:M1492,'P-Das1'!H13),"") | O13: Pessoa Jurídica | P13: =COUNTIF('Proc-G'!H7:H1492,"Pessoa Jurídica") -> 171
D14: Extinto | E14: =COUNTIF('Proc-G'!$AC$7:$AC$1492,D14) -> 2 | F14: =E14/SUM($E$13:$E$17) -> 0.11111111 | H14: =IF('Conf-G'!D13<>"",'Conf-G'!D13,"") | I14: =IF(H14<>"",COUNTIF('Proc-G'!M7:M1492,'P-Das1'!H14),"")
D15: Improcedente | E15: =COUNTIF('Proc-G'!$AC$7:$AC$1492,D15) -> 2 | F15: =E15/SUM($E$13:$E$17) -> 0.11111111 | H15: =IF('Conf-G'!D14<>"",'Conf-G'!D14,"") | I15: =IF(H15<>"",COUNTIF('Proc-G'!M7:M1492,'P-Das1'!H15),"")
D16: Parcialmente Procedente | E16: =COUNTIF('Proc-G'!$AC$7:$AC$1492,D16) -> 3 | F16: =E16/SUM($E$13:$E$17) -> 0.16666667 | H16: =IF('Conf-G'!D15<>"",'Conf-G'!D15,"") | I16: =IF(H16<>"",COUNTIF('Proc-G'!M7:M1492,'P-Das1'!H16),"")
D17: Procedente | E17: =COUNTIF('Proc-G'!$AC$7:$AC$1492,D17) -> 3 | F17: =E17/SUM($E$13:$E$17) -> 0.16666667 | H17: =IF('Conf-G'!D16<>"",'Conf-G'!D16,"") | I17: =IF(H17<>"",COUNTIF('Proc-G'!M7:M1492,'P-Das1'!H17),"")
H18: =IF('Conf-G'!D17<>"",'Conf-G'!D17,"") | I18: =IF(H18<>"",COUNTIF('Proc-G'!M7:M1492,'P-Das1'!H18),"")
H19: =IF('Conf-G'!D18<>"",'Conf-G'!D18,"") | I19: =IF(H19<>"",COUNTIF('Proc-G'!M7:M1492,'P-Das1'!H19),"")
H20: =IF('Conf-G'!D19<>"",'Conf-G'!D19,"") | I20: =IF(H20<>"",COUNTIF('Proc-G'!M7:M1492,'P-Das1'!H20),"")
H21: =IF('Conf-G'!D20<>"",'Conf-G'!D20,"") | I21: =IF(H21<>"",COUNTIF('Proc-G'!M7:M1492,'P-Das1'!H21),"")
H22: =IF('Conf-G'!D21<>"",'Conf-G'!D21,"") | I22: =IF(H22<>"",COUNTIF('Proc-G'!M7:M1492,'P-Das1'!H22),"")
H23: =IF('Conf-G'!D22<>"",'Conf-G'!D22,"") | I23: =IF(H23<>"",COUNTIF('Proc-G'!M7:M1492,'P-Das1'!H23),"")
C33: =IF('Conf-G'!D23<>"",'Conf-G'!D23,"") | D33: =IF(C33<>"",COUNTIF('Proc-G'!M25:M417,'P-Das1'!C33),"")
C34: =IF('Conf-G'!D24<>"",'Conf-G'!D24,"") | D34: =IF(C34<>"",COUNTIF('Proc-G'!M26:M418,'P-Das1'!C34),"")
C35: =IF('Conf-G'!D25<>"",'Conf-G'!D25,"")
C36: =IF('Conf-G'!D26<>"",'Conf-G'!D26,"")
C37: =IF('Conf-G'!D27<>"",'Conf-G'!D27,"")

Sheet Clie-F
G3: =CONCATENATE("Clientes de aniversário hoje: ",I3," (em laranja)") -> Clientes de aniversário hoje: 0 (em laranja) | I3: =COUNTIF(U5:U9999,J3) -> 0 | J3: =DAY(TODAY())&"/"&MONTH(TODAY()) -> 26/2
C4: # | D4: Nome | E4: CPF | F4: Sexo | G4: Data de Nascimento | H4: Idade | I4: Telefone | J4: E-mail | K4: Endereço | L4: Bairro | M4: CEP | N4: Cidade | O4: Estado | P4: Profissão | Q4: Estado Civil | R4: Como nos Conheceu | S4: Observações | T4: Data de Cadastro
A5: =B5&"--"&COUNTIF($B$5:B5,B5) -> 10--1 | B5: =IF(G5<>"",MONTH(G5),"") -> 10 | C5: 1 | D5: Ademilson Moreira de Souza | E5: 122.868.968-79 | F5: M | G5: 26573 | H5: =IF(G5,DATEDIF(G5,TODAY(),"Y"),"") -> 53 | J5: contato@lourencoenajm.adv.br | K5: Rua Antônio Marinoni, 306 | L5: Mir. Dos Ovnis | M5: 18.116-420 | N5: Votorantim | O5: SP | P5: Desempregado | Q5: Casado(a) | R5: Outros | T5: 44319 | U5: =DAY(G5)&"/"&MONTH(G5) -> 1/10
A6: =B6&"--"&COUNTIF($B$5:B6,B6) -> 9--1 | B6: =IF(G6<>"",MONTH(G6),"") -> 9 | C6: 2 | D6: Alcir Santos Simões Junior | E6: 452.124.528-56 | F6: M | G6: 35332 | H6: =IF(G6,DATEDIF(G6,TODAY(),"Y"),"") -> 29 | J6: contato@lourencoenajm.adv.br | K6: Avenida Sargento Da Aeronáutica Plínio F. Golçalves, 959 - Casa 01 | L6: Jardim Cumbica | M6: 7181100 | N6: Guarulhos | O6: SP | P6: Lavador de Carros | Q6: Casado(a) | R6: Parceria | S6: Parceria com Renato/Luciano | T6: 44311 | U6: =DAY(G6)&"/"&MONTH(G6) -> 24/9
A7: =B7&"--"&COUNTIF($B$5:B7,B7) -> 7--1 | B7: =IF(G7<>"",MONTH(G7),"") -> 7 | C7: 3 | D7: Alessandro de Moura | E7: 210.433.798-43 | F7: M | G7: 27589 | H7: =IF(G7,DATEDIF(G7,TODAY(),"Y"),"") -> 50 | J7: contato@lourencoenajm.adv.br | K7: Travessa 02 - Rua Bastos, 58 | L7: Jardim Tamoio | M7: 13.219-323 | N7: Jundiaí | O7: SP | P7: Desempregado | Q7: Casado(a) | R7: Parceria | S7: Parceria com Renato/Luciano | T7: 44239 | U7: =DAY(G7)&"/"&MONTH(G7) -> 14/7
A8: =B8&"--"&COUNTIF($B$5:B8,B8) -> 3--1 | B8: =IF(G8<>"",MONTH(G8),"") -> 3 | C8: 4 | D8: Ariane dos Santos | E8: 381.739.388-14 | F8: F | G8: 32593 | H8: =IF(G8,DATEDIF(G8,TODAY(),"Y"),"") -> 36 | J8: contato@lourencoenajm.adv.br | K8: Rua Otávio Zanqueta, 391 | L8: Santa Isabel | M8: 14.600-000 | N8: São Joaquim da Barra | O8: SP | P8: Funcionária Pública Estadual | Q8: Casado(a) | R8: É Família/Amigo | S8: Família/Dr. Adriano | T8: 44949 | U8: =DAY(G8)&"/"&MONTH(G8) -> 26/3
A9: =B9&"--"&COUNTIF($B$5:B9,B9) -> 3--2 | B9: =IF(G9<>"",MONTH(G9),"") -> 3 | C9: 5 | D9: Ariane Frare | E9: 347.297.298-03 | F9: F | G9: 31481 | H9: =IF(G9,DATEDIF(G9,TODAY(),"Y"),"") -> 39 | J9: contato@lourencoenajm.adv.br | K9: Rua Eduardo Póvoa, 223 | L9: Santa Gertrudes | M9: 13.205-170 | N9: Jundiaí | O9: SP | P9: Operadora de Caixa | Q9: Casado(a) | R9: Outros | T9: 44980 | U9: =DAY(G9)&"/"&MONTH(G9) -> 10/3
A10: =B10&"--"&COUNTIF($B$5:B10,B10) -> 4--1 | B10: =IF(G10<>"",MONTH(G10),"") -> 4 | C10: 6 | D10: Arlene Sofiati Salgado | E10: 323.753.518-43 | F10: F | G10: 30793 | H10: =IF(G10,DATEDIF(G10,TODAY(),"Y"),"") -> 41 | J10: contato@lourencoenajm.adv.br | K10: Av. Comandante Salgado, 392 | L10: Bairro Castelo | M10: 14.300-000 | N10: Batatais | O10: SP | P10: Professora da Rede Municipal | Q10: Solteiro(a) | R10: É Família/Amigo | S10: Cunhada do Dr. Adriano | T10: 43578 | U10: =DAY(G10)&"/"&MONTH(G10) -> 21/4
A11: =B11&"--"&COUNTIF($B$5:B11,B11) -> 8--1 | B11: =IF(G11<>"",MONTH(G11),"") -> 8 | C11: 7 | D11: Cristiano Alves Dos Santos | E11: 019.955.135-98 | F11: M | G11: 29437 | H11: =IF(G11,DATEDIF(G11,TODAY(),"Y"),"") -> 45 | J11: contato@lourencoenajm.adv.br | K11: Rua Maria Barrelaro Lepero, 313 | L11: Jardim Paraiso | M11: 18.550-000 | N11: Boituva | O11: SP | P11: Auxiliar de Produção | Q11: Solteiro(a) | R11: Outros | T11: 44872 | U11: =DAY(G11)&"/"&MONTH(G11) -> 4/8
A12: =B12&"--"&COUNTIF($B$5:B12,B12) -> 8--2 | B12: =IF(G12<>"",MONTH(G12),"") -> 8 | C12: 8 | D12: Daniel Alexandre Picão Alves | E12: 247.527.458-10 | F12: M | G12: 28002 | H12: =IF(G12,DATEDIF(G12,TODAY(),"Y"),"") -> 49 | J12: daniel.picao@yahoo.com | K12: Rua Prof. Sylvio Marcondes, 226 | L12: City Ribeirão | M12: 14.021-410 | N12: Ribeirão Preto | O12: SP | P12: Funcionário Público Estadual | Q12: Casado(a) | R12: É Família/Amigo | S12: Amigo/Dr. Feres | T12: 44599 | U12: =DAY(G12)&"/"&MONTH(G12) -> 30/8
A13: =B13&"--"&COUNTIF($B$5:B13,B13) -> 5--1 | B13: =IF(G13<>"",MONTH(G13),"") -> 5 | C13: 9 | D13: Danielle Contin Nader | E13: 442.101.398-66 | F13: F | G13: 34848 | H13: =IF(G13,DATEDIF(G13,TODAY(),"Y"),"") -> 30 | J13: daniellenader@hotmail.com | K13: Rua São José, 450 - Apart. 30 | L13: Centro | M13: 14.010-160 | N13: Ribeirão Preto | O13: SP | P13: Jornalista | Q13: Casado(a) | R13: Indicação | T13: 44298 | U13: =DAY(G13)&"/"&MONTH(G13) -> 29/5
A14: =B14&"--"&COUNTIF($B$5:B14,B14) -> 3--3 | B14: =IF(G14<>"",MONTH(G14),"") -> 3 | C14: 10 | D14: Edgar Dreger | E14: 615.643.549-20 | F14: M | G14: 23831 | H14: =IF(G14,DATEDIF(G14,TODAY(),"Y"),"") -> 60 | J14: contato@lourencoenajm.adv.br | K14: Estrada Municipal Caçapava, 24 | L14: Indaiatuba | M14: 18.540-000 | N14: Porto Feliz | O14: SP | P14: Desempregado | Q14: Casado(a) | R14: Indicação | S14: Parceria com Renato/Luciano | T14: 44232 | U14: =DAY(G14)&"/"&MONTH(G14) -> 30/3
A15: =B15&"--"&COUNTIF($B$5:B15,B15) -> 7--2 | B15: =IF(G15<>"",MONTH(G15),"") -> 7 | C15: 11 | D15: Edson José Marques | E15: 640.644.2580-04 | F15: M | G15: 18815 | H15: =IF(G15,DATEDIF(G15,TODAY(),"Y"),"") -> 74 | I15: 16- 99296-6935 | J15: edsonjmarques81@gmail.com | K15: Rua Ernesto Petersen, 476 | L15: Quintino Facci II | M15: 14.070-480 | N15: Ribeirão Preto | O15: SP | P15: Aposentado | Q15: Casado(a) | R15: Indicação | S15: Pai do Fernando (Estagiário) | T15: 44652 | U15: =DAY(G15)&"/"&MONTH(G15) -> 6/7
A16: =B16&"--"&COUNTIF($B$5:B16,B16) -> 7--3 | B16: =IF(G16<>"",MONTH(G16),"") -> 7 | C16: 12 | D16: Eleanderson Marcos de Souza Santos | E16: 078.217.636-40 | F16: M | G16: 31979 | H16: =IF(G16,DATEDIF(G16,TODAY(),"Y"),"") -> 38 | J16: contato@lourencoenajm.adv.br | K16: Rua Manoel Francisco Loureiro, 58 | L16: Vila Cláudia | M16: 14.140-000 | N16: Cravinhos | O16: SP | P16: Desempregado | Q16: Casado(a) | R16: Indicação | T16: 43893 | U16: =DAY(G16)&"/"&MONTH(G16) -> 21/7
A17: =B17&"--"&COUNTIF($B$5:B17,B17) -> 6--1 | B17: =IF(G17<>"",MONTH(G17),"") -> 6 | C17: 13 | D17: Felipe Augusto Taveiros Palei | E17: 369.166.168-81 | F17: M | G17: 32303 | H17: =IF(G17,DATEDIF(G17,TODAY(),"Y"),"") -> 37 | J17: augftp88@gmail.com | K17: Rui Barbosa, 196 - Apart. 74 | L17: Centro | M17: 14.015-120 | N17: Ribeirão Preto | O17: SP | P17: Autônomo | Q17: Solteiro(a) | R17: É Família/Amigo | U17: =DAY(G17)&"/"&MONTH(G17) -> 9/6
A18: =B18&"--"&COUNTIF($B$5:B18,B18) -> 9--2 | B18: =IF(G18<>"",MONTH(G18),"") -> 9 | C18: 14 | D18: Fernando José Pereira | E18: 041.031.458-70 | F18: M | G18: 22914 | H18: =IF(G18,DATEDIF(G18,TODAY(),"Y"),"") -> 63 | I18: 16-99335-3157 | J18: ferjhosepwhite@gmail.com | K18: Av. General Euclides de Figueireido | L18: Adelino Simioni | M18: 14.070-260 | N18: Ribeirão Preto | O18: SP | P18: Aposentado | Q18: Casado(a) | R18: Outros | T18: 44652 | U18: =DAY(G18)&"/"&MONTH(G18) -> 25/9
A19: =B19&"--"&COUNTIF($B$5:B19,B19) -> 10--2 | B19: =IF(G19<>"",MONTH(G19),"") -> 10 | C19: 15 | D19: Giuseppe Bonjovani de Paiva | E19: 469.612.138-04 | F19: M | G19: 35723 | H19: =IF(G19,DATEDIF(G19,TODAY(),"Y"),"") -> 28 | J19: giu_bp@hotmail.com | K19: Rua Sergipe, 285 | L19: Campos Elíseos | M19: 14.080-040 | N19: Ribeirão Preto | O19: SP | P19: Auxiliar Administrativo | Q19: Solteiro(a) | R19: Outros | T19: 44474 | U19: =DAY(G19)&"/"&MONTH(G19) -> 20/10
A20: =B20&"--"&COUNTIF($B$5:B20,B20) -> 10--3 | B20: =IF(G20<>"",MONTH(G20),"") -> 10 | C20: 16 | D20: Joao Henrique Cruz Tassinari | E20: 183.319.938-37 | F20: M | G20: 27322 | H20: =IF(G20,DATEDIF(G20,TODAY(),"Y"),"") -> 51 | J20: jtassinari2010@hotmail.com | K20: Rua Nair Estrada Trujilo, 312 | L20: Jardim Diva Tarlá de Carvalho | M20: 14.079-405 | N20: Ribeirão Preto | O20: SP | P20: Vendedor | Q20: Casado(a) | R20: Outros | T20: 44599 | U20: =DAY(G20)&"/"&MONTH(G20) -> 20/10
A21: =B21&"--"&COUNTIF($B$5:B21,B21) -> 12--1 | B21: =IF(G21<>"",MONTH(G21),"") -> 12 | C21: 17 | D21: Julio Cesar Borges | E21: 276.016.638-41 | F21: M | G21: 29190 | H21: =IF(G21,DATEDIF(G21,TODAY(),"Y"),"") -> 46 | J21: ac.julio@hotmail.com | K21: Rua Onze de Agosto, 233 - Apart. 63 | L21: Campos Elíseos | M21: 14.085-030 | N21: Ribeirão Preto | O21: SP | P21: Advogado | Q21: Casado(a) | R21: Outros | T21: 44313 | U21: =DAY(G21)&"/"&MONTH(G21) -> 1/12
A22: =B22&"--"&COUNTIF($B$5:B22,B22) -> 2--1 | B22: =IF(G22<>"",MONTH(G22),"") -> 2 | C22: 18 | D22: Letícia Campos Jorge | E22: 067.682.976-78 | F22: F | G22: 30716 | H22: =IF(G22,DATEDIF(G22,TODAY(),"Y"),"") -> 42 | J22: lezinhautsch@gmail.com | K22: Av. Prof.ª. Edu Rangel Rabelo, 405, bloco 28 - apart. 101 | L22: Manoel Pena | M22: 14.098-331 | N22: Ribeirão Preto | O22: SP | P22: Desempregada | Q22: União Estável | R22: Outros | T22: 44454 | U22: =DAY(G22)&"/"&MONTH(G22) -> 4/2
A23: =B23&"--"&COUNTIF($B$5:B23,B23) -> 8--3 | B23: =IF(G23<>"",MONTH(G23),"") -> 8 | C23: 19 | D23: Luzia Inagaki | E23: 285.262.708-69 | F23: F | G23: 29458 | H23: =IF(G23,DATEDIF(G23,TODAY(),"Y"),"") -> 45 | J23: contato@lourencoenajm.adv.br | K23: Rua Joao Gasparini, 121 | L23: Vila São João | M23: 13.295-000 | N23: Itupeva | O23: SP | P23: Desempregado | Q23: Casado(a) | R23: Parceria | S23: Parceria com Renato/Luciano | T23: 44294 | U23: =DAY(G23)&"/"&MONTH(G23) -> 25/8
A24: =B24&"--"&COUNTIF($B$5:B24,B24) -> 7--4 | B24: =IF(G24<>"",MONTH(G24),"") -> 7 | C24: 20 | D24: Maria Angélica Cal Garcia Prado | E24: 365.329.298-08 | F24: F | G24: 31614 | H24: =IF(G24,DATEDIF(G24,TODAY(),"Y"),"") -> 39 | J24: angelica_calgarcia@yahoo.com.br | K24: Rua Alice Manrique Gabriel, 204 - Quadra A3, Lote 24 | L24: Caguaçu | M24: 18.074-752 | N24: Sorocaba | O24: SP | P24: Funcionária Pública Estadual | Q24: Casado(a) | R24: Outros | T24: 44361 | U24: =DAY(G24)&"/"&MONTH(G24) -> 21/7
A25: =B25&"--"&COUNTIF($B$5:B25,B25) -> 7--5 | B25: =IF(G25<>"",MONTH(G25),"") -> 7 | C25: 21 | D25: Maria Neide Ribas Silva | E25: 030.018.446-80 | F25: F | G25: 27953 | H25: =IF(G25,DATEDIF(G25,TODAY(),"Y"),"") -> 49 | J25: contato@lourencoenajm.adv.br | K25: Rua Nair Estrada Trujilo, 312 | L25: Jardim Diva Tarlá de Carvalho | M25: 14.079-405 | N25: Ribeirão Preto | O25: SP | P25: Do Lar | Q25: Viúvo(a) | R25: Outros | T25: 42888 | U25: =DAY(G25)&"/"&MONTH(G25) -> 12/7
A26: =B26&"--"&COUNTIF($B$5:B26,B26) -> 5--2 | B26: =IF(G26<>"",MONTH(G26),"") -> 5 | C26: 22 | D26: Maria Regina Dos Santos Geraldo | E26: 980.738.698-53 | F26: F | G26: 18401 | H26: =IF(G26,DATEDIF(G26,TODAY(),"Y"),"") -> 75 | J26: contato@lourencoenajm.adv.br | K26: Rua Luís Gomes, 255 | L26: Jardim Paulista | M26: 14.090-220 | N26: Ribeirão Preto | O26: SP | P26: Aposentada | Q26: Viúvo(a) | R26: Outros | T26: 43167 | U26: =DAY(G26)&"/"&MONTH(G26) -> 18/5
A27: =B27&"--"&COUNTIF($B$5:B27,B27) -> 2--2 | B27: =IF(G27<>"",MONTH(G27),"") -> 2 | C27: 23 | D27: Micaela Da Silva Gomes | E27: 480.693.368-62 | F27: F | G27: 36198 | H27: =IF(G27,DATEDIF(G27,TODAY(),"Y"),"") -> 27 | J27: gomesmicaela444@gmail.com | K27: Cel. Francisco Lino, 774 | L27: Vila Rosa | M27: 14.450-000 | N27: Jeriquara | O27: SP | P27: desempregada | Q27: Solteiro(a) | R27: Indicação | T27: 44454 | U27: =DAY(G27)&"/"&MONTH(G27) -> 7/2
A28: =B28&"--"&COUNTIF($B$5:B28,B28) -> 9--3 | B28: =IF(G28<>"",MONTH(G28),"") -> 9 | C28: 24 | D28: Paulo Artur da Silva | E28: 096.398.056-45 | F28: M | G28: 32405 | H28: =IF(G28,DATEDIF(G28,TODAY(),"Y"),"") -> 37 | J28: contato@lourencoenajm.adv.br | K28: Rua Padre Jose Maria Escriva de Balaguer, 325 | L28: Jardim Sonia Regina | M28: 04.935-110 | N28: São Paulo | O28: SP | P28: Desempregado | Q28: Casado(a) | R28: Outros | T28: 44503 | U28: =DAY(G28)&"/"&MONTH(G28) -> 19/9
A29: =B29&"--"&COUNTIF($B$5:B29,B29) -> 5--3 | B29: =IF(G29<>"",MONTH(G29),"") -> 5 | C29: 25 | D29: Ricardo Henrique Queiroz de Souza | E29: 192.026.548-16 | F29: M | G29: 28635 | H29: =IF(G29,DATEDIF(G29,TODAY(),"Y"),"") -> 47 | J29: ricardohqueiroz@hotmail.com | K29: Av. Prof. Edul Rangel Rabello, 405 - BL 28 - Apart. 101 | L29: Jardim Manoel Pena | M29: 14.088-331 | N29: Ribeirão Preto | O29: SP | P29: Gerente de Aeroporto | Q29: Casado(a) | R29: Outros | T29: 44326 | U29: =DAY(G29)&"/"&MONTH(G29) -> 25/5
A30: =B30&"--"&COUNTIF($B$5:B30,B30) -> 3--4 | B30: =IF(G30<>"",MONTH(G30),"") -> 3 | C30: 26 | D30: Aline Cristina da Silva | E30: 069.993.774-48 | F30: F | G30: 32232 | H30: =IF(G30,DATEDIF(G30,TODAY(),"Y"),"") -> 37 | I30: (19) 98866-0127 | J30: contato@lourencoenajm.adv.br | K30: Rua Emílio Agostini, 235 | L30: Jardim Morada do Sol | M30: 13.348-091 | N30: Indaiatuba | O30: SP | P30: Autônomo | Q30: Solteiro(a) | R30: Parceria | T30: 44909 | U30: =DAY(G30)&"/"&MONTH(G30) -> 30/3
A31: =B31&"--"&COUNTIF($B$5:B31,B31) -> 8--4 | B31: =IF(G31<>"",MONTH(G31),"") -> 8 | C31: 27 | D31: Álvaro de Souza Rodriguês Pinheiro | E31: 712.600.891-00 | F31: M | G31: 45165 | H31: M | J31: contato@lourencoenajm.adv.br | K31: Avenida do Café, 1.243, apartamento 13 | L31: Vila Amélia | M31: 14.050-230 | N31: Ribeirão Preto | O31: SP | P31: Estudante | Q31: Solteiro(a) | R31: Indicação | T31: 45117 | U31: =DAY(G31)&"/"&MONTH(G31) -> 27/8
A32: =B32&"--"&COUNTIF($B$5:B32,B32) -> 10--4 | B32: =IF(G32<>"",MONTH(G32),"") -> 10 | C32: 28 | D32: Tomas Yung Joon Kim | E32: 042.563.298-97 | F32: M | G32: 21466 | H32: =IF(G32,DATEDIF(G32,TODAY(),"Y"),"") -> 67 | J32: contato@lourencoenajm.adv.br | K32: Rua São José, n.º 2.765, | L32: Alto da Boa Vista | M32: 14025186 | N32: Ribeirão Preto | O32: SP | P32: Médico | Q32: Divorciado(a) | R32: É Família/Amigo | T32: 45124 | U32: =DAY(G32)&"/"&MONTH(G32) -> 8/10
A33: =B33&"--"&COUNTIF($B$5:B33,B33) -> 6--2 | B33: =IF(G33<>"",MONTH(G33),"") -> 6 | C33: 29 | D33: Adalgisa Pereira Silveira | E33: 116.383.728-88 | F33: F | G33: 24643 | H33: =IF(G33,DATEDIF(G33,TODAY(),"Y"),"") -> 58 | J33: contato@lourencoenajm.adv.br | K33: Rua Tabatinga, n.º 2005, | L33: Jardim Jandaia | M33: 14.060-580 | N33: Ribeirão Preto | O33: SP | P33: Autonoma | Q33: União Estável | R33: Indicação | T33: 45071 | U33: =DAY(G33)&"/"&MONTH(G33) -> 20/6
A34: =B34&"--"&COUNTIF($B$5:B34,B34) -> 9--4 | B34: =IF(G34<>"",MONTH(G34),"") -> 9 | C34: 30 | D34: Cleide Patrícia Dias Cardoso | E34: 186.528.148-48 | F34: F | G34: 28013 | H34: =IF(G34,DATEDIF(G34,TODAY(),"Y"),"") -> 49 | J34: cleidepaty233@outlook.com | K34: Rua Altino Arantes, n.º 1.020 | L34: Jardim Sumarê | M34: 14.025-030 | N34: Ribeirão Preto | O34: SP | P34: Cuidadora | Q34: Casado(a) | R34: Parceria | S34: Parceria com o Dr. Daniel Itokazu | U34: =DAY(G34)&"/"&MONTH(G34) -> 10/9
A35: =B35&"--"&COUNTIF($B$5:B35,B35) -> 4--2 | B35: =IF(G35<>"",MONTH(G35),"") -> 4 | C35: 31 | D35: Gabriel Szurkalo Pantoni | E35: 449.180.178-94 | F35: M | G35: 35898 | H35: =IF(G35,DATEDIF(G35,TODAY(),"Y"),"") -> 27 | J35: contato@lourencoenajm.adv.br | K35: Thereza Carmusciano Paulini, n.º 207 | L35: Jardim Orestes Lopes de Camargo | M35: 14.066-400 | N35: Ribeirão Preto | O35: SP | P35: Frentista | Q35: União Estável | R35: Indicação | S35: Indicação do Rodrigo | T35: 45251 | U35: =DAY(G35)&"/"&MONTH(G35) -> 13/4
A36: =B36&"--"&COUNTIF($B$5:B36,B36) -> 10--5 | B36: =IF(G36<>"",MONTH(G36),"") -> 10 | C36: 32 | D36: Jonathan Feliciano Lima | E36: 388.538.268-78 | F36: M | G36: 33157 | H36: =IF(G36,DATEDIF(G36,TODAY(),"Y"),"") -> 35 | J36: contato@lourencoenajm.adv.br | K36: Francisco Braz Prado, n.º 1.040 | L36: Bom Retiro | M36: 13.142-126 | N36: Ribeirão Preto | O36: SP | P36: Desempregado | Q36: Casado(a) | R36: Parceria | T36: 45210 | U36: =DAY(G36)&"/"&MONTH(G36) -> 11/10
A37: =B37&"--"&COUNTIF($B$5:B37,B37) -> 3--5 | B37: =IF(G37<>"",MONTH(G37),"") -> 3 | C37: 33 | D37: César Augusto de Oliveira | E37: 150.680.848-40 | F37: M | G37: 26728 | H37: =IF(G37,DATEDIF(G37,TODAY(),"Y"),"") -> 52 | I37: (16) 99119-0103 | J37: pere.oliveira@hotmail.com | K37: Rua Niterói, 750 - Casa 7 | L37: Parque Ind. Lagoinha | M37: 14.095-020 | N37: Ribeirão Preto | O37: SP | P37: Vendedor | Q37: Casado(a) | R37: É Família/Amigo | T37: 45332 | U37: =DAY(G37)&"/"&MONTH(G37) -> 5/3
A38: =B38&"--"&COUNTIF($B$5:B38,B38) -> --1 | B38: =IF(G38<>"",MONTH(G38),"") | C38: 34 | H38: =IF(G38,DATEDIF(G38,TODAY(),"Y"),"") | U38: =DAY(G38)&"/"&MONTH(G38) -> 0/1
A39: =B39&"--"&COUNTIF($B$5:B39,B39) -> --2 | B39: =IF(G39<>"",MONTH(G39),"") | C39: 35 | H39: =IF(G39,DATEDIF(G39,TODAY(),"Y"),"") | U39: =DAY(G39)&"/"&MONTH(G39) -> 0/1
A40: =B40&"--"&COUNTIF($B$5:B40,B40) -> --3 | B40: =IF(G40<>"",MONTH(G40),"") | C40: 36 | H40: =IF(G40,DATEDIF(G40,TODAY(),"Y"),"") | U40: =DAY(G40)&"/"&MONTH(G40) -> 0/1
A41: =B41&"--"&COUNTIF($B$5:B41,B41) -> --4 | B41: =IF(G41<>"",MONTH(G41),"") | C41: 37 | H41: =IF(G41,DATEDIF(G41,TODAY(),"Y"),"") | U41: =DAY(G41)&"/"&MONTH(G41) -> 0/1
A42: =B42&"--"&COUNTIF($B$5:B42,B42) -> --5 | B42: =IF(G42<>"",MONTH(G42),"") | C42: 38 | H42: =IF(G42,DATEDIF(G42,TODAY(),"Y"),"") | U42: =DAY(G42)&"/"&MONTH(G42) -> 0/1
A43: =B43&"--"&COUNTIF($B$5:B43,B43) -> --6 | B43: =IF(G43<>"",MONTH(G43),"") | C43: 39 | H43: =IF(G43,DATEDIF(G43,TODAY(),"Y"),"") | U43: =DAY(G43)&"/"&MONTH(G43) -> 0/1
A44: =B44&"--"&COUNTIF($B$5:B44,B44) -> --7 | B44: =IF(G44<>"",MONTH(G44),"") | C44: 40 | H44: =IF(G44,DATEDIF(G44,TODAY(),"Y"),"") | U44: =DAY(G44)&"/"&MONTH(G44) -> 0/1
A45: =B45&"--"&COUNTIF($B$5:B45,B45) -> --8 | B45: =IF(G45<>"",MONTH(G45),"") | C45: 41 | H45: =IF(G45,DATEDIF(G45,TODAY(),"Y"),"") | U45: =DAY(G45)&"/"&MONTH(G45) -> 0/1
A46: =B46&"--"&COUNTIF($B$5:B46,B46) -> --9 | B46: =IF(G46<>"",MONTH(G46),"") | C46: 42 | H46: =IF(G46,DATEDIF(G46,TODAY(),"Y"),"") | U46: =DAY(G46)&"/"&MONTH(G46) -> 0/1
A47: =B47&"--"&COUNTIF($B$5:B47,B47) -> --10 | B47: =IF(G47<>"",MONTH(G47),"") | C47: 43 | H47: =IF(G47,DATEDIF(G47,TODAY(),"Y"),"") | U47: =DAY(G47)&"/"&MONTH(G47) -> 0/1
A48: =B48&"--"&COUNTIF($B$5:B48,B48) -> --11 | B48: =IF(G48<>"",MONTH(G48),"") | C48: 44 | H48: =IF(G48,DATEDIF(G48,TODAY(),"Y"),"") | U48: =DAY(G48)&"/"&MONTH(G48) -> 0/1
A49: =B49&"--"&COUNTIF($B$5:B49,B49) -> --12 | B49: =IF(G49<>"",MONTH(G49),"") | C49: 45 | H49: =IF(G49,DATEDIF(G49,TODAY(),"Y"),"") | U49: =DAY(G49)&"/"&MONTH(G49) -> 0/1
... A6005: =B6005&"--"&COUNTIF($B$5:B6005,B6005) -> --5968 | B6005: =IF(G6005<>"",MONTH(G6005),"") | C6005: 6001 | H6005: =IF(G6005,DATEDIF(G6005,TODAY(),"Y"),"") | U6005: =DAY(G6005)&"/"&MONTH(G6005) -> 0/1

Sheet Clie-A
B4: ESCOLHA UM MÊS → | D4: Maio | I4: =MONTH(1&D4) -> 5
B6: # | C6: Nome | D6: Data de Nascimento | E6: Idade | F6: Telefone | G6: E-mail
B7: 1 | C7: =IFERROR(VLOOKUP($I$4&"--"&ROW(A1),'Clie-F'!$A$5:$H$7000,4,0),"") -> Danielle Contin Nader | D7: =IFERROR(VLOOKUP($I$4&"--"&ROW(A1),'Clie-F'!$A$5:$H$7000,7,0),"") -> 34848 | E7: =IFERROR(IF(D7,DATEDIF(D7,TODAY(),"Y"),""),"") -> 30 | F7: =IFERROR(VLOOKUP($I$4&"--"&ROW(A1),'Clie-F'!$A$5:$J$7000,9,0),"") -> 0 | G7: =IFERROR(VLOOKUP($I$4&"--"&ROW(A1),'Clie-F'!$A$5:$J$7000,10,0),"") -> daniellenader@hotmail.com
B8: 2 | C8: =IFERROR(VLOOKUP($I$4&"--"&ROW(A2),'Clie-F'!$A$5:$H$7000,4,0),"") -> Maria Regina Dos Santos Geraldo | D8: =IFERROR(VLOOKUP($I$4&"--"&ROW(A2),'Clie-F'!$A$5:$H$7000,7,0),"") -> 18401 | E8: =IFERROR(IF(D8,DATEDIF(D8,TODAY(),"Y"),""),"") -> 75 | F8: =IFERROR(VLOOKUP($I$4&"--"&ROW(A2),'Clie-F'!$A$5:$J$7000,9,0),"") -> 0 | G8: =IFERROR(VLOOKUP($I$4&"--"&ROW(A2),'Clie-F'!$A$5:$J$7000,10,0),"") -> contato@lourencoenajm.adv.br
B9: 3 | C9: =IFERROR(VLOOKUP($I$4&"--"&ROW(A3),'Clie-F'!$A$5:$H$7000,4,0),"") -> Ricardo Henrique Queiroz de Souza | D9: =IFERROR(VLOOKUP($I$4&"--"&ROW(A3),'Clie-F'!$A$5:$H$7000,7,0),"") -> 28635 | E9: =IFERROR(IF(D9,DATEDIF(D9,TODAY(),"Y"),""),"") -> 47 | F9: =IFERROR(VLOOKUP($I$4&"--"&ROW(A3),'Clie-F'!$A$5:$J$7000,9,0),"") -> 0 | G9: =IFERROR(VLOOKUP($I$4&"--"&ROW(A3),'Clie-F'!$A$5:$J$7000,10,0),"") -> ricardohqueiroz@hotmail.com
B10: 4 | C10: =IFERROR(VLOOKUP($I$4&"--"&ROW(A4),'Clie-F'!$A$5:$H$7000,4,0),"") | D10: =IFERROR(VLOOKUP($I$4&"--"&ROW(A4),'Clie-F'!$A$5:$H$7000,7,0),"") | E10: =IFERROR(IF(D10,DATEDIF(D10,TODAY(),"Y"),""),"") | F10: =IFERROR(VLOOKUP($I$4&"--"&ROW(A4),'Clie-F'!$A$5:$J$7000,9,0),"") | G10: =IFERROR(VLOOKUP($I$4&"--"&ROW(A4),'Clie-F'!$A$5:$J$7000,10,0),"")
B11: 5 | C11: =IFERROR(VLOOKUP($I$4&"--"&ROW(A5),'Clie-F'!$A$5:$H$7000,4,0),"") | D11: =IFERROR(VLOOKUP($I$4&"--"&ROW(A5),'Clie-F'!$A$5:$H$7000,7,0),"") | E11: =IFERROR(IF(D11,DATEDIF(D11,TODAY(),"Y"),""),"") | F11: =IFERROR(VLOOKUP($I$4&"--"&ROW(A5),'Clie-F'!$A$5:$J$7000,9,0),"") | G11: =IFERROR(VLOOKUP($I$4&"--"&ROW(A5),'Clie-F'!$A$5:$J$7000,10,0),"")
B12: 6 | C12: =IFERROR(VLOOKUP($I$4&"--"&ROW(A6),'Clie-F'!$A$5:$H$7000,4,0),"") | D12: =IFERROR(VLOOKUP($I$4&"--"&ROW(A6),'Clie-F'!$A$5:$H$7000,7,0),"") | E12: =IFERROR(IF(D12,DATEDIF(D12,TODAY(),"Y"),""),"") | F12: =IFERROR(VLOOKUP($I$4&"--"&ROW(A6),'Clie-F'!$A$5:$J$7000,9,0),"") | G12: =IFERROR(VLOOKUP($I$4&"--"&ROW(A6),'Clie-F'!$A$5:$J$7000,10,0),"")
B13: 7 | C13: =IFERROR(VLOOKUP($I$4&"--"&ROW(A7),'Clie-F'!$A$5:$H$7000,4,0),"") | D13: =IFERROR(VLOOKUP($I$4&"--"&ROW(A7),'Clie-F'!$A$5:$H$7000,7,0),"") | E13: =IFERROR(IF(D13,DATEDIF(D13,TODAY(),"Y"),""),"") | F13: =IFERROR(VLOOKUP($I$4&"--"&ROW(A7),'Clie-F'!$A$5:$J$7000,9,0),"") | G13: =IFERROR(VLOOKUP($I$4&"--"&ROW(A7),'Clie-F'!$A$5:$J$7000,10,0),"")
B14: 8 | C14: =IFERROR(VLOOKUP($I$4&"--"&ROW(A8),'Clie-F'!$A$5:$H$7000,4,0),"") | D14: =IFERROR(VLOOKUP($I$4&"--"&ROW(A8),'Clie-F'!$A$5:$H$7000,7,0),"") | E14: =IFERROR(IF(D14,DATEDIF(D14,TODAY(),"Y"),""),"") | F14: =IFERROR(VLOOKUP($I$4&"--"&ROW(A8),'Clie-F'!$A$5:$J$7000,9,0),"") | G14: =IFERROR(VLOOKUP($I$4&"--"&ROW(A8),'Clie-F'!$A$5:$J$7000,10,0),"")
B15: 9 | C15: =IFERROR(VLOOKUP($I$4&"--"&ROW(A9),'Clie-F'!$A$5:$H$7000,4,0),"") | D15: =IFERROR(VLOOKUP($I$4&"--"&ROW(A9),'Clie-F'!$A$5:$H$7000,7,0),"") | E15: =IFERROR(IF(D15,DATEDIF(D15,TODAY(),"Y"),""),"") | F15: =IFERROR(VLOOKUP($I$4&"--"&ROW(A9),'Clie-F'!$A$5:$J$7000,9,0),"") | G15: =IFERROR(VLOOKUP($I$4&"--"&ROW(A9),'Clie-F'!$A$5:$J$7000,10,0),"")
B16: 10 | C16: =IFERROR(VLOOKUP($I$4&"--"&ROW(A10),'Clie-F'!$A$5:$H$7000,4,0),"") | D16: =IFERROR(VLOOKUP($I$4&"--"&ROW(A10),'Clie-F'!$A$5:$H$7000,7,0),"") | E16: =IFERROR(IF(D16,DATEDIF(D16,TODAY(),"Y"),""),"") | F16: =IFERROR(VLOOKUP($I$4&"--"&ROW(A10),'Clie-F'!$A$5:$J$7000,9,0),"") | G16: =IFERROR(VLOOKUP($I$4&"--"&ROW(A10),'Clie-F'!$A$5:$J$7000,10,0),"")
B17: 11 | C17: =IFERROR(VLOOKUP($I$4&"--"&ROW(A11),'Clie-F'!$A$5:$H$7000,4,0),"") | D17: =IFERROR(VLOOKUP($I$4&"--"&ROW(A11),'Clie-F'!$A$5:$H$7000,7,0),"") | E17: =IFERROR(IF(D17,DATEDIF(D17,TODAY(),"Y"),""),"") | F17: =IFERROR(VLOOKUP($I$4&"--"&ROW(A11),'Clie-F'!$A$5:$J$7000,9,0),"") | G17: =IFERROR(VLOOKUP($I$4&"--"&ROW(A11),'Clie-F'!$A$5:$J$7000,10,0),"")
B18: 12 | C18: =IFERROR(VLOOKUP($I$4&"--"&ROW(A12),'Clie-F'!$A$5:$H$7000,4,0),"") | D18: =IFERROR(VLOOKUP($I$4&"--"&ROW(A12),'Clie-F'!$A$5:$H$7000,7,0),"") | E18: =IFERROR(IF(D18,DATEDIF(D18,TODAY(),"Y"),""),"") | F18: =IFERROR(VLOOKUP($I$4&"--"&ROW(A12),'Clie-F'!$A$5:$J$7000,9,0),"") | G18: =IFERROR(VLOOKUP($I$4&"--"&ROW(A12),'Clie-F'!$A$5:$J$7000,10,0),"")
... B3966: 3960 | C3966: =IFERROR(VLOOKUP($I$4&"--"&ROW(A3960),'Clie-F'!$A$5:$H$7000,4,0),"") | D3966: =IFERROR(VLOOKUP($I$4&"--"&ROW(A3960),'Clie-F'!$A$5:$H$7000,7,0),"") | E3966: =IFERROR(IF(D3966,DATEDIF(D3966,TODAY(),"Y"),""),"") | F3966: =IFERROR(VLOOKUP($I$4&"--"&ROW(A3960),'Clie-F'!$A$5:$J$7000,9,0),"") | G3966: =IFERROR(VLOOKUP($I$4&"--"&ROW(A3960),'Clie-F'!$A$5:$J$7000,10,0),"")
B3967: 3961 | E3967: =IF(D3967,DATEDIF(D3967,TODAY(),"Y"),"") | F3967: =IFERROR(VLOOKUP($I$4&"--"&ROW(A3961),'Clie-F'!$B$5:$Z$7000,15,0),"") | G3967: =IFERROR(VLOOKUP($I$4&"--"&ROW(A3961),'Clie-F'!$B$5:$Z$7000,13,0),"")
B3968: 3962 | E3968: =IF(D3968,DATEDIF(D3968,TODAY(),"Y"),"") | F3968: =IFERROR(VLOOKUP($I$4&"--"&ROW(A3962),'Clie-F'!$B$5:$Z$7000,15,0),"") | G3968: =IFERROR(VLOOKUP($I$4&"--"&ROW(A3962),'Clie-F'!$B$5:$Z$7000,13,0),"")
B3969: 3963 | E3969: =IF(D3969,DATEDIF(D3969,TODAY(),"Y"),"") | F3969: =IFERROR(VLOOKUP($I$4&"--"&ROW(A3963),'Clie-F'!$B$5:$Z$7000,15,0),"") | G3969: =IFERROR(VLOOKUP($I$4&"--"&ROW(A3963),'Clie-F'!$B$5:$Z$7000,13,0),"")
B3970: 3964 | E3970: =IF(D3970,DATEDIF(D3970,TODAY(),"Y"),"") | F3970: =IFERROR(VLOOKUP($I$4&"--"&ROW(A3964),'Clie-F'!$B$5:$Z$7000,15,0),"") | G3970: =IFERROR(VLOOKUP($I$4&"--"&ROW(A3964),'Clie-F'!$B$5:$Z$7000,13,0),"")
B3971: 3965 | E3971: =IF(D3971,DATEDIF(D3971,TODAY(),"Y"),"") | F3971: =IFERROR(VLOOKUP($I$4&"--"&ROW(A3965),'Clie-F'!$B$5:$Z$7000,15,0),"") | G3971: =IFERROR(VLOOKUP($I$4&"--"&ROW(A3965),'Clie-F'!$B$5:$Z$7000,13,0),"")
B3972: 3966 | E3972: =IF(D3972,DATEDIF(D3972,TODAY(),"Y"),"") | F3972: =IFERROR(VLOOKUP($I$4&"--"&ROW(A3966),'Clie-F'!$B$5:$Z$7000,15,0),"") | G3972: =IFERROR(VLOOKUP($I$4&"--"&ROW(A3966),'Clie-F'!$B$5:$Z$7000,13,0),"")
B3973: 3967 | E3973: =IF(D3973,DATEDIF(D3973,TODAY(),"Y"),"") | F3973: =IFERROR(VLOOKUP($I$4&"--"&ROW(A3967),'Clie-F'!$B$5:$Z$7000,15,0),"") | G3973: =IFERROR(VLOOKUP($I$4&"--"&ROW(A3967),'Clie-F'!$B$5:$Z$7000,13,0),"")
B3974: 3968 | E3974: =IF(D3974,DATEDIF(D3974,TODAY(),"Y"),"") | F3974: =IFERROR(VLOOKUP($I$4&"--"&ROW(A3968),'Clie-F'!$B$5:$Z$7000,15,0),"") | G3974: =IFERROR(VLOOKUP($I$4&"--"&ROW(A3968),'Clie-F'!$B$5:$Z$7000,13,0),"")
B3975: 3969 | E3975: =IF(D3975,DATEDIF(D3975,TODAY(),"Y"),"") | F3975: =IFERROR(VLOOKUP($I$4&"--"&ROW(A3969),'Clie-F'!$B$5:$Z$7000,15,0),"") | G3975: =IFERROR(VLOOKUP($I$4&"--"&ROW(A3969),'Clie-F'!$B$5:$Z$7000,13,0),"")
B3976: 3970 | E3976: =IF(D3976,DATEDIF(D3976,TODAY(),"Y"),"") | F3976: =IFERROR(VLOOKUP($I$4&"--"&ROW(A3970),'Clie-F'!$B$5:$Z$7000,15,0),"") | G3976: =IFERROR(VLOOKUP($I$4&"--"&ROW(A3970),'Clie-F'!$B$5:$Z$7000,13,0),"")
B3977: 3971 | E3977: =IF(D3977,DATEDIF(D3977,TODAY(),"Y"),"") | F3977: =IFERROR(VLOOKUP($I$4&"--"&ROW(A3971),'Clie-F'!$B$5:$Z$7000,15,0),"") | G3977: =IFERROR(VLOOKUP($I$4&"--"&ROW(A3971),'Clie-F'!$B$5:$Z$7000,13,0),"")
B3978: 3972 | E3978: =IF(D3978,DATEDIF(D3978,TODAY(),"Y"),"") | F3978: =IFERROR(VLOOKUP($I$4&"--"&ROW(A3972),'Clie-F'!$B$5:$Z$7000,15,0),"") | G3978: =IFERROR(VLOOKUP($I$4&"--"&ROW(A3972),'Clie-F'!$B$5:$Z$7000,13,0),"")
... B6007: 6001 | E6007: =IF(D6007,DATEDIF(D6007,TODAY(),"Y"),"") | F6007: =IFERROR(VLOOKUP($I$4&"--"&ROW(A6001),'Clie-F'!$B$5:$Z$7000,15,0),"") | G6007: =IFERROR(VLOOKUP($I$4&"--"&ROW(A6001),'Clie-F'!$B$5:$Z$7000,13,0),"")

Sheet Clie-J
B4: # | C4: Nome Fantasia | D4: Razão Social | E4: CNPJ | F4: Telefone | G4: E-mail | H4: Endereço | I4: Bairro | J4: CEP | K4: Cidade | L4: Estado | M4: Segmento de Atuação | N4: Responsável Legal | O4: Como nos Conheceu | P4: Observações | Q4: Data de Cadastro
B5: 1 | C5: Groppa Tech | D5: Groppa Technology Comércio e Serviços Ltda. | E5: 10.688.124/0001-65 | F5: 16-3963-1089 | G5: financeiro@groppatech.com.br | H5: Rua Vírgilio de Carvalho Neves Neto, 866 | I5: Res. E Comercial Palmares | J5: 14.092-440 | K5: Ribeirão Preto | L5: SP | M5: Manutenção em Equipamentos Hospitalares | N5: Daniel e Simone | O5: É Família/Amigo | P5: Indicação Feres | Q5: 42205
B6: 2 | C6: Pepe Oficina | D6: Pepe Serviços Especializados em Automóveis Ltda. | E6: 58.603.341/0001-31 | F6: 16-3289-1120 | G6: pepe@pepeoficina.com.br | H6: Rua São Paulo, 1721 | I6: Campos Elíseos | J6: 14.085-010 | K6: Ribeirão Preto | L6: SP | M6: Reparadora Automotiva | N6: Marcelo e Lucas | O6: Outros | P6: Indicação Feres | Q6: 43441
B7: 3 | C7: Renove Casa & Design | D7: Renove Casa Design de Interiores Ltda. | E7: 18.165.801/0001-72 | F7: 16-3877-5797 | G7: financeiro@renovecasaedesign.com.br | H7: Av. Anhanguera, 365 | I7: Alto da Boa Vista | J7: 14.025-480 | K7: Ribeirão Preto | L7: SP | M7: Decoração | N7: Ariadne e Gustavo | O7: É Família/Amigo | P7: Indicação Feres | Q7: 44260
B8: 4 | C8: Retire Agora | D8: Retire Agora Comércio de Produtos em Geral e Eletrodomésticos Ltda. | E8: 34.433.675/0001-46 | F8: 16-98256-2193 | G8: contasapagar@retireagora.com.br | H8: Rua Rosa Vermelha, 733 - Galpão 01 - Sala Y | I8: Polo Empresarial Novo México | J8: 29.104-372 | K8: Vila Velha | L8: ES | M8: Comércio em Geral | N8: Murilo e Kríssia | O8: É Família/Amigo | P8: Indicação Feres | Q8: 44309
B9: 5 | C9: Brilho Auto Center | D9: Waldiva Comércio de Peças e Funilaria Ltda. | E9: 67.523.159/0001-61 | F9: 16-3826-1819 | G9: atendimento@brilhoautocenter.com.br | H9: Rua Bolívia, 660 | I9: Vila Mariana | J9: 14.075-250 | K9: Ribeirão Preto | L9: SP | M9: Reparadora Automotiva | N9: Michelle e William | O9: Outros | P9: Indicação Feres | Q9: 44242
B10: 6 | C10: Brilho Auto Center | D10: Brilho Auto Center Funilaria Ltda | E10: 04.950.138/0001-02 | F10: 16-3826-1819 | G10: atendimento@brilhoautocenter.com.br | H10: Rua Bolívia, 660 | I10: Vila Mariana | J10: 14.075-250 | K10: Ribeirão Preto | L10: SP | M10: Reparadora Automotiva | N10: Michelle e William | O10: Outros | P10: Indicação Feres | Q10: 44242
B11: 7 | C11: Ideal Clínicas | D11: F.T.T. Serviços Médicos e Odontológicos Ltda | E11: 32.181.293/0001-47 | F11: 16-3515-1090 | G11: idealclinina@redeidealclinica.com.br | H11: Rua Florêncio de Abreu, 613 | I11: Centro | J11: 14.015-060 | K11: Ribeirão Preto | L11: SP | M11: Medicina e Saúde | N11: Juliana e Fernando | O11: Outros | P11: Indicação Feres | Q11: 44662
B12: 8 | C12: Mister Ottani | D12: Indústria de Massas Alimentícias Ottani Ltda. | E12: 05.619.991/0001-09 | F12: 16-3625-6139 | G12: roberto@misterottani.com.br | H12: Rua Maracaju, 1511 | I12: Monte Alegre | J12: 14.051-120 | K12: Ribeirão Preto | L12: SP | M12: Indústria | N12: Roberto | O12: Outros | P12: indicação Big Compra | Q12: 44490
B13: 9 | C13: Mogiana Auto Peças | D13: Mogiana Auto Peças Ltda. | E13: 33.750.207/0001-32 | F13: 16-3515-7276 | G13: mogianaautopecasrp@gmail.com | H13: Rua Bolívia, 558 | I13: Vila Mariana | J13: 14.075-250 | K13: Ribeirão Preto | L13: SP | M13: Veículos e Peças | N13: Rogério e Fernanda | O13: Outros | P13: Indicação Feres | Q13: 44392
B14: 10 | C14: Supermercados Big Compra Ltda. | D14: Supermercados Big Compra Ltda. | E14: 09.418.668/0001-28 | F14: 16-3975-8045 | G14: william.esteves@smbigcompra.com.br | H14: Rua Heron Domingues, 812 | I14: Parque São Sebastião | J14: 14.093-400 | K14: Ribeirão Preto | L14: SP | M14: Supermercados | N14: Claudinei | O14: Outros | P14: Indicação Feres | Q14: 44343
B15: 11 | C15: Hit Car Centro Automotivo LITDA. | D15: Hit Car Centro Automotivo Ltda. | E15: 03.316.392/0001-90 | F15: 16-3630-1866 | G15: financeiro@hitcar.com.br | H15: Rua Bolívia, 911 | I15: Vila Mariana | J15: 14.075-250 | K15: Ribeirão Preto | L15: SP | M15: Reparadora Automotiva | N15: Nayara Rodrigues | O15: Indicação | P15: Indicação | Q15: 44651
B16: 12 | C16: Marmoraria M & C Ltda | D16: Marmoraria Mundial | E16: 00.903.381/0001-19 | F16: 16-99223-2937 | G16: marmorariaundial01@gmail.com | H16: Av. Dr. Milton Rezende de Junqueira, 569 | I16: Jardim América | J16: 14.600-000 | K16: São Joaquim da Barra | L16: SP | M16: Material de Construção | N16: André Reis Oliveira | O16: É Família/Amigo | P16: Indicação Feres | Q16: 44691
... B18: 14 | C18: Renew - Sistemas de Recuperação e Polimento Automotivo Ltda. | D18: Renew Centro Estético Automotivo | E18: 00.952.716/0001-99 | F18: 16-3713-0600 | G18: renato@renew.com.br | H18: Av. Dom Pedri I, 1255 | I18: Jardim Dr. Antônio Petralia | J18: 14.409-170 | K18: Franca | L18: SP | M18: Reparadora Automotiva | N18: Renato Coelho Nascimento | O18: Indicação | P18: Indicação | Q18: 44837
B19: 15 | C19: Leco Car | D19: Leco Car Comércio e Pintura | E19: 39.014.923/0001-38 | G19: lecocar@lecocar.com.br | H19: Rua Washington Luiz, 244 | I19: Vila Tamandaré | J19: 14.085-190 | K19: Ribeirão Preto | L19: SP | M19: Reparadora Automotiva | N19: Pedro Henrique Giuntini Romeiro | O19: Outros | Q19: 44701
B20: 16 | C20: André Luís Massaro | D20: Massaro Auto Center | E20: 61.895.850/0001-90 | G20: andremassaro@massaroauto.com.br | H20: Av. Caramuru, 1454 | I20: Jardim Sumaré | J20: 14.040-000 | K20: Ribeirão Preto | L20: SP | M20: Reparadora Automotiva | N20: André Luís Massaro | O20: Indicação | Q20: 44721
B21: 17 | C21: Regina Célia Guarita Crochiquia e Outros | D21: Regina Célia Guarita Crochiquia | E21: 24.007.214/0001-58 | G21: admguaritacrochiquia@gmail.com | H21: Estrada Municipal Agudos a Domélia, Fzd Sta. Isabel | I21: Zona Rural de Agudos | J21: 17.120-001 | K21: Agudos | L21: SP | M21: Agronegócio | N21: Regina Célia Guarita Crochiquia | O21: Outros | Q21: 44942
B22: 18 | C22: Sofiati e Salgado Hotel Ltda-ME | D22: Sofiati e Salgado Hotel | E22: 05.586.662/0001-09 | F22: (16) 99197-2267 | G22: rodolfo_salgado@hotmail.com | H22: Estrada Municipal Ayrton Senna, n.º 16 | I22: Jardim Goinânia | J22: 14.302-192 | K22: Batatais | L22: SP | M22: Outros | N22: Rodolfo Sofiati Salgado | O22: É Família/Amigo | Q22: 45059
B23: 19 | C23: R. C. Nascimento | D23: R. C. Nascimento | E23: 17.836.163/0001-01 | G23: renato@renew.com.br | H23: Rua Romildo Morelli, n.º 2.270 - Jardim Dr. Antônio Petráglia | I23: Jardim Antônio Petraglia | J23: 14.409-190 | K23: Franca | L23: SP | M23: Outros | N23: Renato Coelho Nascimento | O23: Outros | Q23: 45191
B24: 20 | C24: Auto Posto Zerrenner | D24: Auto Posto Zerrenner Eireli | E24: 09.105.668/0001-78 | G24: wellignton.moraes@postozerrenner.com.br | H24: Avenida Antônio e Helena Zerrenner, n.º 1.649 | I24: Vila Tibério | J24: 14.050-010 | K24: Ribeirão Preto | L24: SP | M24: Outros | N24: Wellington Morães | O24: Outros | Q24: 45201
B25: 21 | C25: Oficina Classe A | D25: João Vitor de Freitas | E25: 46.087.984/0001-90 | G25: martelinhoclassea@gmail.com | H25: Rua do Comércio, n.º 2.244 | I25: Centro | J25: 14.400-660 | K25: Franca | L25: SP | M25: Veículos e Peças | N25: João Vitor de Freitas | O25: Indicação | Q25: 45261
B26: 22 | C26: Associação dos Empregados no Comércio de Franca | D26: Associação de Empregados no Comércio de Franca | E26: 47.973.425/0001-40 | F26: 16) 3707-4821/ (16) 3707-4823 | G26: secretaria@aeccastelinho.com.br | H26: Avenida Miguel Sábio de Mello, n.º 351 | I26: Jardim Santana | J26: 14.403-068 | K26: Franca | L26: SP | M26: Outros | N26: Gustavo Simei Garcia | O26: Indicação | Q26: 45366
B27: 23 | C27: Posto Everest | D27: Posto Everest de Ribeirão Preto Ltda. | E27: 09.420.400/0001-20 | F27: 16-3236-2705 | G27: fernando@postoeverest.com.br | H27: Avenida da Saudade, 668 | I27: Campos Elíseos | J27: 14.085-000 | K27: Ribeirão Preto | L27: SP | N27: Fernando Roca | O27: Outros | Q27: 45700
B28: 24 | C28: Leão Tintas | D28: Guaíra Comércio de Tintas Ltda. | E28: 72.697.501/0001-80 | F28: 17-3331-2021 | G28: feris68@leaotintas.com.br | H28: Avenida 15, 411 | I28: Centro | J28: 14.790-000 | K28: Guaíra | L28: SP | M28: Comércio em Geral | N28: Feris Jomãa | O28: Outros
B29: 25
B30: 26
B31: 27
B32: 28
B33: 29
B34: 30
B35: 31
B36: 32
B37: 33
B38: 34
B39: 35
B40: 36
... B304: 300

Sheet C-Das1
V5: =COUNTA('Clie-F'!D5:D9999) -> 33
B6: CLIENTES TOTAIS POR ESTADO CIVIL | V6: =COUNTA('Clie-J'!C5:C9999) -> 24 | W6: AC | X6: =COUNTIF('Clie-F'!$O$5:$O$6400,'C-Das1'!W6) -> 0 | Y6: =IF('Conf-C'!B5<>"",'Conf-C'!B5,"") -> Anúncio | Z6: =IF(Y6<>"",COUNTIF('Clie-F'!$R$5:$R$6400,Y6),"") -> 0
B7: Solteiro(a) | C7: =COUNTIF('Clie-F'!$Q$5:$Q$9999,'C-Das1'!B7) -> 7 | D7: =C7/SUM($C$7:$C$11) -> 0.23333333 | P7: CLIENTES TOTAIS POR SEXO | V7: =SUM(V5:V6) -> 57 | W7: AL | X7: =COUNTIF('Clie-F'!$O$5:$O$6400,'C-Das1'!W7) -> 0 | Y7: =IF('Conf-C'!B6<>"",'Conf-C'!B6,"") -> É Família/Amigo | Z7: =IF(Y7<>"",COUNTIF('Clie-F'!$R$5:$R$6400,Y7),"") -> 6
B8: Casado(a) | C8: =COUNTIF('Clie-F'!$Q$5:$Q$9999,'C-Das1'!B8) -> 20 | D8: =C8/SUM($C$7:$C$11) -> 0.66666667 | P8: Homem | Q8: =COUNTIF('Clie-F'!$F$5:$F$6400,"M") -> 20 | R8: =Q8/SUM(Q8:Q9) -> 0.60606061 | W8: AP | X8: =COUNTIF('Clie-F'!$O$5:$O$6400,'C-Das1'!W8) -> 0 | Y8: =IF('Conf-C'!B7<>"",'Conf-C'!B7,"") -> Google | Z8: =IF(Y8<>"",COUNTIF('Clie-F'!$R$5:$R$6400,Y8),"") -> 0
B9: Separado(a) | C9: =COUNTIF('Clie-F'!$Q$5:$Q$9999,'C-Das1'!B9) -> 0 | D9: =C9/SUM($C$7:$C$11) -> 0 | P9: Mulher | Q9: =COUNTIF('Clie-F'!$F$5:$F$6400,"F") -> 13 | R9: =Q9/SUM(Q8:Q9) -> 0.39393939 | W9: AM | X9: =COUNTIF('Clie-F'!$O$5:$O$6400,'C-Das1'!W9) -> 0 | Y9: =IF('Conf-C'!B8<>"",'Conf-C'!B8,"") -> Indicação | Z9: =IF(Y9<>"",COUNTIF('Clie-F'!$R$5:$R$6400,Y9),"") -> 8
B10: Divorciado(a) | C10: =COUNTIF('Clie-F'!$Q$5:$Q$9999,'C-Das1'!B10) -> 1 | D10: =C10/SUM($C$7:$C$11) -> 0.033333333 | W10: BA | X10: =COUNTIF('Clie-F'!$O$5:$O$6400,'C-Das1'!W10) -> 0 | Y10: =IF('Conf-C'!B9<>"",'Conf-C'!B9,"") -> Outros | Z10: =IF(Y10<>"",COUNTIF('Clie-F'!$R$5:$R$6400,Y10),"") -> 13
B11: Viúvo(a) | C11: =COUNTIF('Clie-F'!$Q$5:$Q$9999,'C-Das1'!B11) -> 2 | D11: =C11/SUM($C$7:$C$11) -> 0.066666667 | W11: CE | X11: =COUNTIF('Clie-F'!$O$5:$O$6400,'C-Das1'!W11) -> 0 | Y11: =IF('Conf-C'!B10<>"",'Conf-C'!B10,"") -> Parceria | Z11: =IF(Y11<>"",COUNTIF('Clie-F'!$R$5:$R$6400,Y11),"") -> 6
B12: União Estável | C12: =COUNTIF('Clie-F'!$Q$5:$Q$9999,'C-Das1'!B12) -> 3 | D12: =C12/SUM($C$7:$C$11) -> 0.1 | W12: DF | X12: =COUNTIF('Clie-F'!$O$5:$O$6400,'C-Das1'!W12) -> 0 | Y12: =IF('Conf-C'!B11<>"",'Conf-C'!B11,"") -> Redes Sociais | Z12: =IF(Y12<>"",COUNTIF('Clie-F'!$R$5:$R$6400,Y12),"") -> 0
W13: ES | X13: =COUNTIF('Clie-F'!$O$5:$O$6400,'C-Das1'!W13) -> 0 | Y13: =IF('Conf-C'!B12<>"",'Conf-C'!B12,"") -> Site | Z13: =IF(Y13<>"",COUNTIF('Clie-F'!$R$5:$R$6400,Y13),"") -> 0
B14: CLIENTES TOTAIS POR IDADE | W14: GO | X14: =COUNTIF('Clie-F'!$O$5:$O$6400,'C-Das1'!W14) -> 0 | Y14: =IF('Conf-C'!B12<>"",'Conf-C'!B12,"") -> Site | Z14: =IF(Y14<>"",COUNTIF('Clie-F'!$R$5:$R$6400,Y14),"") -> 0
B15: 0 - 17 | C15: =COUNTIFS('Clie-F'!H5:H9999,"<18") -> 0 | D15: =C15/SUM($C$15:$C$20) -> 0 | W15: MA | X15: =COUNTIF('Clie-F'!$O$5:$O$6400,'C-Das1'!W15) -> 0 | Y15: =IF('Conf-C'!B13<>"",'Conf-C'!B13,"") | Z15: =IF(Y15<>"",COUNTIF('Clie-F'!$R$5:$R$6400,Y15),"") | AA15: =COUNTBLANK(Y6:Y26) -> 12
B16: 18 - 25 | C16: =COUNTIFS('Clie-F'!H5:H9999,">=18",'Clie-F'!H5:H9999,"<26") -> 0 | D16: =C16/SUM($C$15:$C$20) -> 0 | W16: MT | X16: =COUNTIF('Clie-F'!$O$5:$O$6400,'C-Das1'!W16) -> 0 | Y16: =IF('Conf-C'!B14<>"",'Conf-C'!B14,"") | Z16: =IF(Y16<>"",COUNTIF('Clie-F'!$R$5:$R$6400,Y16),"") | AC16: =cont.val -> #NAME?
B17: 26 - 35 | C17: =COUNTIFS('Clie-F'!H5:H9999,">=26",'Clie-F'!H5:H9999,"<36") -> 6 | D17: =C17/SUM($C$15:$C$20) -> 0.1875 | H17: =IF('Conf-G'!D15<>"",'Conf-G'!D15,"") | I17: =IF(H17<>"",COUNTIF('Proc-G'!M17:M409,'C-Das1'!H17),"") | W17: MS | X17: =COUNTIF('Clie-F'!$O$5:$O$6400,'C-Das1'!W17) -> 0 | Y17: =IF('Conf-C'!B15<>"",'Conf-C'!B15,"") | Z17: =IF(Y17<>"",COUNTIF('Clie-F'!$R$5:$R$6400,Y17),"")
B18: 36 - 45 | C18: =COUNTIFS('Clie-F'!H5:H9999,">=36",'Clie-F'!H5:H9999,"<46") -> 11 | D18: =C18/SUM($C$15:$C$20) -> 0.34375 | H18: =IF('Conf-G'!D16<>"",'Conf-G'!D16,"") | I18: =IF(H18<>"",COUNTIF('Proc-G'!M18:M410,'C-Das1'!H18),"") | W18: MG | X18: =COUNTIF('Clie-F'!$O$5:$O$6400,'C-Das1'!W18) -> 0 | Y18: =IF('Conf-C'!B16<>"",'Conf-C'!B16,"") | Z18: =IF(Y18<>"",COUNTIF('Clie-F'!$R$5:$R$6400,Y18),"") | AA18: =ROWS(Y6:Y26) -> 21
B19: 46 - 59 | C19: =COUNTIFS('Clie-F'!H5:H9999,">=46",'Clie-F'!H5:H9999,"<59") -> 10 | D19: =C19/SUM($C$15:$C$20) -> 0.3125 | H19: =IF('Conf-G'!D17<>"",'Conf-G'!D17,"") | I19: =IF(H19<>"",COUNTIF('Proc-G'!M19:M411,'C-Das1'!H19),"") | W19: PA | X19: =COUNTIF('Clie-F'!$O$5:$O$6400,'C-Das1'!W19) -> 0 | Y19: =IF('Conf-C'!B17<>"",'Conf-C'!B17,"") | Z19: =IF(Y19<>"",COUNTIF('Clie-F'!$R$5:$R$6400,Y19),"")
B20: 60+ | C20: =COUNTIFS('Clie-F'!H5:H9999,">=60") -> 5 | D20: =C20/SUM($C$15:$C$20) -> 0.15625 | H20: =IF('Conf-G'!D18<>"",'Conf-G'!D18,"") | I20: =IF(H20<>"",COUNTIF('Proc-G'!M20:M412,'C-Das1'!H20),"") | W20: PB | X20: =COUNTIF('Clie-F'!$O$5:$O$6400,'C-Das1'!W20) -> 0 | Y20: =IF('Conf-C'!B18<>"",'Conf-C'!B18,"") | Z20: =IF(Y20<>"",COUNTIF('Clie-F'!$R$5:$R$6400,Y20),"")
H21: =IF('Conf-G'!D19<>"",'Conf-G'!D19,"") | I21: =IF(H21<>"",COUNTIF('Proc-G'!M21:M413,'C-Das1'!H21),"") | W21: PR | X21: =COUNTIF('Clie-F'!$O$5:$O$6400,'C-Das1'!W21) -> 0 | Y21: =IF('Conf-C'!B19<>"",'Conf-C'!B19,"") | Z21: =IF(Y21<>"",COUNTIF('Clie-F'!$R$5:$R$6400,Y21),"")
H22: =IF('Conf-G'!D20<>"",'Conf-G'!D20,"") | I22: =IF(H22<>"",COUNTIF('Proc-G'!M22:M414,'C-Das1'!H22),"") | W22: PE | X22: =COUNTIF('Clie-F'!$O$5:$O$6400,'C-Das1'!W22) -> 0 | Y22: =IF('Conf-C'!B20<>"",'Conf-C'!B20,"") | Z22: =IF(Y22<>"",COUNTIF('Clie-F'!$R$5:$R$6400,Y22),"")
H23: =IF('Conf-G'!D21<>"",'Conf-G'!D21,"") | I23: =IF(H23<>"",COUNTIF('Proc-G'!M23:M415,'C-Das1'!H23),"") | W23: PI | X23: =COUNTIF('Clie-F'!$O$5:$O$6400,'C-Das1'!W23) -> 0 | Y23: =IF('Conf-C'!B21<>"",'Conf-C'!B21,"") | Z23: =IF(Y23<>"",COUNTIF('Clie-F'!$R$5:$R$6400,Y23),"")
H24: =IF('Conf-G'!D22<>"",'Conf-G'!D22,"") | I24: =IF(H24<>"",COUNTIF('Proc-G'!M24:M416,'C-Das1'!H24),"") | W24: RJ | X24: =COUNTIF('Clie-F'!$O$5:$O$6400,'C-Das1'!W24) -> 0 | Y24: =IF('Conf-C'!B22<>"",'Conf-C'!B22,"") | Z24: =IF(Y24<>"",COUNTIF('Clie-F'!$R$5:$R$6400,Y24),"")
W25: RN | X25: =COUNTIF('Clie-F'!$O$5:$O$6400,'C-Das1'!W25) -> 0 | Y25: =IF('Conf-C'!B23<>"",'Conf-C'!B23,"") | Z25: =IF(Y25<>"",COUNTIF('Clie-F'!$R$5:$R$6400,Y25),"")
W26: RS | X26: =COUNTIF('Clie-F'!$O$5:$O$6400,'C-Das1'!W26) -> 0 | Y26: =IF('Conf-C'!B24<>"",'Conf-C'!B24,"") | Z26: =IF(Y26<>"",COUNTIF('Clie-F'!$R$5:$R$6400,Y26),"")
W27: RO | X27: =COUNTIF('Clie-F'!$O$5:$O$6400,'C-Das1'!W27) -> 0 | Y27: =IF('Conf-C'!B25<>"",'Conf-C'!B25,"") | Z27: =IF(Y27<>"",COUNTIF('Clie-F'!$R$5:$R$6400,Y27),"")
W28: RR | X28: =COUNTIF('Clie-F'!$O$5:$O$6400,'C-Das1'!W28) -> 0 | Y28: =IF('Conf-C'!B26<>"",'Conf-C'!B26,"") | Z28: =IF(Y28<>"",COUNTIF('Clie-F'!$R$5:$R$6400,Y28),"")
W29: SC | X29: =COUNTIF('Clie-F'!$O$5:$O$6400,'C-Das1'!W29) -> 0 | Y29: =IF('Conf-C'!B27<>"",'Conf-C'!B27,"") | Z29: =IF(Y29<>"",COUNTIF('Clie-F'!$R$5:$R$6400,Y29),"")
W30: SP | X30: =COUNTIF('Clie-F'!$O$5:$O$6400,'C-Das1'!W30) -> 33 | Y30: =IF('Conf-C'!B28<>"",'Conf-C'!B28,"") | Z30: =IF(Y30<>"",COUNTIF('Clie-F'!$R$5:$R$6400,Y30),"")
W31: SE | X31: =COUNTIF('Clie-F'!$O$5:$O$6400,'C-Das1'!W31) -> 0 | Y31: =IF('Conf-C'!B29<>"",'Conf-C'!B29,"") | Z31: =IF(Y31<>"",COUNTIF('Clie-F'!$R$5:$R$6400,Y31),"")
W32: TO | X32: =COUNTIF('Clie-F'!$O$5:$O$6400,'C-Das1'!W32) -> 0 | Y32: =IF('Conf-C'!B30<>"",'Conf-C'!B30,"") | Z32: =IF(Y32<>"",COUNTIF('Clie-F'!$R$5:$R$6400,Y32),"")
W33: Exterior | X33: =COUNTIF('Clie-F'!$O$5:$O$6400,'C-Das1'!W33) -> 0
C34: =IF('Conf-G'!D23<>"",'Conf-G'!D23,"") | D34: =IF(C34<>"",COUNTIF('Proc-G'!M25:M417,'C-Das1'!C34),"")
C35: =IF('Conf-G'!D24<>"",'Conf-G'!D24,"") | D35: =IF(C35<>"",COUNTIF('Proc-G'!M26:M418,'C-Das1'!C35),"")
C36: =IF('Conf-G'!D25<>"",'Conf-G'!D25,"")
C37: =IF('Conf-G'!D26<>"",'Conf-G'!D26,"")
C38: =IF('Conf-G'!D27<>"",'Conf-G'!D27,"")

Sheet C-Das2
V5: =COUNTA('Clie-F'!D5:D400) -> 33
V6: =COUNTA('Clie-J'!C5:C400) -> 24 | W6: AC | X6: =COUNTIF('Clie-J'!$L$5:$L$400,'C-Das2'!W6) -> 0 | Y6: =IF('Conf-C'!B5<>"",'Conf-C'!B5,"") -> Anúncio | Z6: =IF(Y6<>"",COUNTIF('Clie-J'!$O$5:$O$400,Y6),"") -> 0 | AB6: =IF('Conf-C'!D5<>"",'Conf-C'!D5,"") -> Agronegócio | AC6: =IF(AB6<>"",COUNTIF('Clie-J'!$M$5:$M$400,AB6),"") -> 1 | AD6: =COUNTBLANK(AB6:AB80) -> 49
V7: =SUM(V5:V6) -> 57 | W7: AL | X7: =COUNTIF('Clie-J'!$L$5:$L$400,'C-Das2'!W7) -> 0 | Y7: =IF('Conf-C'!B6<>"",'Conf-C'!B6,"") -> É Família/Amigo | Z7: =IF(Y7<>"",COUNTIF('Clie-J'!$O$5:$O$400,Y7),"") -> 5 | AB7: =IF('Conf-C'!D6<>"",'Conf-C'!D6,"") -> Alimentos e Bebidas | AC7: =IF(AB7<>"",COUNTIF('Clie-J'!$M$5:$M$400,AB7),"") -> 0 | AD7: =ROWS(AB6:AB80) -> 75
W8: AP | X8: =COUNTIF('Clie-J'!$L$5:$L$400,'C-Das2'!W8) -> 0 | Y8: =IF('Conf-C'!B7<>"",'Conf-C'!B7,"") -> Google | Z8: =IF(Y8<>"",COUNTIF('Clie-J'!$O$5:$O$400,Y8),"") -> 0 | AB8: =IF('Conf-C'!D7<>"",'Conf-C'!D7,"") -> Arquitetura | AC8: =IF(AB8<>"",COUNTIF('Clie-J'!$M$5:$M$400,AB8),"") -> 0
W9: AM | X9: =COUNTIF('Clie-J'!$L$5:$L$400,'C-Das2'!W9) -> 0 | Y9: =IF('Conf-C'!B8<>"",'Conf-C'!B8,"") -> Indicação | Z9: =IF(Y9<>"",COUNTIF('Clie-J'!$O$5:$O$400,Y9),"") -> 6 | AB9: =IF('Conf-C'!D8<>"",'Conf-C'!D8,"") -> Atacado e Distribuição | AC9: =IF(AB9<>"",COUNTIF('Clie-J'!$M$5:$M$400,AB9),"") -> 0
W10: BA | X10: =COUNTIF('Clie-J'!$L$5:$L$400,'C-Das2'!W10) -> 0 | Y10: =IF('Conf-C'!B9<>"",'Conf-C'!B9,"") -> Outros | Z10: =IF(Y10<>"",COUNTIF('Clie-J'!$O$5:$O$400,Y10),"") -> 13 | AB10: =IF('Conf-C'!D9<>"",'Conf-C'!D9,"") -> Bebidas | AC10: =IF(AB10<>"",COUNTIF('Clie-J'!$M$5:$M$400,AB10),"") -> 0
W11: CE | X11: =COUNTIF('Clie-J'!$L$5:$L$400,'C-Das2'!W11) -> 0 | Y11: =IF('Conf-C'!B10<>"",'Conf-C'!B10,"") -> Parceria | Z11: =IF(Y11<>"",COUNTIF('Clie-J'!$O$5:$O$400,Y11),"") -> 0 | AB11: =IF('Conf-C'!D10<>"",'Conf-C'!D10,"") -> Beleza | AC11: =IF(AB11<>"",COUNTIF('Clie-J'!$M$5:$M$400,AB11),"") -> 0
W12: DF | X12: =COUNTIF('Clie-J'!$L$5:$L$400,'C-Das2'!W12) -> 0 | Y12: =IF('Conf-C'!B11<>"",'Conf-C'!B11,"") -> Redes Sociais | Z12: =IF(Y12<>"",COUNTIF('Clie-J'!$O$5:$O$400,Y12),"") -> 0 | AB12: =IF('Conf-C'!D11<>"",'Conf-C'!D11,"") -> Cartório | AC12: =IF(AB12<>"",COUNTIF('Clie-J'!$M$5:$M$400,AB12),"") -> 0
